{
 "updated": "2026-07-24T03:49:56.164561+00:00",
 "total": 109,
 "countries": [
  {
   "name": "United States",
   "es": "Estados Unidos",
   "lat": 39.8,
   "lon": -98.6,
   "count": 26,
   "items": [
    {
     "title": "Nobel economist on anti-China, anti-science US, AI’s risks",
     "link": "https://www.scmp.com/plus/economy/china-economy/article/3361667/nobel-economist-anti-china-anti-science-us-ais-risks?utm_source=rss_feed",
     "source": "News - South China Morning Post",
     "image": "https://cdn.i-scmp.com/sites/default/files/styles/1280x720/public/d8/images/canvas/2026/07/24/2fb3f803-7c2a-473b-bfbd-1660f1d90c61_b72935e2.jpg?itok=tE5eflON&v=1784860317",
     "ts": 1784863982000,
     "beat": "china",
     "beatName": "China"
    },
    {
     "title": "Iran war: US launches new strikes over shipping routes threat",
     "link": "https://www.dw.com/en/iran-war-us-launches-new-strikes-over-shipping-routes-threat/live-78093040?maca=en-rss-en-all-1573-rdf",
     "source": "Deutsche Welle",
     "image": "",
     "ts": 1784862720000,
     "beat": "actualidad",
     "beatName": "Actualidad Global"
    },
    {
     "title": "EE.UU. sanciona a presunto jefe del Cártel Jalisco Nueva Generación",
     "link": "https://www.dw.com/es/ee-uu-sanciona-a-presunto-jefe-del-cártel-jalisco-nueva-generación/a-78093036?maca=spa-rss-sp-all-1122-rdf",
     "source": "Deutsche Welle: DW.COM Spanish",
     "image": "",
     "ts": 1784861100000,
     "beat": "panama_latam",
     "beatName": "Panamá · LatAm"
    },
    {
     "title": "HSBC agrees to US$2 billion deal to sell Singapore insurance branch to Allianz",
     "link": "https://www.scmp.com/business/companies/article/3361669/hsbc-agrees-us2-billion-deal-sell-singapore-insurance-branch-allianz?utm_source=rss_feed",
     "source": "News - South China Morning Post",
     "image": "https://cdn.i-scmp.com/sites/default/files/styles/1280x720/public/d8/images/canvas/2026/07/24/4092a638-f375-4749-9f6f-1f273748af9d_c982ef0b.jpg?itok=CRlqLOFc&v=1784860710",
     "ts": 1784860711000,
     "beat": "china",
     "beatName": "China"
    },
    {
     "title": "Middle East live: US launches new strikes on Iran as oil prices skyrocket",
     "link": "https://www.france24.com/en/middle-east/20260724-middle-east-live-us-launches-new-strikes-on-iran-as-oil-prices-skyrocket",
     "source": "Latest news from the Middle East, daily international news reports - France 24",
     "image": "https://s.france24.com/media/display/28a9aede-8703-11f1-a60d-005056a90284/w:1024/p:16x9/000-C2Y62NR.jpg",
     "ts": 1784860637000,
     "beat": "medio_oriente",
     "beatName": "Medio Oriente"
    },
    {
     "title": "US launches 13th night of strikes as Iran warns of escalation in the Gulf",
     "link": "https://www.aljazeera.com/video/newsfeed/2026/7/24/us-launches-13th-night-of-strikes-as-iran-warns-of-escalation-in-the-gulf?traffic_source=rss",
     "source": "Al Jazeera – Breaking News, World News and Video from Al Jazeera",
     "image": "",
     "ts": 1784859941000,
     "beat": "actualidad",
     "beatName": "Actualidad Global"
    },
    {
     "title": "Australia ramps up Aukus funding with US$3.2 billion for nuclear submarine yard",
     "link": "https://www.scmp.com/news/asia/australasia/article/3361665/australia-ramps-aukus-funding-us32-billion-nuclear-submarine-yard?utm_source=rss_feed",
     "source": "News - South China Morning Post",
     "image": "https://cdn.i-scmp.com/sites/default/files/styles/1280x720/public/d8/images/canvas/2026/07/24/dd718ead-13ed-4075-ab11-576f5dbe23bf_8e434a47.jpg?itok=sSbvBGMT&v=1784859592",
     "ts": 1784859593000,
     "beat": "china",
     "beatName": "China"
    },
    {
     "title": "US imposes tariffs on dozens of trade partners over 'forced labour' imports",
     "link": "https://www.bbc.co.uk/news/articles/cvgj61j6l08o?at_medium=RSS&at_campaign=rss",
     "source": "BBC News",
     "image": "https://ichef.bbci.co.uk/ace/standard/240/cpsprodpb/02b7/live/fa2c0bc0-86b1-11f1-bb58-d3ffca85db6d.jpg",
     "ts": 1784859000000,
     "beat": "actualidad",
     "beatName": "Actualidad Global"
    },
    {
     "title": "US court affirms release of pro-Palestine scholar as legal battle continues",
     "link": "https://www.aljazeera.com/news/2026/7/24/us-court-affirms-release-of-pro-palestine-scholar-as-legal-battle-continues?traffic_source=rss",
     "source": "Al Jazeera – Breaking News, World News and Video from Al Jazeera",
     "image": "",
     "ts": 1784858775000,
     "beat": "actualidad",
     "beatName": "Actualidad Global"
    },
    {
     "title": "Ukraine’s Zelenskyy meets with far-right US activist Laura Loomer",
     "link": "https://www.aljazeera.com/news/2026/7/24/ukraine-zelenskyy-meets-with-trump-ally-laura-loomer?traffic_source=rss",
     "source": "Al Jazeera – Breaking News, World News and Video from Al Jazeera",
     "image": "",
     "ts": 1784857767000,
     "beat": "actualidad",
     "beatName": "Actualidad Global"
    }
   ]
  },
  {
   "name": "Iran",
   "es": "Irán",
   "lat": 32.4,
   "lon": 53.7,
   "count": 15,
   "items": [
    {
     "title": "Cuál es la importancia del estrecho de Bab el-Mandeb, la estratégica ruta marítima del mar Rojo amenazada por los hutíes con el respaldo de Irán",
     "link": "https://www.bbc.com/mundo/articles/cdewk1ek4eeo?at_medium=RSS&at_campaign=rss",
     "source": "BBC Mundo",
     "image": "https://ichef.bbci.co.uk/ace/ws/240/cpsprodpb/3d2a/live/b6b4c110-2c49-11f1-b979-37139b7cb8c6.jpg",
     "ts": 1784864761000,
     "beat": "panama_latam",
     "beatName": "Panamá · LatAm"
    },
    {
     "title": "Mientras el mundo mira a Irán, la guerra en Ucrania entra en una nueva fase",
     "link": "https://www.prensa.com/opinion/mientras-el-mundo-mira-a-iran-la-guerra-en-ucrania-entra-en-una-nueva-fase/",
     "source": "La Prensa",
     "image": "https://www.prensa.com/resizer/v2/7YASYF5XYRHS5CN5JJXUADCZOQ.jpg?auth=94e00e097a3a98adb8ce3f9de27859271365e3a91e0148a92cc83babf3657213&smart=true&width=3492&height=1964",
     "ts": 1784863800000,
     "beat": "panama_latam",
     "beatName": "Panamá · LatAm"
    },
    {
     "title": "Iran war: US launches new strikes over shipping routes threat",
     "link": "https://www.dw.com/en/iran-war-us-launches-new-strikes-over-shipping-routes-threat/live-78093040?maca=en-rss-en-all-1573-rdf",
     "source": "Deutsche Welle",
     "image": "",
     "ts": 1784862720000,
     "beat": "actualidad",
     "beatName": "Actualidad Global"
    },
    {
     "title": "Middle East live: US launches new strikes on Iran as oil prices skyrocket",
     "link": "https://www.france24.com/en/middle-east/20260724-middle-east-live-us-launches-new-strikes-on-iran-as-oil-prices-skyrocket",
     "source": "Latest news from the Middle East, daily international news reports - France 24",
     "image": "https://s.france24.com/media/display/28a9aede-8703-11f1-a60d-005056a90284/w:1024/p:16x9/000-C2Y62NR.jpg",
     "ts": 1784860637000,
     "beat": "medio_oriente",
     "beatName": "Medio Oriente"
    },
    {
     "title": "US launches 13th night of strikes as Iran warns of escalation in the Gulf",
     "link": "https://www.aljazeera.com/video/newsfeed/2026/7/24/us-launches-13th-night-of-strikes-as-iran-warns-of-escalation-in-the-gulf?traffic_source=rss",
     "source": "Al Jazeera – Breaking News, World News and Video from Al Jazeera",
     "image": "",
     "ts": 1784859941000,
     "beat": "actualidad",
     "beatName": "Actualidad Global"
    },
    {
     "title": "Pentagon list of service members killed in Iran war removes most recent four",
     "link": "https://www.theguardian.com/us-news/2026/jul/23/pentagon-service-members-killed-iran",
     "source": "World news | The Guardian",
     "image": "https://i.guim.co.uk/img/media/feded9a3ee9adb4c41c167da54cd36b605b26b00/3_0_7200_5760/master/7200.jpg?width=140&quality=85&auto=format&fit=max&s=b44db195f76f3afc3debd4bb4c0f3c89",
     "ts": 1784857787000,
     "beat": "actualidad",
     "beatName": "Actualidad Global"
    },
    {
     "title": "Analyst: voting against Iran war funding a tough sell for Congress",
     "link": "https://www.aljazeera.com/video/newsfeed/2026/7/24/analyst-voting-against-iran-war-funding-a-tough-sell-for-congress?traffic_source=rss",
     "source": "Al Jazeera – Breaking News, World News and Video from Al Jazeera",
     "image": "",
     "ts": 1784853043000,
     "beat": "actualidad",
     "beatName": "Actualidad Global"
    },
    {
     "title": "Trump threatens Iran and Houthi rebels with 'major military punishment'",
     "link": "https://www.france24.com/en/middle-east/20260723-trump-threatens-iran-and-houthi-rebels-with-major-military-punishment",
     "source": "Latest news from the Middle East, daily international news reports - France 24",
     "image": "https://s.france24.com/media/display/669a0bb4-867f-11f1-bc8a-005056a90284/w:1024/p:16x9/9cf489352df1b19309121efdf4c467be9adf5d68.jpg",
     "ts": 1784850848000,
     "beat": "medio_oriente",
     "beatName": "Medio Oriente"
    },
    {
     "title": "Donald Trump says decision on ‘massive attack’ against Iran is close",
     "link": "https://www.theguardian.com/world/2026/jul/23/trump-says-he-is-close-to-decision-on-largest-yet-attack-on-iran",
     "source": "Middle East and north Africa | The Guardian",
     "image": "https://i.guim.co.uk/img/media/ef5928b90349e9fb0c3814aef2e08c202e498226/360_468_2976_2381/master/2976.jpg?width=140&quality=85&auto=format&fit=max&s=e65e84d2b2d65cb6d36ce6142b5d2962",
     "ts": 1784825905000,
     "beat": "medio_oriente",
     "beatName": "Medio Oriente"
    },
    {
     "title": "Why Iran is targeting Kuwait's desalination plants as part of its war strategy",
     "link": "https://www.france24.com/en/middle-east/20260723-why-iran-targeting-kuwaits-desalination-plants",
     "source": "Latest news from the Middle East, daily international news reports - France 24",
     "image": "https://s.france24.com/media/display/c6ab2b0e-85ea-11f1-a430-005056bfb2b6/w:1024/p:16x9/2026-07-21T135520Z-950614241-RC2DIMA49QH1-RTRMADP-3-IRAN-CRISIS-KUWAIT.jpg",
     "ts": 1784825598000,
     "beat": "medio_oriente",
     "beatName": "Medio Oriente"
    }
   ]
  },
  {
   "name": "China",
   "es": "China",
   "lat": 35.9,
   "lon": 104.2,
   "count": 13,
   "items": [
    {
     "title": "Nobel economist on anti-China, anti-science US, AI’s risks",
     "link": "https://www.scmp.com/plus/economy/china-economy/article/3361667/nobel-economist-anti-china-anti-science-us-ais-risks?utm_source=rss_feed",
     "source": "News - South China Morning Post",
     "image": "https://cdn.i-scmp.com/sites/default/files/styles/1280x720/public/d8/images/canvas/2026/07/24/2fb3f803-7c2a-473b-bfbd-1660f1d90c61_b72935e2.jpg?itok=tE5eflON&v=1784860317",
     "ts": 1784863982000,
     "beat": "china",
     "beatName": "China"
    },
    {
     "title": "Monkeying around disrupts Hong Kong MTR services for second day in row",
     "link": "https://www.scmp.com/news/hong-kong/transport/article/3361670/monkeying-around-disrupts-hong-kong-mtr-services-second-day-row?utm_source=rss_feed",
     "source": "News - South China Morning Post",
     "image": "https://cdn.i-scmp.com/sites/default/files/styles/1280x720/public/d8/images/canvas/2026/07/24/90d71484-f941-4231-a4bc-f12916744574_67d9d931.jpg?itok=Drr5XHBk&v=1784861549",
     "ts": 1784861426000,
     "beat": "china",
     "beatName": "China"
    },
    {
     "title": "Typhoon Noul to come closest to Hong Kong late Saturday into Sunday",
     "link": "https://www.scmp.com/news/hong-kong/health-environment/article/3361668/typhoon-noul-come-closest-hong-kong-late-saturday-sunday?utm_source=rss_feed",
     "source": "News - South China Morning Post",
     "image": "https://cdn.i-scmp.com/sites/default/files/styles/1280x720/public/d8/images/canvas/2026/07/24/ccbe7d7f-6f57-4b67-b3a4-ffe83ae31b50_e9ae740d.jpg?itok=EwENbcuf&v=1784860669",
     "ts": 1784860673000,
     "beat": "china",
     "beatName": "China"
    },
    {
     "title": "Hong Kong must wake up to the cold hard geopolitics of AI",
     "link": "https://www.scmp.com/opinion/hong-kong-opinion/article/3361470/hong-kong-must-wake-cold-hard-geopolitics-ai?utm_source=rss_feed",
     "source": "News - South China Morning Post",
     "image": "https://cdn.i-scmp.com/sites/default/files/styles/1280x720/public/d8/images/canvas/2026/07/23/b432acbb-75b8-4a44-a107-66aefd4ad9f8_cfdb9e94.jpg?itok=3mZbeE14&v=1784786127",
     "ts": 1784856609000,
     "beat": "china",
     "beatName": "China"
    },
    {
     "title": "Chinese nationals plead guilty to illegally shipping turtles from US to Hong Kong",
     "link": "https://www.scmp.com/news/china/diplomacy/article/3361661/chinese-nationals-plead-guilty-illegally-shipping-turtles-us-hong-kong?utm_source=rss_feed",
     "source": "News - South China Morning Post",
     "image": "https://cdn.i-scmp.com/sites/default/files/styles/1280x720/public/d8/images/canvas/2026/07/24/3823e321-e59f-413e-8126-38456551cfc6_a5cc6a00.jpg?itok=UohjIx1S&v=1784856605",
     "ts": 1784856607000,
     "beat": "china",
     "beatName": "China"
    },
    {
     "title": "Why the divorces of China’s A-share firm owners provoke market nerves",
     "link": "https://www.scmp.com/business/china-business/article/3361656/why-divorces-chinas-share-firm-owners-provoke-market-nerves?utm_source=rss_feed",
     "source": "News - South China Morning Post",
     "image": "https://cdn.i-scmp.com/sites/default/files/styles/1280x720/public/d8/images/canvas/2026/07/24/1c49ef12-d154-4e94-b140-65d74c6cd24b_6eec6e06.jpg?itok=hBulBgWY&v=1784853364",
     "ts": 1784854818000,
     "beat": "china",
     "beatName": "China"
    },
    {
     "title": "China targets new space-based computing network to process data born in orbit",
     "link": "https://www.scmp.com/news/china/science/article/3361559/china-targets-new-space-based-computing-network-process-data-born-orbit?utm_source=rss_feed",
     "source": "News - South China Morning Post",
     "image": "https://cdn.i-scmp.com/sites/default/files/styles/1280x720/public/d8/images/canvas/2026/07/23/7e6f624c-2ae7-4c1e-9481-1f42035608e8_a0ee17f5.jpg?itok=f2V16N4m&v=1784785991",
     "ts": 1784854809000,
     "beat": "china",
     "beatName": "China"
    },
    {
     "title": "More Americans think China is world leader in AI, new survey reveals",
     "link": "https://www.scmp.com/news/china/diplomacy/article/3361654/more-americans-think-china-world-leader-ai-new-survey-reveals?utm_source=rss_feed",
     "source": "News - South China Morning Post",
     "image": "https://cdn.i-scmp.com/sites/default/files/styles/1280x720/public/d8/images/canvas/2026/07/24/4231efd7-8433-4455-9833-2a3dbfa3dddb_f8434388.jpg?itok=Rfm08Lbc&v=1784848877",
     "ts": 1784848884000,
     "beat": "china",
     "beatName": "China"
    },
    {
     "title": "How scholar Ackbar Abbas changed the way people thought about Hong Kong",
     "link": "https://www.scmp.com/lifestyle/arts/article/3361422/how-scholar-ackbar-abbas-changed-way-people-thought-about-hong-kong?utm_source=rss_feed",
     "source": "News - South China Morning Post",
     "image": "https://cdn.i-scmp.com/sites/default/files/styles/1280x720/public/d8/images/canvas/2026/07/23/8a89cbba-d6a5-4ba5-b1e1-75ab9c508f72_0b90259c.jpg?itok=22rRHFml&v=1784782252",
     "ts": 1784848506000,
     "beat": "china",
     "beatName": "China"
    },
    {
     "title": "US slaps fresh tariffs on China, 50-plus countries in latest wave",
     "link": "https://www.scmp.com/news/us/diplomacy/article/3361650/us-slaps-fresh-tariffs-china-50-plus-countries-latest-wave?utm_source=rss_feed",
     "source": "News - South China Morning Post",
     "image": "https://cdn.i-scmp.com/sites/default/files/styles/1280x720/public/d8/images/canvas/2026/07/24/392b1f5c-8695-4f18-b2d4-2dd583346bb9_b00fabaf.jpg?itok=ol87IVXQ&v=1784843780",
     "ts": 1784843029000,
     "beat": "china",
     "beatName": "China"
    }
   ]
  },
  {
   "name": "Yemen",
   "es": "Yemen",
   "lat": 15.6,
   "lon": 48.0,
   "count": 10,
   "items": [
    {
     "title": "Cuál es la importancia del estrecho de Bab el-Mandeb, la estratégica ruta marítima del mar Rojo amenazada por los hutíes con el respaldo de Irán",
     "link": "https://www.bbc.com/mundo/articles/cdewk1ek4eeo?at_medium=RSS&at_campaign=rss",
     "source": "BBC Mundo",
     "image": "https://ichef.bbci.co.uk/ace/ws/240/cpsprodpb/3d2a/live/b6b4c110-2c49-11f1-b979-37139b7cb8c6.jpg",
     "ts": 1784864761000,
     "beat": "panama_latam",
     "beatName": "Panamá · LatAm"
    },
    {
     "title": "As oil soars, experts watch Red Sea tankers for clarity on Houthi blockade",
     "link": "https://www.aljazeera.com/economy/2026/7/24/as-oil-soars-experts-watch-red-sea-tankers-for-clarity-on-houthi-blockade?traffic_source=rss",
     "source": "Al Jazeera – Breaking News, World News and Video from Al Jazeera",
     "image": "",
     "ts": 1784864050000,
     "beat": "actualidad",
     "beatName": "Actualidad Global"
    },
    {
     "title": "Houthi attacks raise fears of wider Middle East conflict and more global economic damage",
     "link": "https://www.bbc.co.uk/news/articles/cvgve0vxy1yo?at_medium=RSS&at_campaign=rss",
     "source": "BBC News",
     "image": "https://ichef.bbci.co.uk/ace/standard/240/cpsprodpb/39c0/live/60bb5b90-86b5-11f1-bb58-d3ffca85db6d.jpg",
     "ts": 1784858389000,
     "beat": "actualidad",
     "beatName": "Actualidad Global"
    },
    {
     "title": "Houthi attacks raise fears of wider Middle East conflict and more global economic damage",
     "link": "https://www.bbc.co.uk/news/articles/cvgve0vxy1yo?at_medium=RSS&at_campaign=rss",
     "source": "BBC News",
     "image": "https://ichef.bbci.co.uk/ace/standard/240/cpsprodpb/39c0/live/60bb5b90-86b5-11f1-bb58-d3ffca85db6d.jpg",
     "ts": 1784858389000,
     "beat": "medio_oriente",
     "beatName": "Medio Oriente"
    },
    {
     "title": "Los hutíes de Yemen cumplen su amenaza y reivindican un ataque a petroleros saudíes en el mar Rojo",
     "link": "https://elpais.com/internacional/2026-07-23/los-huties-de-yemen-ejecutan-su-amenaza-y-atacan-a-petroleros-saudies-en-el-mar-rojo.html",
     "source": "EL PAÍS Edición América: el periódico global",
     "image": "https://imagenes.elpais.com/resizer/v2/MYWPGI4VRVCZ3O5LJP3NPHWKCM.JPG?auth=752f28d16873db0b14378515797d0cf7ffd4e32871d7c52d75a8f0529224aa2a",
     "ts": 1784853279000,
     "beat": "panama_latam",
     "beatName": "Panamá · LatAm"
    },
    {
     "title": "UN envoy for Yemen ‘alarmed’ by Houthis’ Red Sea attacks, calls for talks",
     "link": "https://www.aljazeera.com/news/2026/7/24/un-envoy-for-yemen-alarmed-by-houthis-red-sea-attacks-calls-for-talks?traffic_source=rss",
     "source": "Al Jazeera – Breaking News, World News and Video from Al Jazeera",
     "image": "",
     "ts": 1784851405000,
     "beat": "actualidad",
     "beatName": "Actualidad Global"
    },
    {
     "title": "Trump threatens Iran and Houthi rebels with 'major military punishment'",
     "link": "https://www.france24.com/en/middle-east/20260723-trump-threatens-iran-and-houthi-rebels-with-major-military-punishment",
     "source": "Latest news from the Middle East, daily international news reports - France 24",
     "image": "https://s.france24.com/media/display/669a0bb4-867f-11f1-bc8a-005056a90284/w:1024/p:16x9/9cf489352df1b19309121efdf4c467be9adf5d68.jpg",
     "ts": 1784850848000,
     "beat": "medio_oriente",
     "beatName": "Medio Oriente"
    },
    {
     "title": "Yemen's Houthis attack Saudi tanker as US launches more Iran strikes",
     "link": "https://www.bbc.co.uk/news/articles/cpw9xzx9r4ko?at_medium=RSS&at_campaign=rss",
     "source": "BBC News",
     "image": "https://ichef.bbci.co.uk/ace/standard/240/cpsprodpb/cf38/live/90c9e750-8676-11f1-b976-0b9c15b0ccfc.jpg",
     "ts": 1784825459000,
     "beat": "medio_oriente",
     "beatName": "Medio Oriente"
    },
    {
     "title": "Middle East war's economic impact 'could get worse' if Houthis join in",
     "link": "https://www.france24.com/en/middle-east-war-s-economic-impact-could-get-worse-if-houthis-join-in",
     "source": "Latest news from the Middle East, daily international news reports - France 24",
     "image": "https://s.france24.com/media/display/80ddc394-818e-11f1-9a7b-005056bfb2b6/w:1024/p:16x9/capture-1837471216a599f8ecf1ee9-86829095.jpg",
     "ts": 1784816630000,
     "beat": "medio_oriente",
     "beatName": "Medio Oriente"
    },
    {
     "title": "How Houthi strikes on oil tankers will impact the Middle East war",
     "link": "https://www.france24.com/en/how-houthi-strikes-on-oil-tankers-will-impact-the-middle-east-war",
     "source": "Latest news from the Middle East, daily international news reports - France 24",
     "image": "https://s.france24.com/media/display/b1b9d426-8436-11f1-9437-005056a90284/w:1024/p:16x9/2026-07-15T122836Z-97536865-RC20HKAGF0XM-RTRMADP-3-IRAN-CRISIS-YEMEN-RED-SEA.jpg",
     "ts": 1784809645000,
     "beat": "medio_oriente",
     "beatName": "Medio Oriente"
    }
   ]
  },
  {
   "name": "Israel",
   "es": "Israel",
   "lat": 31.0,
   "lon": 34.9,
   "count": 6,
   "items": [
    {
     "title": "Japanese militant who took part in 1972 Israel airport attack dies in Beirut",
     "link": "https://www.scmp.com/news/world/middle-east/article/3361679/japanese-militant-who-took-part-1972-israel-airport-attack-dies-beirut?utm_source=rss_feed",
     "source": "News - South China Morning Post",
     "image": "https://cdn.i-scmp.com/sites/default/files/styles/1280x720/public/d8/images/canvas/2026/07/24/a2a42246-3a94-4b25-8be9-dab4816b047d_aec588a0.jpg?itok=F6X2esHo&v=1784864374",
     "ts": 1784864375000,
     "beat": "china",
     "beatName": "China"
    },
    {
     "title": "Israel bombs Gaza after displacement orders, kills two Palestinians",
     "link": "https://www.aljazeera.com/news/2026/7/24/israel-bombs-gaza-after-displacement-orders-kills-two-palestinians?traffic_source=rss",
     "source": "Al Jazeera – Breaking News, World News and Video from Al Jazeera",
     "image": "",
     "ts": 1784852948000,
     "beat": "actualidad",
     "beatName": "Actualidad Global"
    },
    {
     "title": "Trump throws newly signed Saudi nuclear deal into doubt with Israel recognition demand",
     "link": "https://www.scmp.com/news/us/diplomacy/article/3361652/trump-throws-newly-signed-saudi-nuclear-deal-doubt-israel-recognition-demand?utm_source=rss_feed",
     "source": "News - South China Morning Post",
     "image": "https://cdn.i-scmp.com/sites/default/files/styles/1280x720/public/d8/images/canvas/2026/07/24/6e16d6aa-b93a-47cc-b571-c8a5382c617d_24366d8e.jpg?itok=Elx-8mx_&v=1784844069",
     "ts": 1784844071000,
     "beat": "china",
     "beatName": "China"
    },
    {
     "title": "Trump stuns Saudis by pinning nuclear deal to Israel ties",
     "link": "https://www.france24.com/en/trump-stuns-saudis-by-pinning-nuclear-deal-to-israel-ties",
     "source": "Latest news from the Middle East, daily international news reports - France 24",
     "image": "https://s.france24.com/media/display/63de934a-c4dd-11f0-a1c1-005056a97e36/w:1024/p:16x9/AP25322654314785.jpg",
     "ts": 1784831048000,
     "beat": "medio_oriente",
     "beatName": "Medio Oriente"
    },
    {
     "title": "Saudis must recognise Israel for nuclear deal, says Trump",
     "link": "https://www.bbc.co.uk/news/articles/cwye71yq8wwo?at_medium=RSS&at_campaign=rss",
     "source": "BBC News",
     "image": "https://ichef.bbci.co.uk/ace/standard/240/cpsprodpb/3939/live/be2c4e20-86a0-11f1-926f-c90d1bcfbc84.jpg",
     "ts": 1784829482000,
     "beat": "medio_oriente",
     "beatName": "Medio Oriente"
    },
    {
     "title": "Trump says Saudi nuclear deal contingent on Riyadh normalising relations with Israel",
     "link": "https://www.france24.com/en/middle-east/20260723-trump-stuns-saudis-by-pinning-nuclear-deal-to-israel-ties",
     "source": "Latest news from the Middle East, daily international news reports - France 24",
     "image": "https://s.france24.com/media/display/435d636a-8613-11f1-afb8-005056bfb2b6/w:1024/p:16x9/7471a41ebc7365941af7ada73db3369ccd91b9e6.jpg",
     "ts": 1784824274000,
     "beat": "medio_oriente",
     "beatName": "Medio Oriente"
    }
   ]
  },
  {
   "name": "Australia",
   "es": "Australia",
   "lat": -25.3,
   "lon": 133.8,
   "count": 5,
   "items": [
    {
     "title": "Australia news live: eye health warning over GLP-1 drugs; victims of clergy abuse promised ‘full’ compensation by Christian Brothers",
     "link": "https://www.theguardian.com/australia-news/live/2026/jul/24/australia-news-live-jim-chalmers-anthony-albanese-labor-conference-gas-tax-gambling-reform-one-nation-pauline-hanson-ntwnfb",
     "source": "World news | The Guardian",
     "image": "https://i.guim.co.uk/img/media/64876f21c88dc2a424e7004e6e87354773faefeb/244_0_5982_4786/master/5982.jpg?width=140&quality=85&auto=format&fit=max&s=7b279b85677309df9bdb201cbe4e3679",
     "ts": 1784863457000,
     "beat": "actualidad",
     "beatName": "Actualidad Global"
    },
    {
     "title": "Isla Bell death: man previously accused of killing Melbourne teen loses bid to have final charge dropped",
     "link": "https://www.theguardian.com/australia-news/2026/jul/24/isla-bell-death-melbourne-ntwnfb",
     "source": "World news | The Guardian",
     "image": "https://i.guim.co.uk/img/media/b09969ad9582561f32c4cfc117d48d3e52d6c030/403_0_6462_5173/master/6462.jpg?width=140&quality=85&auto=format&fit=max&s=f49b4f91156df4e601bf5d2e9ea6eeef",
     "ts": 1784863207000,
     "beat": "actualidad",
     "beatName": "Actualidad Global"
    },
    {
     "title": "Australia ramps up Aukus funding with US$3.2 billion for nuclear submarine yard",
     "link": "https://www.scmp.com/news/asia/australasia/article/3361665/australia-ramps-aukus-funding-us32-billion-nuclear-submarine-yard?utm_source=rss_feed",
     "source": "News - South China Morning Post",
     "image": "https://cdn.i-scmp.com/sites/default/files/styles/1280x720/public/d8/images/canvas/2026/07/24/dd718ead-13ed-4075-ab11-576f5dbe23bf_8e434a47.jpg?itok=sSbvBGMT&v=1784859592",
     "ts": 1784859593000,
     "beat": "china",
     "beatName": "China"
    },
    {
     "title": "Qantas tests new ultra long-range Airbus in 17,000km direct flight from France to Melbourne",
     "link": "https://www.theguardian.com/business/2026/jul/24/qantas-project-sunrise-airbus-a350-1000ulr-ultra-long-range-france-melbourne-test-flight",
     "source": "World news | The Guardian",
     "image": "https://i.guim.co.uk/img/media/baac5dc44b8125477c220194aae8e6c46174d7e4/463_0_2500_2000/master/2500.jpg?width=140&quality=85&auto=format&fit=max&s=3b5bb7f30e4e768fc26a48d76c907b0d",
     "ts": 1784853590000,
     "beat": "actualidad",
     "beatName": "Actualidad Global"
    },
    {
     "title": "Meet the judges who will crown Australia’s next breakout startup",
     "link": "https://techcrunch.com/2026/07/23/meet-the-judges-who-will-crown-australias-next-breakout-startup/",
     "source": "TechCrunch",
     "image": "",
     "ts": 1784851500000,
     "beat": "tech",
     "beatName": "Tecnología & IA"
    }
   ]
  },
  {
   "name": "Ukraine",
   "es": "Ucrania",
   "lat": 48.4,
   "lon": 31.2,
   "count": 4,
   "items": [
    {
     "title": "Mientras el mundo mira a Irán, la guerra en Ucrania entra en una nueva fase",
     "link": "https://www.prensa.com/opinion/mientras-el-mundo-mira-a-iran-la-guerra-en-ucrania-entra-en-una-nueva-fase/",
     "source": "La Prensa",
     "image": "https://www.prensa.com/resizer/v2/7YASYF5XYRHS5CN5JJXUADCZOQ.jpg?auth=94e00e097a3a98adb8ce3f9de27859271365e3a91e0148a92cc83babf3657213&smart=true&width=3492&height=1964",
     "ts": 1784863800000,
     "beat": "panama_latam",
     "beatName": "Panamá · LatAm"
    },
    {
     "title": "Trump ally Loomer meets Zelensky in Ukraine after dramatic U-turn on war",
     "link": "https://www.scmp.com/news/world/europe/article/3361672/trump-ally-loomer-meets-zelensky-ukraine-after-dramatic-u-turn-war?utm_source=rss_feed",
     "source": "News - South China Morning Post",
     "image": "https://cdn.i-scmp.com/sites/default/files/styles/1280x720/public/d8/images/canvas/2026/07/24/feef8e60-d379-42d0-acb1-1990fece5105_6d7962b4.jpg?itok=ctBARDoO&v=1784861959",
     "ts": 1784861846000,
     "beat": "china",
     "beatName": "China"
    },
    {
     "title": "Ukraine’s Zelenskyy meets with far-right US activist Laura Loomer",
     "link": "https://www.aljazeera.com/news/2026/7/24/ukraine-zelenskyy-meets-with-trump-ally-laura-loomer?traffic_source=rss",
     "source": "Al Jazeera – Breaking News, World News and Video from Al Jazeera",
     "image": "",
     "ts": 1784857767000,
     "beat": "actualidad",
     "beatName": "Actualidad Global"
    },
    {
     "title": "Replay: Marco Rubio addresses Middle East and Ukraine conflicts",
     "link": "https://www.france24.com/en/replay-marco-rubio-addresses-middle-east-and-ukraine-conflicts",
     "source": "Latest news from the Middle East, daily international news reports - France 24",
     "image": "https://s.france24.com/media/display/4dcd71c6-8674-11f1-9b09-005056a90284/w:1024/p:16x9/2026-07-23T082918Z-949515159-RC2KJMAUZ4U4-RTRMADP-3-ASEAN-PHILIPPINES.jpg",
     "ts": 1784797185000,
     "beat": "medio_oriente",
     "beatName": "Medio Oriente"
    }
   ]
  },
  {
   "name": "Saudi Arabia",
   "es": "Arabia Saudita",
   "lat": 23.9,
   "lon": 45.1,
   "count": 4,
   "items": [
    {
     "title": "Trump condiciona acuerdo nuclear con Arabia Saudita",
     "link": "https://www.dw.com/es/trump-condiciona-acuerdo-nuclear-con-arabia-saudita/a-78092787?maca=spa-rss-sp-all-1122-rdf",
     "source": "Deutsche Welle: DW.COM Spanish",
     "image": "",
     "ts": 1784852940000,
     "beat": "panama_latam",
     "beatName": "Panamá · LatAm"
    },
    {
     "title": "Trump says Saudi nuclear deal contingent on Riyadh normalising relations with Israel",
     "link": "https://www.france24.com/en/middle-east/20260723-trump-stuns-saudis-by-pinning-nuclear-deal-to-israel-ties",
     "source": "Latest news from the Middle East, daily international news reports - France 24",
     "image": "https://s.france24.com/media/display/435d636a-8613-11f1-afb8-005056bfb2b6/w:1024/p:16x9/7471a41ebc7365941af7ada73db3369ccd91b9e6.jpg",
     "ts": 1784824274000,
     "beat": "medio_oriente",
     "beatName": "Medio Oriente"
    },
    {
     "title": "US signs landmark nuclear deal with Saudi Arabia",
     "link": "https://www.bbc.co.uk/news/articles/cj03r59z73po?at_medium=RSS&at_campaign=rss",
     "source": "BBC News",
     "image": "https://ichef.bbci.co.uk/ace/standard/240/cpsprodpb/4d92/live/fdf9b860-866b-11f1-bee8-53ce494e1abc.jpg",
     "ts": 1784798270000,
     "beat": "medio_oriente",
     "beatName": "Medio Oriente"
    },
    {
     "title": "US and Saudi Arabia reach a multi-billion dollar civilian nuclear deal",
     "link": "https://www.france24.com/en/us-and-saudi-arabia-reach-a-multi-billion-dollar-civilian-nuclear-deal",
     "source": "Latest news from the Middle East, daily international news reports - France 24",
     "image": "https://s.france24.com/media/display/5bb16bbe-85d2-11f1-9368-005056bf30b7/w:1024/p:16x9/AP17270487406383.jpg",
     "ts": 1784797454000,
     "beat": "medio_oriente",
     "beatName": "Medio Oriente"
    }
   ]
  },
  {
   "name": "India",
   "es": "India",
   "lat": 20.6,
   "lon": 79.0,
   "count": 3,
   "items": [
    {
     "title": "The ‘cockroaches’ marching on India’s government – podcast",
     "link": "https://www.theguardian.com/news/audio/2026/jul/24/the-cockroaches-marching-on-indias-government-podcast",
     "source": "World news | The Guardian",
     "image": "https://i.guim.co.uk/img/media/85ecfe5550814cdc196c83873606be76129c9f54/0_0_4414_3533/master/4414.jpg?width=140&quality=85&auto=format&fit=max&s=f38136f222295c038cc2e1c2723f38e4",
     "ts": 1784858400000,
     "beat": "actualidad",
     "beatName": "Actualidad Global"
    },
    {
     "title": "Modi promete \"castigos severos\" contra filtraciones de exámenes por protestas de las \"cucarachas\"",
     "link": "https://www.france24.com/es/video/20260724-modi-promete-castigos-severos-contra-filtraciones-de-ex%C3%A1menes-por-protestas-de-las-cucarachas",
     "source": "France 24 - Noticias y actualidad internacional en vivo",
     "image": "https://s.france24.com/media/display/2cfb5dfc-86f4-11f1-9958-005056bfb2b6/w:1024/p:16x9/Modi-promete-medidas-por-filtracion-de-examenes-ante-la-presion-de-las-cucarachas.png",
     "ts": 1784852544000,
     "beat": "panama_latam",
     "beatName": "Panamá · LatAm"
    },
    {
     "title": "India ‘cockroach’ activist Sonam Wangchuk ends hunger strike as protests spread",
     "link": "https://www.theguardian.com/world/2026/jul/24/india-cockroach-protest-sonam-wangchuk-ends-hunger-strike",
     "source": "World news | The Guardian",
     "image": "https://i.guim.co.uk/img/media/e1b2b3845b48d3db7cd97ab7093f041d99cde8a7/467_0_5763_4613/master/5763.jpg?width=140&quality=85&auto=format&fit=max&s=013de476ea391a505a0f19a94c9f533f",
     "ts": 1784852432000,
     "beat": "actualidad",
     "beatName": "Actualidad Global"
    }
   ]
  },
  {
   "name": "Mexico",
   "es": "México",
   "lat": 23.6,
   "lon": -102.6,
   "count": 2,
   "items": [
    {
     "title": "EE. UU. y México bloquean cuentas a 55 personas relacionadas con el cartel Jalisco Nueva Generación",
     "link": "https://www.france24.com/es/video/20260724-ee-uu-y-m%C3%A9xico-bloquean-cuentas-a-55-personas-relacionadas-con-el-cartel-jalisco-nueva-generaci%C3%B3n",
     "source": "France 24 - Noticias y actualidad internacional en vivo",
     "image": "https://s.france24.com/media/display/0831f38e-86f7-11f1-8fd0-005056bfb2b6/w:1024/p:16x9/ES-20260723-190915-191036-CS.jpg",
     "ts": 1784853355000,
     "beat": "panama_latam",
     "beatName": "Panamá · LatAm"
    },
    {
     "title": "Ghost Scare Up First Trailer for Mexico City Concert Film ‘2 Big to Rig’",
     "link": "https://www.rollingstone.com/music/music-news/ghost-first-trailer-mexico-city-concert-film-2-big-to-rig-1235597960/",
     "source": "Music – Rolling Stone",
     "image": "",
     "ts": 1784834679000,
     "beat": "musica",
     "beatName": "Música & Industria"
    }
   ]
  },
  {
   "name": "Palestine",
   "es": "Palestina",
   "lat": 31.9,
   "lon": 35.2,
   "count": 2,
   "items": [
    {
     "title": "US court affirms release of pro-Palestine scholar as legal battle continues",
     "link": "https://www.aljazeera.com/news/2026/7/24/us-court-affirms-release-of-pro-palestine-scholar-as-legal-battle-continues?traffic_source=rss",
     "source": "Al Jazeera – Breaking News, World News and Video from Al Jazeera",
     "image": "",
     "ts": 1784858775000,
     "beat": "actualidad",
     "beatName": "Actualidad Global"
    },
    {
     "title": "Israel bombs Gaza after displacement orders, kills two Palestinians",
     "link": "https://www.aljazeera.com/news/2026/7/24/israel-bombs-gaza-after-displacement-orders-kills-two-palestinians?traffic_source=rss",
     "source": "Al Jazeera – Breaking News, World News and Video from Al Jazeera",
     "image": "",
     "ts": 1784852948000,
     "beat": "actualidad",
     "beatName": "Actualidad Global"
    }
   ]
  },
  {
   "name": "France",
   "es": "Francia",
   "lat": 46.2,
   "lon": 2.2,
   "count": 2,
   "items": [
    {
     "title": "Qantas tests new ultra long-range Airbus in 17,000km direct flight from France to Melbourne",
     "link": "https://www.theguardian.com/business/2026/jul/24/qantas-project-sunrise-airbus-a350-1000ulr-ultra-long-range-france-melbourne-test-flight",
     "source": "World news | The Guardian",
     "image": "https://i.guim.co.uk/img/media/baac5dc44b8125477c220194aae8e6c46174d7e4/463_0_2500_2000/master/2500.jpg?width=140&quality=85&auto=format&fit=max&s=3b5bb7f30e4e768fc26a48d76c907b0d",
     "ts": 1784853590000,
     "beat": "actualidad",
     "beatName": "Actualidad Global"
    },
    {
     "title": "Thousands flee wildfires in France and Spain as temperatures reach extreme levels in southern Europe",
     "link": "https://www.theguardian.com/world/2026/jul/23/people-evacuated-intense-wildfire-saumos-france",
     "source": "World news | The Guardian",
     "image": "https://i.guim.co.uk/img/media/4c0553fd54435dc932a03d73737bbeaa9c10a256/421_0_4896_3919/master/4896.jpg?width=140&quality=85&auto=format&fit=max&s=113269bd9965a7cc24ef40cda4ebd51d",
     "ts": 1784852162000,
     "beat": "actualidad",
     "beatName": "Actualidad Global"
    }
   ]
  },
  {
   "name": "Panama",
   "es": "Panamá",
   "lat": 8.5,
   "lon": -80.8,
   "count": 2,
   "items": [
    {
     "title": "Lluvias: hallan sin vida a desaparecido tras ser arrastrado un vehículo en Darién",
     "link": "https://www.prensa.com/judiciales/lluvias-hallan-sin-vida-a-desaparecido-tras-ser-arrastrado-un-vehiculo-en-darien/",
     "source": "La Prensa",
     "image": "https://www.prensa.com/resizer/v2/3KDIAT6RHNCL5OM2NWHMW7A3OQ.jpg?auth=0e894f3540d0fe526e150f32df669524a0546d14d1e46e1fe7f7e837cf6b8d38&smart=true&width=1440&height=1174",
     "ts": 1784862884000,
     "beat": "panama_latam",
     "beatName": "Panamá · LatAm"
    },
    {
     "title": "Mulino anuncia que hará cambios al interés preferencial y al ITBI de viviendas",
     "link": "https://www.prensa.com/economia/mulino-anuncia-que-hara-cambios-al-interes-preferencial-y-al-itbi-de-viviendas/",
     "source": "La Prensa",
     "image": "https://www.prensa.com/resizer/v2/3TBMYA5EPFAUHE7MMMRJNWD4HA.jpeg?auth=76063d0736c0459f47139eeca6f59cfb1dbc20070b3be174b2c0cff11d23ce93&smart=true&width=1280&height=854",
     "ts": 1784856168000,
     "beat": "panama_latam",
     "beatName": "Panamá · LatAm"
    }
   ]
  },
  {
   "name": "Chad",
   "es": "Chad",
   "lat": 15.5,
   "lon": 18.7,
   "count": 1,
   "items": [
    {
     "title": "Listen to Chad Hugo’s First Solo Single Featuring Tierra Whack and Leikeli47",
     "link": "https://pitchfork.com/story/watch-chad-hugo-and-tierra-whack-dance-through-an-apocalyptic-planet/",
     "source": "RSS: News",
     "image": "https://media.pitchfork.com/photos/6a623bd4f90654ad37042914/master/pass/unnamed%20(42).jpg",
     "ts": 1784824971000,
     "beat": "musica",
     "beatName": "Música & Industria"
    }
   ]
  },
  {
   "name": "Indonesia",
   "es": "Indonesia",
   "lat": -0.8,
   "lon": 113.9,
   "count": 1,
   "items": [
    {
     "title": "FBI Returns Looted Cultural Artifacts to Indonesia",
     "link": "https://www.artnews.com/art-news/news/u-s-repatriates-looted-indonesian-cultural-artifacts-1234793281/",
     "source": "ARTnews.com",
     "image": "",
     "ts": 1784830674000,
     "beat": "arte",
     "beatName": "Arte · Cultura · Educación"
    }
   ]
  },
  {
   "name": "Spain",
   "es": "España",
   "lat": 40.5,
   "lon": -3.7,
   "count": 1,
   "items": [
    {
     "title": "Thousands flee wildfires in France and Spain as temperatures reach extreme levels in southern Europe",
     "link": "https://www.theguardian.com/world/2026/jul/23/people-evacuated-intense-wildfire-saumos-france",
     "source": "World news | The Guardian",
     "image": "https://i.guim.co.uk/img/media/4c0553fd54435dc932a03d73737bbeaa9c10a256/421_0_4896_3919/master/4896.jpg?width=140&quality=85&auto=format&fit=max&s=113269bd9965a7cc24ef40cda4ebd51d",
     "ts": 1784852162000,
     "beat": "actualidad",
     "beatName": "Actualidad Global"
    }
   ]
  },
  {
   "name": "Colombia",
   "es": "Colombia",
   "lat": 4.6,
   "lon": -74.3,
   "count": 1,
   "items": [
    {
     "title": "Alcalde Alejandro Char reaccionó a la propuesta de Abelardo De La Espriella para convertir a Barranquilla en la capital alterna de Colombia: 'Gracias'",
     "link": "https://www.eltiempo.com/colombia/barranquilla/alcalde-alejandro-char-reacciono-a-la-propuesta-de-abelardo-de-la-espriella-para-convertir-a-barranquilla-en-la-capital-alterna-de-colombia-gracias-3573456",
     "source": "EL TIEMPO.COM -Colombia",
     "image": "https://imagenes2.eltiempo.com/files/og_thumbnail/uploads/2026/07/23/6a62dacd6202f.png",
     "ts": 1784863463000,
     "beat": "panama_latam",
     "beatName": "Panamá · LatAm"
    }
   ]
  },
  {
   "name": "Argentina",
   "es": "Argentina",
   "lat": -38.4,
   "lon": -63.6,
   "count": 1,
   "items": [
    {
     "title": "Javier Milei se suma a la polémica sobre la selección argentina en el Mundial: ‘Nos tienen celos’",
     "link": "https://www.prensa.com/deportes/javier-milei-se-suma-a-la-polemica-sobre-la-seleccion-argentina-en-el-mundial-nos-tienen-celos/",
     "source": "La Prensa",
     "image": "https://www.prensa.com/resizer/v2/R7VJOSBHP5DBHPRFZPLTHVLEMA.jpeg?auth=20d478b38520a1e3b2bfb8541b2e465e1dc540d3aff032487881ef3bd85f77e4&smart=true&width=1280&height=960",
     "ts": 1784855475000,
     "beat": "panama_latam",
     "beatName": "Panamá · LatAm"
    }
   ]
  },
  {
   "name": "Venezuela",
   "es": "Venezuela",
   "lat": 6.4,
   "lon": -66.6,
   "count": 1,
   "items": [
    {
     "title": "“Esto fue horrible\": la cadena de tragedias para los sobrevivientes de los terremotos en Venezuela",
     "link": "https://www.france24.com/es/am%C3%A9rica-latina/20260724-venezuela-terremotos-esto-fue-horrible-la-cadena-de-tragedias-para-los-sobrevivientes",
     "source": "France 24 - Noticias y actualidad internacional en vivo",
     "image": "https://s.france24.com/media/display/e495ad42-86ee-11f1-9dc6-005056a90284/w:1024/p:16x9/8023623815001w.jpg",
     "ts": 1784853897000,
     "beat": "panama_latam",
     "beatName": "Panamá · LatAm"
    }
   ]
  },
  {
   "name": "United Kingdom",
   "es": "Reino Unido",
   "lat": 55.4,
   "lon": -3.4,
   "count": 1,
   "items": [
    {
     "title": "UK ‘ready to defend itself’ after Iranian threat over US bases",
     "link": "https://www.theguardian.com/world/2026/jul/23/uk-ready-to-defend-itself-iran-threat-us-bases",
     "source": "Middle East and north Africa | The Guardian",
     "image": "https://i.guim.co.uk/img/media/e1c12d0d4c30b233389f2362dd10269516d753c0/611_0_5551_4442/master/5551.jpg?width=140&quality=85&auto=format&fit=max&s=f00e148f7e5d1e1118628e83ca1a3d26",
     "ts": 1784846497000,
     "beat": "medio_oriente",
     "beatName": "Medio Oriente"
    }
   ]
  },
  {
   "name": "United Arab Emirates",
   "es": "Emiratos Árabes",
   "lat": 23.4,
   "lon": 53.8,
   "count": 1,
   "items": [
    {
     "title": "Dubai offers £600 rewards to residents who lure friends to visit as tourist numbers plummet",
     "link": "https://www.theguardian.com/world/2026/jul/23/dubai-offers-tourists-benefits",
     "source": "Middle East and north Africa | The Guardian",
     "image": "https://i.guim.co.uk/img/media/734540cdd2ceb7b784f26f386546f7556fdfcb1e/252_0_3780_3024/master/3780.jpg?width=140&quality=85&auto=format&fit=max&s=0a0f74c7a8058a9d01a1a02ca5551fb4",
     "ts": 1784806103000,
     "beat": "medio_oriente",
     "beatName": "Medio Oriente"
    }
   ]
  },
  {
   "name": "Iraq",
   "es": "Irak",
   "lat": 33.2,
   "lon": 43.7,
   "count": 1,
   "items": [
    {
     "title": "Iraq’s impossible predicament: why the country is trapped between Iran and the US",
     "link": "https://www.theguardian.com/news/ng-interactive/2026/jul/23/iraqs-impossible-predicament-why-the-country-is-trapped-between-iran-and-the-us",
     "source": "Middle East and north Africa | The Guardian",
     "image": "https://i.guim.co.uk/img/media/15a79a0ae8fd7270220aa4fdf9bc5e2e8784af01/0_285_2036_1629/master/2036.jpg?width=140&quality=85&auto=format&fit=max&s=d01e7be8fa01b8e4a4f4981cc88f1053",
     "ts": 1784779235000,
     "beat": "medio_oriente",
     "beatName": "Medio Oriente"
    }
   ]
  },
  {
   "name": "Lebanon",
   "es": "Líbano",
   "lat": 33.9,
   "lon": 35.9,
   "count": 1,
   "items": [
    {
     "title": "Japanese militant who took part in 1972 Israel airport attack dies in Beirut",
     "link": "https://www.scmp.com/news/world/middle-east/article/3361679/japanese-militant-who-took-part-1972-israel-airport-attack-dies-beirut?utm_source=rss_feed",
     "source": "News - South China Morning Post",
     "image": "https://cdn.i-scmp.com/sites/default/files/styles/1280x720/public/d8/images/canvas/2026/07/24/a2a42246-3a94-4b25-8be9-dab4816b047d_aec588a0.jpg?itok=F6X2esHo&v=1784864374",
     "ts": 1784864375000,
     "beat": "china",
     "beatName": "China"
    }
   ]
  },
  {
   "name": "Philippines",
   "es": "Filipinas",
   "lat": 12.9,
   "lon": 121.8,
   "count": 1,
   "items": [
    {
     "title": "Is it all economic doom and gloom for the Philippines?",
     "link": "https://www.scmp.com/week-asia/economics/article/3361631/it-all-economic-doom-and-gloom-philippines?utm_source=rss_feed",
     "source": "News - South China Morning Post",
     "image": "https://cdn.i-scmp.com/sites/default/files/styles/1280x720/public/d8/images/canvas/2026/07/23/db14c4a8-d403-4df1-99d1-aa6c0dc1ac05_3698a229.jpg?itok=tk6p2TAR&v=1784812758",
     "ts": 1784862007000,
     "beat": "china",
     "beatName": "China"
    }
   ]
  },
  {
   "name": "Singapore",
   "es": "Singapur",
   "lat": 1.35,
   "lon": 103.8,
   "count": 1,
   "items": [
    {
     "title": "HSBC agrees to US$2 billion deal to sell Singapore insurance branch to Allianz",
     "link": "https://www.scmp.com/business/companies/article/3361669/hsbc-agrees-us2-billion-deal-sell-singapore-insurance-branch-allianz?utm_source=rss_feed",
     "source": "News - South China Morning Post",
     "image": "https://cdn.i-scmp.com/sites/default/files/styles/1280x720/public/d8/images/canvas/2026/07/24/4092a638-f375-4749-9f6f-1f273748af9d_c982ef0b.jpg?itok=CRlqLOFc&v=1784860710",
     "ts": 1784860711000,
     "beat": "china",
     "beatName": "China"
    }
   ]
  },
  {
   "name": "Japan",
   "es": "Japón",
   "lat": 36.2,
   "lon": 138.3,
   "count": 1,
   "items": [
    {
     "title": "Why Japan’s fighter jet future looks ‘more optimistic’ with Canada’s entry",
     "link": "https://www.scmp.com/week-asia/politics/article/3361624/why-japans-fighter-jet-future-looks-more-optimistic-canadas-entry?utm_source=rss_feed",
     "source": "News - South China Morning Post",
     "image": "https://cdn.i-scmp.com/sites/default/files/styles/1280x720/public/d8/images/canvas/2026/07/23/d27aadef-ba9a-4d9e-bc28-fcdd2fbd0ccc_2b4cbefb.jpg?itok=7YbQ3gaP&v=1784806899",
     "ts": 1784851214000,
     "beat": "china",
     "beatName": "China"
    }
   ]
  },
  {
   "name": "Canada",
   "es": "Canadá",
   "lat": 56.1,
   "lon": -106.3,
   "count": 1,
   "items": [
    {
     "title": "Why Japan’s fighter jet future looks ‘more optimistic’ with Canada’s entry",
     "link": "https://www.scmp.com/week-asia/politics/article/3361624/why-japans-fighter-jet-future-looks-more-optimistic-canadas-entry?utm_source=rss_feed",
     "source": "News - South China Morning Post",
     "image": "https://cdn.i-scmp.com/sites/default/files/styles/1280x720/public/d8/images/canvas/2026/07/23/d27aadef-ba9a-4d9e-bc28-fcdd2fbd0ccc_2b4cbefb.jpg?itok=7YbQ3gaP&v=1784806899",
     "ts": 1784851214000,
     "beat": "china",
     "beatName": "China"
    }
   ]
  },
  {
   "name": "Brazil",
   "es": "Brasil",
   "lat": -14.2,
   "lon": -51.9,
   "count": 1,
   "items": [
    {
     "title": "China vows to defend Brazil’s sovereignty as Trump’s 25% tariff bites",
     "link": "https://www.scmp.com/news/china/diplomacy/article/3361648/china-vows-defend-brazils-sovereignty-trumps-25-tariff-bites?utm_source=rss_feed",
     "source": "News - South China Morning Post",
     "image": "https://cdn.i-scmp.com/sites/default/files/styles/1280x720/public/d8/images/canvas/2026/07/24/33c0dc16-b85c-4f05-97a3-e23c1ca4fb98_c38b86f2.jpg?itok=rL5xozqY&v=1784836478",
     "ts": 1784836487000,
     "beat": "china",
     "beatName": "China"
    }
   ]
  }
 ]
}