{
 "updated": "2026-07-04T08:06:47.750755+00:00",
 "count": 223,
 "max": 5.9,
 "items": [
  {
   "mag": 5.9,
   "place": "296 km SSW of Severo-Kuril’sk, Russia",
   "time": 1783066973615,
   "lon": 154.2634,
   "lat": 48.3001,
   "depth": 75.804,
   "url": "https://earthquake.usgs.gov/earthquakes/eventpage/us6000t9tf"
  },
  {
   "mag": 5.3,
   "place": "Balleny Islands region",
   "time": 1783110135219,
   "lon": 155.7881,
   "lat": -62.1125,
   "depth": 10,
   "url": "https://earthquake.usgs.gov/earthquakes/eventpage/us6000t9zw"
  },
  {
   "mag": 5.2,
   "place": "24 km SW of Balangonan, Philippines",
   "time": 1783131683141,
   "lon": 125.1808,
   "lat": 5.429,
   "depth": 10,
   "url": "https://earthquake.usgs.gov/earthquakes/eventpage/us6000ta14"
  },
  {
   "mag": 5.1,
   "place": "135 km N of Lae, Papua New Guinea",
   "time": 1783151423853,
   "lon": 147.103,
   "lat": -5.5049,
   "depth": 182.779,
   "url": "https://earthquake.usgs.gov/earthquakes/eventpage/us6000ta2x"
  },
  {
   "mag": 5,
   "place": "43 km SW of Ovalle, Chile",
   "time": 1783134573198,
   "lon": -71.4792,
   "lat": -30.9133,
   "depth": 49.84,
   "url": "https://earthquake.usgs.gov/earthquakes/eventpage/us6000ta18"
  },
  {
   "mag": 4.9,
   "place": "18 km SW of Sarangani, Philippines",
   "time": 1783073439450,
   "lon": 125.3575,
   "lat": 5.2762,
   "depth": 67.627,
   "url": "https://earthquake.usgs.gov/earthquakes/eventpage/us6000t9tw"
  },
  {
   "mag": 4.9,
   "place": "36 km WSW of Sarangani, Philippines",
   "time": 1783073321073,
   "lon": 125.1729,
   "lat": 5.2416,
   "depth": 61.466,
   "url": "https://earthquake.usgs.gov/earthquakes/eventpage/us6000t9tv"
  },
  {
   "mag": 4.8,
   "place": "Izu Islands, Japan region",
   "time": 1783141432698,
   "lon": 142.4608,
   "lat": 32.089,
   "depth": 10,
   "url": "https://earthquake.usgs.gov/earthquakes/eventpage/us6000ta20"
  },
  {
   "mag": 4.8,
   "place": "26 km SW of Balangonan, Philippines",
   "time": 1783139187270,
   "lon": 125.17,
   "lat": 5.4243,
   "depth": 10.124,
   "url": "https://earthquake.usgs.gov/earthquakes/eventpage/us6000ta1t"
  },
  {
   "mag": 4.8,
   "place": "42 km SW of Balangonan, Philippines",
   "time": 1783105757167,
   "lon": 125.049,
   "lat": 5.3374,
   "depth": 59.785,
   "url": "https://earthquake.usgs.gov/earthquakes/eventpage/us6000t9zf"
  },
  {
   "mag": 4.8,
   "place": "24 km SE of Tambolaka, Indonesia",
   "time": 1783098892701,
   "lon": 119.4219,
   "lat": -9.5546,
   "depth": 41.705,
   "url": "https://earthquake.usgs.gov/earthquakes/eventpage/us6000t9yy"
  },
  {
   "mag": 4.7,
   "place": "67 km W of Tobelo, Indonesia",
   "time": 1783066299694,
   "lon": 127.4042,
   "lat": 1.6895,
   "depth": 141.078,
   "url": "https://earthquake.usgs.gov/earthquakes/eventpage/us6000t9ta"
  },
  {
   "mag": 4.6,
   "place": "91 km SE of Kumano, Japan",
   "time": 1783133775263,
   "lon": 136.8775,
   "lat": 33.3762,
   "depth": 388.05,
   "url": "https://earthquake.usgs.gov/earthquakes/eventpage/us6000ta17"
  },
  {
   "mag": 4.6,
   "place": "west of Macquarie Island",
   "time": 1783070195165,
   "lon": 147.0388,
   "lat": -56.2709,
   "depth": 10,
   "url": "https://earthquake.usgs.gov/earthquakes/eventpage/us6000t9ts"
  },
  {
   "mag": 4.5,
   "place": "Fiji region",
   "time": 1783123250589,
   "lon": -178.202,
   "lat": -19.9341,
   "depth": 576.196,
   "url": "https://earthquake.usgs.gov/earthquakes/eventpage/us6000ta0n"
  },
  {
   "mag": 4.5,
   "place": "158 km ENE of Beauséjour, Guadeloupe",
   "time": 1783089925609,
   "lon": -59.627,
   "lat": 16.6199,
   "depth": 10,
   "url": "https://earthquake.usgs.gov/earthquakes/eventpage/us6000t9um"
  },
  {
   "mag": 4.4,
   "place": "48 km NNE of Sarykemer, Kazakhstan",
   "time": 1783122055905,
   "lon": 71.713,
   "lat": 43.4086,
   "depth": 10,
   "url": "https://earthquake.usgs.gov/earthquakes/eventpage/us6000ta0j"
  },
  {
   "mag": 4.4,
   "place": "59 km ENE of Kyzyl-Eshme, Kyrgyzstan",
   "time": 1783071353629,
   "lon": 72.9214,
   "lat": 39.7508,
   "depth": 10,
   "url": "https://earthquake.usgs.gov/earthquakes/eventpage/us6000t9tt"
  },
  {
   "mag": 4.3,
   "place": "124 km WSW of Hihifo, Tonga",
   "time": 1783144003221,
   "lon": -174.939,
   "lat": -16.1828,
   "depth": 301.374,
   "url": "https://earthquake.usgs.gov/earthquakes/eventpage/us6000ta2b"
  },
  {
   "mag": 4.3,
   "place": "257 km WSW of Tual, Indonesia",
   "time": 1783105232733,
   "lon": 130.4865,
   "lat": -6.1348,
   "depth": 139.299,
   "url": "https://earthquake.usgs.gov/earthquakes/eventpage/us6000t9zc"
  },
  {
   "mag": 4.3,
   "place": "46 km SW of Ḩājjīābād, Iran",
   "time": 1783078492471,
   "lon": 55.531,
   "lat": 28.0541,
   "depth": 10,
   "url": "https://earthquake.usgs.gov/earthquakes/eventpage/us6000t9u3"
  },
  {
   "mag": 4,
   "place": "233 km ESE of Attu Station, Alaska",
   "time": 1783119820230,
   "lon": 176.226,
   "lat": 51.879,
   "depth": 10,
   "url": "https://earthquake.usgs.gov/earthquakes/eventpage/aka2026nbudue"
  },
  {
   "mag": 3.9,
   "place": "13 km SE of La Romana, Dominican Republic",
   "time": 1783090655180,
   "lon": -68.8915,
   "lat": 18.3276,
   "depth": 148,
   "url": "https://earthquake.usgs.gov/earthquakes/eventpage/pr2026184000"
  },
  {
   "mag": 3.8,
   "place": "66 km WSW of Port Alexander, Alaska",
   "time": 1783134756182,
   "lon": -135.599,
   "lat": 55.978,
   "depth": 0.9,
   "url": "https://earthquake.usgs.gov/earthquakes/eventpage/aka2026ncclpa"
  },
  {
   "mag": 3.8,
   "place": "140 km E of Atka, Alaska",
   "time": 1783089322264,
   "lon": -172.18,
   "lat": 51.999,
   "depth": 10,
   "url": "https://earthquake.usgs.gov/earthquakes/eventpage/aka2026nbdfam"
  },
  {
   "mag": 3.5,
   "place": "204 km SSW of Adak, Alaska",
   "time": 1783093721108,
   "lon": -177.391,
   "lat": 50.101,
   "depth": 10,
   "url": "https://earthquake.usgs.gov/earthquakes/eventpage/aka2026nbfqkv"
  },
  {
   "mag": 3.4,
   "place": "73 km NW of San Antonio, Puerto Rico",
   "time": 1783131700622,
   "lon": -67.6028,
   "lat": 18.9565,
   "depth": 39.904,
   "url": "https://earthquake.usgs.gov/earthquakes/eventpage/us6000ta10"
  },
  {
   "mag": 3.3,
   "place": "65 km N of Hatillo, Puerto Rico",
   "time": 1783127414830,
   "lon": -66.772,
   "lat": 19.074,
   "depth": 40.22,
   "url": "https://earthquake.usgs.gov/earthquakes/eventpage/pr71522598"
  },
  {
   "mag": 3.3,
   "place": "125 km E of Chalkyitsik, Alaska",
   "time": 1783095246750,
   "lon": -140.8766,
   "lat": 66.6242,
   "depth": 10,
   "url": "https://earthquake.usgs.gov/earthquakes/eventpage/us6000t9uy"
  },
  {
   "mag": 3.2,
   "place": "95 km N of Isabela, Puerto Rico",
   "time": 1783121940920,
   "lon": -67.1056666666667,
   "lat": 19.3556666666667,
   "depth": 24.06,
   "url": "https://earthquake.usgs.gov/earthquakes/eventpage/pr71522593"
  },
  {
   "mag": 3.0,
   "place": "61 km NNE of Cruz Bay, U.S. Virgin Islands",
   "time": 1783116135200,
   "lon": -64.5673333333333,
   "lat": 18.8385,
   "depth": 45.76,
   "url": "https://earthquake.usgs.gov/earthquakes/eventpage/pr71522573"
  },
  {
   "mag": 2.9,
   "place": "44 km W of Ninilchik, Alaska",
   "time": 1783083601362,
   "lon": -152.457,
   "lat": 60.123,
   "depth": 89.3,
   "url": "https://earthquake.usgs.gov/earthquakes/eventpage/aka2026nbaaik"
  },
  {
   "mag": 2.8,
   "place": "36 km SSW of Los Ybanez, Texas",
   "time": 1783138092984,
   "lon": -102.113,
   "lat": 32.438,
   "depth": 6.5674,
   "url": "https://earthquake.usgs.gov/earthquakes/eventpage/tx2026nabvvf"
  },
  {
   "mag": 2.7,
   "place": "92 km SSE of Kokhanok, Alaska",
   "time": 1783141086686,
   "lon": -154.364,
   "lat": 58.637,
   "depth": 10.7,
   "url": "https://earthquake.usgs.gov/earthquakes/eventpage/aka2026ncfzau"
  },
  {
   "mag": 2.7,
   "place": "54 km SW of Akhiok, Alaska",
   "time": 1783130428043,
   "lon": -154.83,
   "lat": 56.611,
   "depth": 59,
   "url": "https://earthquake.usgs.gov/earthquakes/eventpage/aka2026ncabar"
  },
  {
   "mag": 2.6,
   "place": "90 km ESE of McCarthy, Alaska",
   "time": 1783146000606,
   "lon": -141.276,
   "lat": 61.264,
   "depth": 5,
   "url": "https://earthquake.usgs.gov/earthquakes/eventpage/aka2026ncisbm"
  },
  {
   "mag": 2.6,
   "place": "198 km WSW of Pistol River, Oregon",
   "time": 1783138478917,
   "lon": -126.7348,
   "lat": 41.8984,
   "depth": 10,
   "url": "https://earthquake.usgs.gov/earthquakes/eventpage/us6000ta1q"
  },
  {
   "mag": 2.6,
   "place": "242 km SE of Chignik, Alaska",
   "time": 1783137493816,
   "lon": -156.044,
   "lat": 54.574,
   "depth": 5,
   "url": "https://earthquake.usgs.gov/earthquakes/eventpage/aka2026ncdyzk"
  },
  {
   "mag": 2.5,
   "place": "8 km ENE of Borrego Springs, CA",
   "time": 1783143729130,
   "lon": -116.296333333333,
   "lat": 33.2858333333333,
   "depth": 8.29,
   "url": "https://earthquake.usgs.gov/earthquakes/eventpage/ci41286343"
  },
  {
   "mag": 2.5,
   "place": "3 km SW of Anderson Springs, CA",
   "time": 1783131820870,
   "lon": -122.717498779297,
   "lat": 38.7578315734863,
   "depth": 0.699999988079071,
   "url": "https://earthquake.usgs.gov/earthquakes/eventpage/nc75389021"
  },
  {
   "mag": 2.5,
   "place": "59 km NE of Tonopah, Nevada",
   "time": 1783108985465,
   "lon": -116.7271,
   "lat": 38.4306,
   "depth": 4.4389,
   "url": "https://earthquake.usgs.gov/earthquakes/eventpage/nn00921133"
  },
  {
   "mag": 2.5,
   "place": "6 km SW of Saint-Siméon, Canada",
   "time": 1783091540254,
   "lon": -69.9501,
   "lat": 47.8089,
   "depth": 10,
   "url": "https://earthquake.usgs.gov/earthquakes/eventpage/us6000t9up"
  },
  {
   "mag": 2.4,
   "place": "29 km NW of Toyah, Texas",
   "time": 1783150733333,
   "lon": -104.004,
   "lat": 31.512,
   "depth": 4.7269,
   "url": "https://earthquake.usgs.gov/earthquakes/eventpage/tx2026naiuwa"
  },
  {
   "mag": 2.4,
   "place": "31 km NW of Toyah, Texas",
   "time": 1783142654898,
   "lon": -104.012,
   "lat": 31.524,
   "depth": 4.5052,
   "url": "https://earthquake.usgs.gov/earthquakes/eventpage/tx2026naejjc"
  },
  {
   "mag": 2.4,
   "place": "31 km NW of Toyah, Texas",
   "time": 1783142559695,
   "lon": -104.01,
   "lat": 31.53,
   "depth": 4.3386,
   "url": "https://earthquake.usgs.gov/earthquakes/eventpage/tx2026naehlt"
  },
  {
   "mag": 2.3,
   "place": "54 km SE of Gabbs, Nevada",
   "time": 1783108995263,
   "lon": -117.406,
   "lat": 38.5875,
   "depth": 5.1203,
   "url": "https://earthquake.usgs.gov/earthquakes/eventpage/nn00921136"
  },
  {
   "mag": 2.3,
   "place": "61 km NW of Beluga, Alaska",
   "time": 1783105267985,
   "lon": -151.956,
   "lat": 61.5,
   "depth": 5,
   "url": "https://earthquake.usgs.gov/earthquakes/eventpage/aka2026nbmblc"
  },
  {
   "mag": 2.3,
   "place": "5 km SE of Kingston, Washington",
   "time": 1783094119640,
   "lon": -122.453166666667,
   "lat": 47.7648333333333,
   "depth": 27.83,
   "url": "https://earthquake.usgs.gov/earthquakes/eventpage/uw714040272"
  },
  {
   "mag": 2.2,
   "place": "4 km WSW of Las Vegas, Nevada",
   "time": 1783113853123,
   "lon": -115.1767,
   "lat": 36.1562,
   "depth": 3.2454,
   "url": "https://earthquake.usgs.gov/earthquakes/eventpage/nn00921137"
  },
  {
   "mag": 2.1,
   "place": "1 km W of Brawley, CA",
   "time": 1783146178720,
   "lon": -115.540333333333,
   "lat": 32.9801666666667,
   "depth": 11.59,
   "url": "https://earthquake.usgs.gov/earthquakes/eventpage/ci41286375"
  },
  {
   "mag": 2.1,
   "place": "64 km NNW of Aleneva, Alaska",
   "time": 1783128159306,
   "lon": -153.216,
   "lat": 58.617,
   "depth": 71.8,
   "url": "https://earthquake.usgs.gov/earthquakes/eventpage/aka2026nbyugj"
  },
  {
   "mag": 2.1,
   "place": "14 km ESE of Pāhala, Hawaii",
   "time": 1783124444180,
   "lon": -155.355163574219,
   "lat": 19.1526660919189,
   "depth": 26.7299995422363,
   "url": "https://earthquake.usgs.gov/earthquakes/eventpage/hv74996591"
  },
  {
   "mag": 2.1,
   "place": "15 km WSW of San Simeon, CA",
   "time": 1783107431690,
   "lon": -121.346833333333,
   "lat": 35.5921666666667,
   "depth": 2.66,
   "url": "https://earthquake.usgs.gov/earthquakes/eventpage/nc75388811"
  },
  {
   "mag": 2.1,
   "place": "15 km SSW of Searles Valley, CA",
   "time": 1783087108330,
   "lon": -117.4565,
   "lat": 35.64,
   "depth": 7.25,
   "url": "https://earthquake.usgs.gov/earthquakes/eventpage/ci41285983"
  },
  {
   "mag": 2.1,
   "place": "12 km ESE of Pearsall, Texas",
   "time": 1783086200903,
   "lon": -98.978,
   "lat": 28.839,
   "depth": 5.1966,
   "url": "https://earthquake.usgs.gov/earthquakes/eventpage/tx2026myzeok"
  },
  {
   "mag": 2.1,
   "place": "25 km N of Skwentna, Alaska",
   "time": 1783070567270,
   "lon": -151.404,
   "lat": 62.215,
   "depth": 89.5,
   "url": "https://earthquake.usgs.gov/earthquakes/eventpage/aka2026nastxh"
  },
  {
   "mag": 2,
   "place": "108 km SSE of Halibut Cove, Alaska",
   "time": 1783118447812,
   "lon": -150.16,
   "lat": 58.785,
   "depth": 4.6,
   "url": "https://earthquake.usgs.gov/earthquakes/eventpage/aka2026nbtjwa"
  },
  {
   "mag": 2.0,
   "place": "3 km SW of Pāhala, Hawaii",
   "time": 1783109358440,
   "lon": -155.497161865234,
   "lat": 19.1805000305176,
   "depth": 27.8500003814697,
   "url": "https://earthquake.usgs.gov/earthquakes/eventpage/hv74996471"
  },
  {
   "mag": 2.0,
   "place": "3 km ENE of Running Springs, CA",
   "time": 1783099862800,
   "lon": -117.076333333333,
   "lat": 34.2153333333333,
   "depth": 3.7,
   "url": "https://earthquake.usgs.gov/earthquakes/eventpage/ci41286103"
  },
  {
   "mag": 2.0,
   "place": "18 km NNE of Indio, CA",
   "time": 1783085158250,
   "lon": -116.171666666667,
   "lat": 33.8811666666667,
   "depth": 3.01,
   "url": "https://earthquake.usgs.gov/earthquakes/eventpage/ci41285959"
  },
  {
   "mag": 2,
   "place": "38 km W of Tatitlek, Alaska",
   "time": 1783070173292,
   "lon": -147.38,
   "lat": 60.924,
   "depth": 20,
   "url": "https://earthquake.usgs.gov/earthquakes/eventpage/aka2026nasohc"
  },
  {
   "mag": 1.9,
   "place": "21 km NNW of Piru, CA",
   "time": 1783151555270,
   "lon": -118.882833333333,
   "lat": 34.587,
   "depth": 1.95,
   "url": "https://earthquake.usgs.gov/earthquakes/eventpage/ci41286399"
  },
  {
   "mag": 1.9,
   "place": "1 km SW of Brawley, CA",
   "time": 1783145881630,
   "lon": -115.534833333333,
   "lat": 32.9738333333333,
   "depth": 12.18,
   "url": "https://earthquake.usgs.gov/earthquakes/eventpage/ci41286367"
  },
  {
   "mag": 1.9,
   "place": "5 km SSE of Pāhala, Hawaii",
   "time": 1783127395170,
   "lon": -155.464172363281,
   "lat": 19.1528339385986,
   "depth": 31.2999992370605,
   "url": "https://earthquake.usgs.gov/earthquakes/eventpage/hv74996611"
  },
  {
   "mag": 1.9,
   "place": "15 km S of Joshua Tree, CA",
   "time": 1783115599780,
   "lon": -116.324166666667,
   "lat": 34.0035,
   "depth": 8.07,
   "url": "https://earthquake.usgs.gov/earthquakes/eventpage/ci41286175"
  },
  {
   "mag": 1.9,
   "place": "56 km S of Kingston, Nevada",
   "time": 1783107993524,
   "lon": -117.1273,
   "lat": 38.7067,
   "depth": 16,
   "url": "https://earthquake.usgs.gov/earthquakes/eventpage/nn00921130"
  },
  {
   "mag": 1.9,
   "place": "7 km N of Shaver Lake, CA",
   "time": 1783107403340,
   "lon": -119.325,
   "lat": 37.1651666666667,
   "depth": 26.12,
   "url": "https://earthquake.usgs.gov/earthquakes/eventpage/nc75388816"
  },
  {
   "mag": 1.9,
   "place": "54 km W of Nanwalek, Alaska",
   "time": 1783098563327,
   "lon": -152.871,
   "lat": 59.344,
   "depth": 93,
   "url": "https://earthquake.usgs.gov/earthquakes/eventpage/aka2026nbiino"
  },
  {
   "mag": 1.9,
   "place": "23 km W of Petrolia, CA",
   "time": 1783090705140,
   "lon": -124.557167053223,
   "lat": 40.3001670837402,
   "depth": 24.1100006103516,
   "url": "https://earthquake.usgs.gov/earthquakes/eventpage/nc75388641"
  },
  {
   "mag": 1.9,
   "place": "53 km SSW of Whites City, New Mexico",
   "time": 1783082368964,
   "lon": -104.493,
   "lat": 31.707,
   "depth": 6.3818,
   "url": "https://earthquake.usgs.gov/earthquakes/eventpage/tx2026myxaxz"
  },
  {
   "mag": 1.8,
   "place": "30 km NW of Toyah, Texas",
   "time": 1783138110106,
   "lon": -104.011,
   "lat": 31.521,
   "depth": 7.061,
   "url": "https://earthquake.usgs.gov/earthquakes/eventpage/tx2026nabvzg"
  },
  {
   "mag": 1.8,
   "place": "91 km SE of Pope-Vannoy Landing, Alaska",
   "time": 1783136722657,
   "lon": -153.585,
   "lat": 58.883,
   "depth": 13.3,
   "url": "https://earthquake.usgs.gov/earthquakes/eventpage/aka2026ncdnzv"
  },
  {
   "mag": 1.8,
   "place": "4 km ESE of Tyonek, Alaska",
   "time": 1783130734478,
   "lon": -151.067,
   "lat": 61.055,
   "depth": 66.2,
   "url": "https://earthquake.usgs.gov/earthquakes/eventpage/aka2026ncaflk"
  },
  {
   "mag": 1.8,
   "place": "12 km ENE of Naalehu, Hawaii",
   "time": 1783127614960,
   "lon": -155.466827392578,
   "lat": 19.0925006866455,
   "depth": 26,
   "url": "https://earthquake.usgs.gov/earthquakes/eventpage/hv74996616"
  },
  {
   "mag": 1.8,
   "place": "28 km SSE of Waikoloa, Hawaii",
   "time": 1783123087940,
   "lon": -155.650329589844,
   "lat": 19.7216663360596,
   "depth": 36.9700012207031,
   "url": "https://earthquake.usgs.gov/earthquakes/eventpage/hv74996581"
  },
  {
   "mag": 1.8,
   "place": "8 km SSW of Pāhala, Hawaii",
   "time": 1783120679940,
   "lon": -155.5,
   "lat": 19.1266670227051,
   "depth": 28.1499996185303,
   "url": "https://earthquake.usgs.gov/earthquakes/eventpage/hv74996561"
  },
  {
   "mag": 1.8,
   "place": "73 km S of Cordova, Alaska",
   "time": 1783112717720,
   "lon": -145.542,
   "lat": 59.896,
   "depth": 15.5,
   "url": "https://earthquake.usgs.gov/earthquakes/eventpage/aka2026nbqfcu"
  },
  {
   "mag": 1.8,
   "place": "30 km NW of Toyah, Texas",
   "time": 1783104492715,
   "lon": -104.011,
   "lat": 31.511,
   "depth": 4.9234,
   "url": "https://earthquake.usgs.gov/earthquakes/eventpage/tx2026mzjhbs"
  },
  {
   "mag": 1.8,
   "place": "18 km NNW of Glacier View, Alaska",
   "time": 1783101534444,
   "lon": -147.83,
   "lat": 61.951,
   "depth": 29.1,
   "url": "https://earthquake.usgs.gov/earthquakes/eventpage/aka2026nbjzln"
  },
  {
   "mag": 1.8,
   "place": "30 km NW of Toyah, Texas",
   "time": 1783101362644,
   "lon": -104.006,
   "lat": 31.525,
   "depth": 7.2406,
   "url": "https://earthquake.usgs.gov/earthquakes/eventpage/tx2026mzhmyy"
  },
  {
   "mag": 1.8,
   "place": "6 km NNW of Redwood Valley, CA",
   "time": 1783089755260,
   "lon": -123.232498168945,
   "lat": 39.3123321533203,
   "depth": 3.88000011444092,
   "url": "https://earthquake.usgs.gov/earthquakes/eventpage/nc75388626"
  },
  {
   "mag": 1.8,
   "place": "17 km WNW of Willow, Alaska",
   "time": 1783079671539,
   "lon": -150.357,
   "lat": 61.797,
   "depth": 26.7,
   "url": "https://earthquake.usgs.gov/earthquakes/eventpage/aka2026naxvnq"
  },
  {
   "mag": 1.7,
   "place": "18 km NNW of Crane, Texas",
   "time": 1783148281246,
   "lon": -102.41,
   "lat": 31.558,
   "depth": 0,
   "url": "https://earthquake.usgs.gov/earthquakes/eventpage/tx2026nahmga"
  },
  {
   "mag": 1.7,
   "place": "58 km S of Cordova, Alaska",
   "time": 1783142493320,
   "lon": -145.566,
   "lat": 60.023,
   "depth": 12.3,
   "url": "https://earthquake.usgs.gov/earthquakes/eventpage/aka2026ncgtjw"
  },
  {
   "mag": 1.7,
   "place": "16 km NE of Yerington, Nevada",
   "time": 1783138305461,
   "lon": -119.0444,
   "lat": 39.0987,
   "depth": 9.998,
   "url": "https://earthquake.usgs.gov/earthquakes/eventpage/nn00921149"
  },
  {
   "mag": 1.7,
   "place": "31 km NW of Toyah, Texas",
   "time": 1783112578460,
   "lon": -104.009,
   "lat": 31.525,
   "depth": 4.22,
   "url": "https://earthquake.usgs.gov/earthquakes/eventpage/tx2026mzntja"
  },
  {
   "mag": 1.7,
   "place": "5 km NW of The Geysers, CA",
   "time": 1783086580500,
   "lon": -122.791496276855,
   "lat": 38.8098335266113,
   "depth": 2.91000008583069,
   "url": "https://earthquake.usgs.gov/earthquakes/eventpage/nc75388586"
  },
  {
   "mag": 1.7,
   "place": "8 km ENE of Blackhawk, CA",
   "time": 1783080144780,
   "lon": -121.830001831055,
   "lat": 37.8585014343262,
   "depth": 7.42000007629395,
   "url": "https://earthquake.usgs.gov/earthquakes/eventpage/nc75388551"
  },
  {
   "mag": 1.7,
   "place": "23 km NNE of Sterling City, Texas",
   "time": 1783068612372,
   "lon": -100.909,
   "lat": 32.041,
   "depth": 0,
   "url": "https://earthquake.usgs.gov/earthquakes/eventpage/tx2026myplys"
  },
  {
   "mag": 1.7,
   "place": "15 km ESE of Pearsall, Texas",
   "time": 1783068305684,
   "lon": -98.954,
   "lat": 28.823,
   "depth": 7.4047,
   "url": "https://earthquake.usgs.gov/earthquakes/eventpage/tx2026myphls"
  },
  {
   "mag": 1.6,
   "place": "4 km ESE of Nikiski, Alaska",
   "time": 1783118802837,
   "lon": -151.216,
   "lat": 60.675,
   "depth": 65.9,
   "url": "https://earthquake.usgs.gov/earthquakes/eventpage/aka2026nbtpaw"
  },
  {
   "mag": 1.6,
   "place": "62 km NNE of Aleneva, Alaska",
   "time": 1783117882070,
   "lon": -152.601,
   "lat": 58.601,
   "depth": 50.9,
   "url": "https://earthquake.usgs.gov/earthquakes/eventpage/aka2026nbtbsw"
  },
  {
   "mag": 1.6,
   "place": "14 km SE of Petrolia, CA",
   "time": 1783100112020,
   "lon": -124.179496765137,
   "lat": 40.232666015625,
   "depth": 12.5600004196167,
   "url": "https://earthquake.usgs.gov/earthquakes/eventpage/nc75388721"
  },
  {
   "mag": 1.6,
   "place": "19 km WSW of Charlotte, Texas",
   "time": 1783087720424,
   "lon": -98.897,
   "lat": 28.796,
   "depth": 8.4619,
   "url": "https://earthquake.usgs.gov/earthquakes/eventpage/tx2026mzaake"
  },
  {
   "mag": 1.5,
   "place": "11 km WSW of Corona, CA",
   "time": 1783132212570,
   "lon": -117.669833333333,
   "lat": 33.8133333333333,
   "depth": 4.47,
   "url": "https://earthquake.usgs.gov/earthquakes/eventpage/ci41286279"
  },
  {
   "mag": 1.5,
   "place": "19 km WSW of Johannesburg, CA",
   "time": 1783131174520,
   "lon": -117.817166666667,
   "lat": 35.298,
   "depth": 9.12,
   "url": "https://earthquake.usgs.gov/earthquakes/eventpage/ci41286263"
  },
  {
   "mag": 1.5,
   "place": "5 km NNW of Susitna North, Alaska",
   "time": 1783114661855,
   "lon": -149.9,
   "lat": 62.206,
   "depth": 22.3,
   "url": "https://earthquake.usgs.gov/earthquakes/eventpage/aka2026nbrhet"
  },
  {
   "mag": 1.5,
   "place": "93 km SE of Pope-Vannoy Landing, Alaska",
   "time": 1783105734714,
   "lon": -153.548,
   "lat": 58.871,
   "depth": 11.6,
   "url": "https://earthquake.usgs.gov/earthquakes/eventpage/aka2026nbmhvw"
  },
  {
   "mag": 1.5,
   "place": "6 km ESE of Chenega, Alaska",
   "time": 1783103116274,
   "lon": -147.902,
   "lat": 60.037,
   "depth": 30.5,
   "url": "https://earthquake.usgs.gov/earthquakes/eventpage/aka2026nbkwiu"
  },
  {
   "mag": 1.5,
   "place": "3 km ENE of Running Springs, CA",
   "time": 1783091244660,
   "lon": -117.077,
   "lat": 34.215,
   "depth": 3.57,
   "url": "https://earthquake.usgs.gov/earthquakes/eventpage/ci41286015"
  },
  {
   "mag": 1.5,
   "place": "57 km NW of Toyah, Texas",
   "time": 1783086664626,
   "lon": -104.266,
   "lat": 31.644,
   "depth": 6.51,
   "url": "https://earthquake.usgs.gov/earthquakes/eventpage/tx2026myzkla"
  },
  {
   "mag": 1.5,
   "place": "7 km WSW of Gilroy, CA",
   "time": 1783081608610,
   "lon": -121.635665893555,
   "lat": 36.9813346862793,
   "depth": 3.85999989509583,
   "url": "https://earthquake.usgs.gov/earthquakes/eventpage/nc75388571"
  },
  {
   "mag": 1.5,
   "place": "9 km NW of Redwood Valley, CA",
   "time": 1783078382790,
   "lon": -123.267501831055,
   "lat": 39.3291664123535,
   "depth": 6.90999984741211,
   "url": "https://earthquake.usgs.gov/earthquakes/eventpage/nc75388536"
  },
  {
   "mag": 1.5,
   "place": "47 km SW of Nanwalek, Alaska",
   "time": 1783076862516,
   "lon": -152.411,
   "lat": 59.012,
   "depth": 74,
   "url": "https://earthquake.usgs.gov/earthquakes/eventpage/aka2026nawgyn"
  },
  {
   "mag": 1.5,
   "place": "11 km WSW of Templeton, CA",
   "time": 1783071872440,
   "lon": -120.820663452148,
   "lat": 35.5238342285156,
   "depth": 5.80999994277954,
   "url": "https://earthquake.usgs.gov/earthquakes/eventpage/nc75388516"
  },
  {
   "mag": 1.5,
   "place": "2 km NNW of Cobb, CA",
   "time": 1783070422210,
   "lon": -122.731834411621,
   "lat": 38.8349990844727,
   "depth": -0.0299999993294477,
   "url": "https://earthquake.usgs.gov/earthquakes/eventpage/nc75388491"
  },
  {
   "mag": 1.5,
   "place": "70 km NW of Aleneva, Alaska",
   "time": 1783066010445,
   "lon": -153.596,
   "lat": 58.584,
   "depth": 77.7,
   "url": "https://earthquake.usgs.gov/earthquakes/eventpage/aka2026naqgdh"
  },
  {
   "mag": 1.4,
   "place": "67 km S of Cordova, Alaska",
   "time": 1783137263696,
   "lon": -145.551,
   "lat": 59.95,
   "depth": 16.5,
   "url": "https://earthquake.usgs.gov/earthquakes/eventpage/aka2026ncdvve"
  },
  {
   "mag": 1.4,
   "place": "11 km N of Redwood Valley, CA",
   "time": 1783130780410,
   "lon": -123.223831176758,
   "lat": 39.3638343811035,
   "depth": 7.1399998664856,
   "url": "https://earthquake.usgs.gov/earthquakes/eventpage/nc75389011"
  },
  {
   "mag": 1.4,
   "place": "58 km W of Anchor Point, Alaska",
   "time": 1783122101253,
   "lon": -152.863,
   "lat": 59.87,
   "depth": 97.8,
   "url": "https://earthquake.usgs.gov/earthquakes/eventpage/aka2026nbvkrw"
  },
  {
   "mag": 1.4,
   "place": "11 km NNW of Piru, CA",
   "time": 1783116422200,
   "lon": -118.829666666667,
   "lat": 34.5071666666667,
   "depth": 2.59,
   "url": "https://earthquake.usgs.gov/earthquakes/eventpage/ci41286183"
  },
  {
   "mag": 1.4,
   "place": "31 km SW of Petersville, Alaska",
   "time": 1783113190949,
   "lon": -151.213,
   "lat": 62.3,
   "depth": 74.7,
   "url": "https://earthquake.usgs.gov/earthquakes/eventpage/aka2026nbqlxy"
  },
  {
   "mag": 1.4,
   "place": "29 km W of Tyonek, Alaska",
   "time": 1783092879372,
   "lon": -151.673,
   "lat": 61.025,
   "depth": 76.3,
   "url": "https://earthquake.usgs.gov/earthquakes/eventpage/aka2026nbfekj"
  },
  {
   "mag": 1.4,
   "place": "1 km WNW of Universal City, CA",
   "time": 1783089018950,
   "lon": -118.364833333333,
   "lat": 34.1421666666667,
   "depth": 16.21,
   "url": "https://earthquake.usgs.gov/earthquakes/eventpage/ci41285999"
  },
  {
   "mag": 1.4,
   "place": "20 km NNW of Piru, CA",
   "time": 1783085919300,
   "lon": -118.887,
   "lat": 34.5826666666667,
   "depth": 2.08,
   "url": "https://earthquake.usgs.gov/earthquakes/eventpage/ci41285967"
  },
  {
   "mag": 1.4,
   "place": "2 km NNW of Cobb, CA",
   "time": 1783070572830,
   "lon": -122.732666015625,
   "lat": 38.8361663818359,
   "depth": 0.860000014305115,
   "url": "https://earthquake.usgs.gov/earthquakes/eventpage/nc75388496"
  },
  {
   "mag": 1.4,
   "place": "2 km NNE of Eureka Roadhouse, Alaska",
   "time": 1783066595626,
   "lon": -147.158,
   "lat": 61.961,
   "depth": 27.4,
   "url": "https://earthquake.usgs.gov/earthquakes/eventpage/aka2026naqnzw"
  },
  {
   "mag": 1.3,
   "place": "6 km NNW of The Geysers, CA",
   "time": 1783149326240,
   "lon": -122.789001464844,
   "lat": 38.820499420166,
   "depth": 0.910000026226044,
   "url": "https://earthquake.usgs.gov/earthquakes/eventpage/nc75389121"
  },
  {
   "mag": 1.3,
   "place": "43 km NNE of Chickaloon, Alaska",
   "time": 1783145361676,
   "lon": -148.194,
   "lat": 62.168,
   "depth": 17.8,
   "url": "https://earthquake.usgs.gov/earthquakes/eventpage/aka2026nciive"
  },
  {
   "mag": 1.3,
   "place": "43 km ESE of Pedro Bay, Alaska",
   "time": 1783142815612,
   "lon": -153.407,
   "lat": 59.616,
   "depth": 19.5,
   "url": "https://earthquake.usgs.gov/earthquakes/eventpage/aka2026ncgxzc"
  },
  {
   "mag": 1.3,
   "place": "32 km W of Olancha, CA",
   "time": 1783139727760,
   "lon": -118.3605,
   "lat": 36.226,
   "depth": 4.15,
   "url": "https://earthquake.usgs.gov/earthquakes/eventpage/ci41286327"
  },
  {
   "mag": 1.3,
   "place": "22 km NE of Chase, Alaska",
   "time": 1783134484559,
   "lon": -149.797,
   "lat": 62.597,
   "depth": 5,
   "url": "https://earthquake.usgs.gov/earthquakes/eventpage/aka2026ncchqq"
  },
  {
   "mag": 1.3,
   "place": "6 km WNW of Cobb, CA",
   "time": 1783110977480,
   "lon": -122.791168212891,
   "lat": 38.8354988098145,
   "depth": 2,
   "url": "https://earthquake.usgs.gov/earthquakes/eventpage/nc75388846"
  },
  {
   "mag": 1.3,
   "place": "93 km SE of Pope-Vannoy Landing, Alaska",
   "time": 1783109030926,
   "lon": -153.553,
   "lat": 58.87,
   "depth": 12.2,
   "url": "https://earthquake.usgs.gov/earthquakes/eventpage/aka2026nbodvl"
  },
  {
   "mag": 1.3,
   "place": "65 km WNW of Karluk, Alaska",
   "time": 1783103896557,
   "lon": -155.43,
   "lat": 57.838,
   "depth": 17.7,
   "url": "https://earthquake.usgs.gov/earthquakes/eventpage/aka2026nblhpw"
  },
  {
   "mag": 1.3,
   "place": "27 km NW of Beluga, Alaska",
   "time": 1783103789357,
   "lon": -151.452,
   "lat": 61.316,
   "depth": 79.6,
   "url": "https://earthquake.usgs.gov/earthquakes/eventpage/aka2026nblgbk"
  },
  {
   "mag": 1.3,
   "place": "17 km ESE of Anza, CA",
   "time": 1783093849480,
   "lon": -116.509166666667,
   "lat": 33.482,
   "depth": 11.59,
   "url": "https://earthquake.usgs.gov/earthquakes/eventpage/ci41286023"
  },
  {
   "mag": 1.3,
   "place": "5 km NW of The Geysers, CA",
   "time": 1783086603270,
   "lon": -122.791496276855,
   "lat": 38.8105010986328,
   "depth": 3.13000011444092,
   "url": "https://earthquake.usgs.gov/earthquakes/eventpage/nc75388591"
  },
  {
   "mag": 1.2,
   "place": "13 km N of Ocotillo Wells, CA",
   "time": 1783129008730,
   "lon": -116.125833333333,
   "lat": 33.2591666666667,
   "depth": 8.27,
   "url": "https://earthquake.usgs.gov/earthquakes/eventpage/ci41286247"
  },
  {
   "mag": 1.2,
   "place": "9 km WNW of The Geysers, CA",
   "time": 1783125240170,
   "lon": -122.841499328613,
   "lat": 38.8194999694824,
   "depth": 2.15000009536743,
   "url": "https://earthquake.usgs.gov/earthquakes/eventpage/nc75388941"
  },
  {
   "mag": 1.2,
   "place": "34 km WSW of Salamatof, Alaska",
   "time": 1783124312193,
   "lon": -151.906,
   "lat": 60.499,
   "depth": 80.2,
   "url": "https://earthquake.usgs.gov/earthquakes/eventpage/aka2026nbwqqr"
  },
  {
   "mag": 1.2,
   "place": "10 km NE of Hoodsport, Washington",
   "time": 1783120240990,
   "lon": -123.036666666667,
   "lat": 47.4658333333333,
   "depth": 7.28,
   "url": "https://earthquake.usgs.gov/earthquakes/eventpage/uw714040502"
  },
  {
   "mag": 1.2,
   "place": "11 km ENE of Adelanto, CA",
   "time": 1783097660050,
   "lon": -117.306333333333,
   "lat": 34.639,
   "depth": -0.69,
   "url": "https://earthquake.usgs.gov/earthquakes/eventpage/ci41286063"
  },
  {
   "mag": 1.2,
   "place": "25 km ESE of Ocotillo Wells, CA",
   "time": 1783094771560,
   "lon": -115.880833333333,
   "lat": 33.0766666666667,
   "depth": 2.09,
   "url": "https://earthquake.usgs.gov/earthquakes/eventpage/ci41286039"
  },
  {
   "mag": 1.2,
   "place": "16 km ENE of San Martin, CA",
   "time": 1783089831870,
   "lon": -121.440498352051,
   "lat": 37.1303329467773,
   "depth": 4.48000001907349,
   "url": "https://earthquake.usgs.gov/earthquakes/eventpage/nc75388631"
  },
  {
   "mag": 1.2,
   "place": "35 km SE of Malaga, New Mexico",
   "time": 1783085124780,
   "lon": -103.788,
   "lat": 32.008,
   "depth": 7.9456,
   "url": "https://earthquake.usgs.gov/earthquakes/eventpage/tx2026myypbv"
  },
  {
   "mag": 1.2,
   "place": "2 km NNW of Cobb, CA",
   "time": 1783070864960,
   "lon": -122.731330871582,
   "lat": 38.8370018005371,
   "depth": 0.389999985694885,
   "url": "https://earthquake.usgs.gov/earthquakes/eventpage/nc75388506"
  },
  {
   "mag": 1.2,
   "place": "7 km NW of The Geysers, CA",
   "time": 1783070071000,
   "lon": -122.807502746582,
   "lat": 38.8253326416016,
   "depth": 2.57999992370605,
   "url": "https://earthquake.usgs.gov/earthquakes/eventpage/nc75388486"
  },
  {
   "mag": 1.1,
   "place": "7 km NW of Sutton-Alpine, Alaska",
   "time": 1783148024012,
   "lon": -148.86,
   "lat": 61.831,
   "depth": 6.2,
   "url": "https://earthquake.usgs.gov/earthquakes/eventpage/aka2026ncjvhr"
  },
  {
   "mag": 1.1,
   "place": "5 km NW of The Geysers, CA",
   "time": 1783146403070,
   "lon": -122.795166015625,
   "lat": 38.8160018920898,
   "depth": 2.6800000667572,
   "url": "https://earthquake.usgs.gov/earthquakes/eventpage/nc75389111"
  },
  {
   "mag": 1.1,
   "place": "11 km NNW of Hollister, CA",
   "time": 1783144861810,
   "lon": -121.431999206543,
   "lat": 36.9456672668457,
   "depth": 4.71999979019165,
   "url": "https://earthquake.usgs.gov/earthquakes/eventpage/nc75389106"
  },
  {
   "mag": 1.1,
   "place": "5 km NE of Odessa, Texas",
   "time": 1783144380406,
   "lon": -102.335,
   "lat": 31.884,
   "depth": 5.8426,
   "url": "https://earthquake.usgs.gov/earthquakes/eventpage/tx2026nafidl"
  },
  {
   "mag": 1.1,
   "place": "62 km S of Whites City, New Mexico",
   "time": 1783130395424,
   "lon": -104.496,
   "lat": 31.619,
   "depth": 4.2705,
   "url": "https://earthquake.usgs.gov/earthquakes/eventpage/tx2026mzxpdb"
  },
  {
   "mag": 1.1,
   "place": "3 km NW of The Geysers, CA",
   "time": 1783127607090,
   "lon": -122.785003662109,
   "lat": 38.796501159668,
   "depth": 3.57999992370605,
   "url": "https://earthquake.usgs.gov/earthquakes/eventpage/nc75388971"
  },
  {
   "mag": 1.1,
   "place": "13 km NE of Napa, CA",
   "time": 1783103694480,
   "lon": -122.192832946777,
   "lat": 38.3904991149902,
   "depth": 2.49000000953674,
   "url": "https://earthquake.usgs.gov/earthquakes/eventpage/nc75388761"
  },
  {
   "mag": 1.1,
   "place": "37 km ENE of McKinney Acres, Texas",
   "time": 1783103532049,
   "lon": -102.155,
   "lat": 32.428,
   "depth": 6.3167,
   "url": "https://earthquake.usgs.gov/earthquakes/eventpage/tx2026mzitgp"
  },
  {
   "mag": 1.1,
   "place": "21 km ESE of Little Lake, CA",
   "time": 1783102556090,
   "lon": -117.686833333333,
   "lat": 35.8806666666667,
   "depth": 4.08,
   "url": "https://earthquake.usgs.gov/earthquakes/eventpage/ci41286135"
  },
  {
   "mag": 1.1,
   "place": "3 km ENE of Running Springs, CA",
   "time": 1783099821610,
   "lon": -117.0745,
   "lat": 34.2156666666667,
   "depth": 3.77,
   "url": "https://earthquake.usgs.gov/earthquakes/eventpage/ci41286095"
  },
  {
   "mag": 1.1,
   "place": "6 km WNW of Cobb, CA",
   "time": 1783098251200,
   "lon": -122.794830322266,
   "lat": 38.8375015258789,
   "depth": 2.15000009536743,
   "url": "https://earthquake.usgs.gov/earthquakes/eventpage/nc75388696"
  },
  {
   "mag": 1.1,
   "place": "20 km NNW of Piru, CA",
   "time": 1783086199070,
   "lon": -118.885833333333,
   "lat": 34.581,
   "depth": 2.2,
   "url": "https://earthquake.usgs.gov/earthquakes/eventpage/ci41285975"
  },
  {
   "mag": 1.1,
   "place": "74 km WNW of Karluk, Alaska",
   "time": 1783084761783,
   "lon": -155.6,
   "lat": 57.844,
   "depth": 91.2,
   "url": "https://earthquake.usgs.gov/earthquakes/eventpage/aka2026nbarci"
  },
  {
   "mag": 1.1,
   "place": "10 km NE of San Martin, CA",
   "time": 1783076917420,
   "lon": -121.516334533691,
   "lat": 37.140998840332,
   "depth": 10.039999961853,
   "url": "https://earthquake.usgs.gov/earthquakes/eventpage/nc75388531"
  },
  {
   "mag": 1.1,
   "place": "7 km NW of The Geysers, CA",
   "time": 1783073812090,
   "lon": -122.811996459961,
   "lat": 38.818000793457,
   "depth": 2.75999999046326,
   "url": "https://earthquake.usgs.gov/earthquakes/eventpage/nc75388521"
  },
  {
   "mag": 1.1,
   "place": "89 km NNW of Aleneva, Alaska",
   "time": 1783069043032,
   "lon": -153.637,
   "lat": 58.772,
   "depth": 5,
   "url": "https://earthquake.usgs.gov/earthquakes/eventpage/aka2026narxyo"
  },
  {
   "mag": 1.0,
   "place": "22 km S of Borrego Springs, CA",
   "time": 1783139983050,
   "lon": -116.3615,
   "lat": 33.0573333333333,
   "depth": 12.27,
   "url": "https://earthquake.usgs.gov/earthquakes/eventpage/ci41286335"
  },
  {
   "mag": 1.0,
   "place": "22 km E of Julian, CA",
   "time": 1783137217220,
   "lon": -116.365166666667,
   "lat": 33.0526666666667,
   "depth": 13.42,
   "url": "https://earthquake.usgs.gov/earthquakes/eventpage/ci41286303"
  },
  {
   "mag": 1,
   "place": "6 km NW of The Geysers, CA",
   "time": 1783136963640,
   "lon": -122.796501159668,
   "lat": 38.8175010681152,
   "depth": 2.34999990463257,
   "url": "https://earthquake.usgs.gov/earthquakes/eventpage/nc75389066"
  },
  {
   "mag": 1.0,
   "place": "4 km SW of Devore, CA",
   "time": 1783122297320,
   "lon": -117.437666666667,
   "lat": 34.1961666666667,
   "depth": 9.81,
   "url": "https://earthquake.usgs.gov/earthquakes/eventpage/ci41286207"
  },
  {
   "mag": 1,
   "place": "7 km E of Fox, Alaska",
   "time": 1783115287340,
   "lon": -147.457,
   "lat": 64.954,
   "depth": 5,
   "url": "https://earthquake.usgs.gov/earthquakes/eventpage/aka2026nbrqfr"
  },
  {
   "mag": 1.0,
   "place": "144 km W of Adak, Alaska",
   "time": 1783113546810,
   "lon": -178.734833333333,
   "lat": 51.824,
   "depth": 14.71,
   "url": "https://earthquake.usgs.gov/earthquakes/eventpage/av94286803"
  },
  {
   "mag": 1,
   "place": "1 km ESE of The Geysers, CA",
   "time": 1783111268020,
   "lon": -122.743835449219,
   "lat": 38.7736663818359,
   "depth": 2.34999990463257,
   "url": "https://earthquake.usgs.gov/earthquakes/eventpage/nc75388851"
  },
  {
   "mag": 1,
   "place": "88 km WNW of Aleneva, Alaska",
   "time": 1783098893473,
   "lon": -154.256,
   "lat": 58.421,
   "depth": 5,
   "url": "https://earthquake.usgs.gov/earthquakes/eventpage/aka2026nbinie"
  },
  {
   "mag": 1,
   "place": "19 km NNE of Four Mile Road, Alaska",
   "time": 1783095968153,
   "lon": -148.919,
   "lat": 64.752,
   "depth": 1.2,
   "url": "https://earthquake.usgs.gov/earthquakes/eventpage/aka2026nbgxaw"
  },
  {
   "mag": 1.0,
   "place": "18 km ESE of Anza, CA",
   "time": 1783093868410,
   "lon": -116.502,
   "lat": 33.4836666666667,
   "depth": 11.54,
   "url": "https://earthquake.usgs.gov/earthquakes/eventpage/ci41286031"
  },
  {
   "mag": 1.0,
   "place": "5 km WNW of Cobb, CA",
   "time": 1783088967220,
   "lon": -122.783996582031,
   "lat": 38.8356666564941,
   "depth": 2.64000010490417,
   "url": "https://earthquake.usgs.gov/earthquakes/eventpage/nc75388621"
  },
  {
   "mag": 1.0,
   "place": "7 km NW of The Geysers, CA",
   "time": 1783087414720,
   "lon": -122.809997558594,
   "lat": 38.8248329162598,
   "depth": 1.98000001907349,
   "url": "https://earthquake.usgs.gov/earthquakes/eventpage/nc75388601"
  },
  {
   "mag": 1.0,
   "place": "15 km SSW of Searles Valley, CA",
   "time": 1783084563470,
   "lon": -117.459833333333,
   "lat": 35.6378333333333,
   "depth": 6.44,
   "url": "https://earthquake.usgs.gov/earthquakes/eventpage/ci41285951"
  },
  {
   "mag": 1.0,
   "place": "12 km N of Ocotillo Wells, CA",
   "time": 1783080892610,
   "lon": -116.124666666667,
   "lat": 33.2541666666667,
   "depth": 6.58,
   "url": "https://earthquake.usgs.gov/earthquakes/eventpage/ci41285943"
  },
  {
   "mag": 1.0,
   "place": "2 km NNW of Cobb, CA",
   "time": 1783070851790,
   "lon": -122.731498718262,
   "lat": 38.8368339538574,
   "depth": 0.569999992847443,
   "url": "https://earthquake.usgs.gov/earthquakes/eventpage/nc75388501"
  },
  {
   "mag": 0.9,
   "place": "22 km S of Borrego Springs, CA",
   "time": 1783143842230,
   "lon": -116.359833333333,
   "lat": 33.0565,
   "depth": 12.97,
   "url": "https://earthquake.usgs.gov/earthquakes/eventpage/ci41286351"
  },
  {
   "mag": 0.9,
   "place": "4 km WSW of Carpinteria, CA",
   "time": 1783138104300,
   "lon": -119.559333333333,
   "lat": 34.3886666666667,
   "depth": 11.4,
   "url": "https://earthquake.usgs.gov/earthquakes/eventpage/ci41286311"
  },
  {
   "mag": 0.9,
   "place": "17 km WSW of Johannesburg, CA",
   "time": 1783122533910,
   "lon": -117.800333333333,
   "lat": 35.304,
   "depth": 6.13,
   "url": "https://earthquake.usgs.gov/earthquakes/eventpage/ci41286215"
  },
  {
   "mag": 0.9,
   "place": "6 km NW of The Geysers, CA",
   "time": 1783115846990,
   "lon": -122.80549621582,
   "lat": 38.8185005187988,
   "depth": 3.19000005722046,
   "url": "https://earthquake.usgs.gov/earthquakes/eventpage/nc75388881"
  },
  {
   "mag": 0.9,
   "place": "16 km NNE of Thousand Palms, CA",
   "time": 1783112956580,
   "lon": -116.314333333333,
   "lat": 33.9538333333333,
   "depth": 8.94,
   "url": "https://earthquake.usgs.gov/earthquakes/eventpage/ci41286167"
  },
  {
   "mag": 0.9,
   "place": "15 km NNW of Midland, Texas",
   "time": 1783110683599,
   "lon": -102.17,
   "lat": 32.115,
   "depth": 4.6318,
   "url": "https://earthquake.usgs.gov/earthquakes/eventpage/tx2026mzmscy"
  },
  {
   "mag": 0.9,
   "place": "50 km NW of Beluga, Alaska",
   "time": 1783108421849,
   "lon": -151.754,
   "lat": 61.458,
   "depth": 6.3,
   "url": "https://earthquake.usgs.gov/earthquakes/eventpage/aka2026nbnuym"
  },
  {
   "mag": 0.9,
   "place": "3 km ENE of Running Springs, CA",
   "time": 1783100085610,
   "lon": -117.0755,
   "lat": 34.2146666666667,
   "depth": 3.64,
   "url": "https://earthquake.usgs.gov/earthquakes/eventpage/ci41286119"
  },
  {
   "mag": 0.9,
   "place": "14 km WSW of Stanton, Texas",
   "time": 1783097518135,
   "lon": -101.933,
   "lat": 32.097,
   "depth": 7.9346,
   "url": "https://earthquake.usgs.gov/earthquakes/eventpage/tx2026mzfkzi"
  },
  {
   "mag": 0.9,
   "place": "13 km WSW of Stanton, Texas",
   "time": 1783080116030,
   "lon": -101.931,
   "lat": 32.101,
   "depth": 8.9111,
   "url": "https://earthquake.usgs.gov/earthquakes/eventpage/tx2026myvvez"
  },
  {
   "mag": 0.9,
   "place": "16 km SSW of Nixon, Texas",
   "time": 1783066796962,
   "lon": -97.805,
   "lat": 29.124,
   "depth": 8.8236,
   "url": "https://earthquake.usgs.gov/earthquakes/eventpage/tx2026myolxn"
  },
  {
   "mag": 0.8,
   "place": "11 km WNW of Cobb, CA",
   "time": 1783150299040,
   "lon": -122.84049987793,
   "lat": 38.8530006408691,
   "depth": 1.01999998092651,
   "url": "https://earthquake.usgs.gov/earthquakes/eventpage/nc75389131"
  },
  {
   "mag": 0.8,
   "place": "4 km NW of The Geysers, CA",
   "time": 1783146790410,
   "lon": -122.780166625977,
   "lat": 38.8038330078125,
   "depth": 3.35999989509583,
   "url": "https://earthquake.usgs.gov/earthquakes/eventpage/nc75389116"
  },
  {
   "mag": 0.8,
   "place": "4 km W of Lake Arrowhead, CA",
   "time": 1783145384760,
   "lon": -117.236333333333,
   "lat": 34.2551666666667,
   "depth": 21.15,
   "url": "https://earthquake.usgs.gov/earthquakes/eventpage/ci41286359"
  },
  {
   "mag": 0.8,
   "place": "13 km N of Ocotillo Wells, CA",
   "time": 1783129223410,
   "lon": -116.128,
   "lat": 33.2621666666667,
   "depth": 6.98,
   "url": "https://earthquake.usgs.gov/earthquakes/eventpage/ci41286255"
  },
  {
   "mag": 0.8,
   "place": "2 km N of The Geysers, CA",
   "time": 1783128041450,
   "lon": -122.759162902832,
   "lat": 38.7949981689453,
   "depth": 1.24000000953674,
   "url": "https://earthquake.usgs.gov/earthquakes/eventpage/nc75388981"
  },
  {
   "mag": 0.8,
   "place": "8 km ENE of Desert Hot Springs, CA",
   "time": 1783124530810,
   "lon": -116.416333333333,
   "lat": 33.9778333333333,
   "depth": 7.19,
   "url": "https://earthquake.usgs.gov/earthquakes/eventpage/ci41286231"
  },
  {
   "mag": 0.8,
   "place": "14 km NNW of Borrego Springs, CA",
   "time": 1783118659260,
   "lon": -116.4065,
   "lat": 33.3776666666667,
   "depth": 9.49,
   "url": "https://earthquake.usgs.gov/earthquakes/eventpage/ci41286199"
  },
  {
   "mag": 0.8,
   "place": "4 km W of Cobb, CA",
   "time": 1783112737890,
   "lon": -122.763832092285,
   "lat": 38.8224983215332,
   "depth": 2.47000002861023,
   "url": "https://earthquake.usgs.gov/earthquakes/eventpage/nc75388866"
  },
  {
   "mag": 0.8,
   "place": "5 km WNW of The Geysers, CA",
   "time": 1783107605870,
   "lon": -122.804168701172,
   "lat": 38.7938346862793,
   "depth": 1.5,
   "url": "https://earthquake.usgs.gov/earthquakes/eventpage/nc75388821"
  },
  {
   "mag": 0.8,
   "place": "7 km NW of The Geysers, CA",
   "time": 1783105295410,
   "lon": -122.820167541504,
   "lat": 38.8228340148926,
   "depth": 12.2600002288818,
   "url": "https://earthquake.usgs.gov/earthquakes/eventpage/nc75388786"
  },
  {
   "mag": 0.8,
   "place": "5 km NW of The Geysers, CA",
   "time": 1783092839580,
   "lon": -122.791496276855,
   "lat": 38.8113327026367,
   "depth": 3.17000007629395,
   "url": "https://earthquake.usgs.gov/earthquakes/eventpage/nc75388656"
  },
  {
   "mag": 0.8,
   "place": "3 km SW of Redlands, CA",
   "time": 1783089355740,
   "lon": -117.204,
   "lat": 34.0305,
   "depth": 12.34,
   "url": "https://earthquake.usgs.gov/earthquakes/eventpage/ci41286007"
  },
  {
   "mag": 0.8,
   "place": "7 km NW of The Geysers, CA",
   "time": 1783087651870,
   "lon": -122.806999206543,
   "lat": 38.8238334655762,
   "depth": 2.72000002861023,
   "url": "https://earthquake.usgs.gov/earthquakes/eventpage/nc75388606"
  },
  {
   "mag": 0.8,
   "place": "5 km WNW of The Geysers, CA",
   "time": 1783069003930,
   "lon": -122.813331604004,
   "lat": 38.7970008850098,
   "depth": 3.49000000953674,
   "url": "https://earthquake.usgs.gov/earthquakes/eventpage/nc75388476"
  },
  {
   "mag": 0.8,
   "place": "6 km NW of The Geysers, CA",
   "time": 1783068810530,
   "lon": -122.812164306641,
   "lat": 38.8121681213379,
   "depth": 2.5699999332428,
   "url": "https://earthquake.usgs.gov/earthquakes/eventpage/nc75388471"
  },
  {
   "mag": 0.7,
   "place": "9 km N of Borrego Springs, CA",
   "time": 1783149241700,
   "lon": -116.382833333333,
   "lat": 33.334,
   "depth": 11.9,
   "url": "https://earthquake.usgs.gov/earthquakes/eventpage/ci41286391"
  },
  {
   "mag": 0.7,
   "place": "7 km WNW of Cobb, CA",
   "time": 1783140526820,
   "lon": -122.800163269043,
   "lat": 38.8363342285156,
   "depth": 2.17000007629395,
   "url": "https://earthquake.usgs.gov/earthquakes/eventpage/nc75389091"
  },
  {
   "mag": 0.7,
   "place": "13 km NE of Little Lake, CA",
   "time": 1783139453340,
   "lon": -117.804166666667,
   "lat": 36.0215,
   "depth": 1.45,
   "url": "https://earthquake.usgs.gov/earthquakes/eventpage/ci41286319"
  },
  {
   "mag": 0.7,
   "place": "3 km NW of The Geysers, CA",
   "time": 1783137449700,
   "lon": -122.780670166016,
   "lat": 38.8011665344238,
   "depth": 3.03999996185303,
   "url": "https://earthquake.usgs.gov/earthquakes/eventpage/nc75389071"
  },
  {
   "mag": 0.7,
   "place": "13 km N of Ocotillo Wells, CA",
   "time": 1783128317810,
   "lon": -116.121666666667,
   "lat": 33.2588333333333,
   "depth": 8.94,
   "url": "https://earthquake.usgs.gov/earthquakes/eventpage/ci41286239"
  },
  {
   "mag": 0.7,
   "place": "15 km SE of Mammoth Lakes, CA",
   "time": 1783104326930,
   "lon": -118.875666666667,
   "lat": 37.527,
   "depth": 5.09,
   "url": "https://earthquake.usgs.gov/earthquakes/eventpage/nc75388776"
  },
  {
   "mag": 0.7,
   "place": "23 km E of Tres Pinos, CA",
   "time": 1783101246740,
   "lon": -121.068168640137,
   "lat": 36.7598342895508,
   "depth": 9.85999965667725,
   "url": "https://earthquake.usgs.gov/earthquakes/eventpage/nc75388726"
  },
  {
   "mag": 0.7,
   "place": "10 km NNW of Anza, CA",
   "time": 1783088906750,
   "lon": -116.708833333333,
   "lat": 33.6443333333333,
   "depth": 13.49,
   "url": "https://earthquake.usgs.gov/earthquakes/eventpage/ci41285991"
  },
  {
   "mag": 0.7,
   "place": "8 km WNW of Cobb, CA",
   "time": 1783081430010,
   "lon": -122.808166503906,
   "lat": 38.837833404541,
   "depth": 2.24000000953674,
   "url": "https://earthquake.usgs.gov/earthquakes/eventpage/nc75388566"
  },
  {
   "mag": 0.7,
   "place": "13 km N of Ocotillo Wells, CA",
   "time": 1783080838790,
   "lon": -116.119,
   "lat": 33.256,
   "depth": 7.51,
   "url": "https://earthquake.usgs.gov/earthquakes/eventpage/ci41285935"
  },
  {
   "mag": 0.7,
   "place": "18 km NW of Stanton, Texas",
   "time": 1783078008085,
   "lon": -101.909,
   "lat": 32.26,
   "depth": 7.9346,
   "url": "https://earthquake.usgs.gov/earthquakes/eventpage/tx2026myuoel"
  },
  {
   "mag": 0.7,
   "place": "22 km NNW of Midland, Texas",
   "time": 1783074678134,
   "lon": -102.162,
   "lat": 32.185,
   "depth": 8.9111,
   "url": "https://earthquake.usgs.gov/earthquakes/eventpage/tx2026mystbq"
  },
  {
   "mag": 0.7,
   "place": "32 km E of McKinney Acres, Texas",
   "time": 1783074323248,
   "lon": -102.188,
   "lat": 32.354,
   "depth": 8.4229,
   "url": "https://earthquake.usgs.gov/earthquakes/eventpage/tx2026myspzh"
  },
  {
   "mag": 0.7,
   "place": "9 km WNW of The Geysers, CA",
   "time": 1783067556470,
   "lon": -122.842666625977,
   "lat": 38.8196678161621,
   "depth": 2.32999992370605,
   "url": "https://earthquake.usgs.gov/earthquakes/eventpage/nc75388461"
  },
  {
   "mag": 0.6,
   "place": "11 km ENE of Ridgecrest, CA",
   "time": 1783146800370,
   "lon": -117.557833333333,
   "lat": 35.6445,
   "depth": 5.83,
   "url": "https://earthquake.usgs.gov/earthquakes/eventpage/ci41286383"
  },
  {
   "mag": 0.6,
   "place": "6 km SE of Loma Linda, CA",
   "time": 1783135806920,
   "lon": -117.219333333333,
   "lat": 34.0013333333333,
   "depth": 4.59,
   "url": "https://earthquake.usgs.gov/earthquakes/eventpage/ci41286295"
  },
  {
   "mag": 0.6,
   "place": "11 km NE of Julian, CA",
   "time": 1783135709720,
   "lon": -116.5155,
   "lat": 33.15,
   "depth": 8.6,
   "url": "https://earthquake.usgs.gov/earthquakes/eventpage/ci41286287"
  },
  {
   "mag": 0.6,
   "place": "20 km SE of Midland, Texas",
   "time": 1783089290294,
   "lon": -101.911,
   "lat": 31.876,
   "depth": 5.7861,
   "url": "https://earthquake.usgs.gov/earthquakes/eventpage/tx2026mzawxq"
  },
  {
   "mag": 0.6,
   "place": "11 km NE of Julian, CA",
   "time": 1783068472010,
   "lon": -116.527666666667,
   "lat": 33.1528333333333,
   "depth": 6.27,
   "url": "https://earthquake.usgs.gov/earthquakes/eventpage/ci41285919"
  },
  {
   "mag": 0.5,
   "place": "151 km W of Adak, Alaska",
   "time": 1783106173290,
   "lon": -178.823333333333,
   "lat": 51.7871666666667,
   "depth": 10.91,
   "url": "https://earthquake.usgs.gov/earthquakes/eventpage/av94286588"
  },
  {
   "mag": 0.5,
   "place": "9 km SW of Idyllwild, CA",
   "time": 1783098442850,
   "lon": -116.792333333333,
   "lat": 33.6811666666667,
   "depth": 15.14,
   "url": "https://earthquake.usgs.gov/earthquakes/eventpage/ci41286079"
  },
  {
   "mag": 0.5,
   "place": "149 km W of Adak, Alaska",
   "time": 1783073600040,
   "lon": -178.800666666667,
   "lat": 51.7856666666667,
   "depth": 4.94,
   "url": "https://earthquake.usgs.gov/earthquakes/eventpage/av94285678"
  },
  {
   "mag": 0.4,
   "place": "5 km WSW of Anza, CA",
   "time": 1783099430500,
   "lon": -116.728666666667,
   "lat": 33.5413333333333,
   "depth": 8.69,
   "url": "https://earthquake.usgs.gov/earthquakes/eventpage/ci41286087"
  },
  {
   "mag": 0.3,
   "place": "9 km WNW of The Geysers, CA",
   "time": 1783136312810,
   "lon": -122.847503662109,
   "lat": 38.8211669921875,
   "depth": 2.44000005722046,
   "url": "https://earthquake.usgs.gov/earthquakes/eventpage/nc75389056"
  },
  {
   "mag": 0.3,
   "place": "10 km NW of The Geysers, CA",
   "time": 1783107258990,
   "lon": -122.839,
   "lat": 38.841,
   "depth": 2.43,
   "url": "https://earthquake.usgs.gov/earthquakes/eventpage/nc75388806"
  },
  {
   "mag": 0.1,
   "place": "155 km W of Adak, Alaska",
   "time": 1783108537170,
   "lon": -178.878833333333,
   "lat": 51.7608333333333,
   "depth": 10.27,
   "url": "https://earthquake.usgs.gov/earthquakes/eventpage/av94286658"
  },
  {
   "mag": 0.1,
   "place": "153 km W of Adak, Alaska",
   "time": 1783107803150,
   "lon": -178.862333333333,
   "lat": 51.7875,
   "depth": 8.49,
   "url": "https://earthquake.usgs.gov/earthquakes/eventpage/av94286618"
  },
  {
   "mag": 0,
   "place": "150 km W of Adak, Alaska",
   "time": 1783088651460,
   "lon": -178.8175,
   "lat": 51.804,
   "depth": 6.63,
   "url": "https://earthquake.usgs.gov/earthquakes/eventpage/av94286128"
  }
 ]
}