{
 "updated": "2026-06-24T23:45:43.951662+00:00",
 "count": 325,
 "max": 7.5,
 "items": [
  {
   "mag": 7.5,
   "place": "23 km SE of Yumare, Venezuela",
   "time": 1782338712092,
   "lon": -68.5139,
   "lat": 10.453,
   "depth": 10,
   "url": "https://earthquake.usgs.gov/earthquakes/eventpage/us6000t7zp"
  },
  {
   "mag": 7.2,
   "place": "24 km ENE of San Felipe, Venezuela",
   "time": 1782338673586,
   "lon": -68.52,
   "lat": 10.3874,
   "depth": 21.896,
   "url": "https://earthquake.usgs.gov/earthquakes/eventpage/us6000t7zc"
  },
  {
   "mag": 6.9,
   "place": "35 km ENE of Kuji, Japan",
   "time": 1782340215418,
   "lon": 142.132,
   "lat": 40.3462,
   "depth": 51.709,
   "url": "https://earthquake.usgs.gov/earthquakes/eventpage/us6000t7zq"
  },
  {
   "mag": 5.6,
   "place": "11 km N of Redwood Valley, CA",
   "time": 1782313840760,
   "lon": -123.228833333333,
   "lat": 39.3623333333333,
   "depth": 8.85,
   "url": "https://earthquake.usgs.gov/earthquakes/eventpage/nc75382936"
  },
  {
   "mag": 5.1,
   "place": "61 km SSW of Panguna, Papua New Guinea",
   "time": 1782281842718,
   "lon": 155.1762,
   "lat": -6.7815,
   "depth": 70.1,
   "url": "https://earthquake.usgs.gov/earthquakes/eventpage/us6000t7t2"
  },
  {
   "mag": 5,
   "place": "71 km WNW of Catuday, Philippines",
   "time": 1782266689661,
   "lon": 119.1731,
   "lat": 16.5122,
   "depth": 10,
   "url": "https://earthquake.usgs.gov/earthquakes/eventpage/us6000t7rx"
  },
  {
   "mag": 4.9,
   "place": "1 km E of El Palmarcito, Mexico",
   "time": 1782303391673,
   "lon": -93.197,
   "lat": 15.4949,
   "depth": 93.488,
   "url": "https://earthquake.usgs.gov/earthquakes/eventpage/us6000t7uf"
  },
  {
   "mag": 4.9,
   "place": "28 km SE of Fry, Greece",
   "time": 1782289554497,
   "lon": 27.1649,
   "lat": 35.2481,
   "depth": 10,
   "url": "https://earthquake.usgs.gov/earthquakes/eventpage/us6000t7tc"
  },
  {
   "mag": 4.9,
   "place": "64 km WNW of Catuday, Philippines",
   "time": 1782264859440,
   "lon": 119.2436,
   "lat": 16.5023,
   "depth": 10,
   "url": "https://earthquake.usgs.gov/earthquakes/eventpage/us6000t7rq"
  },
  {
   "mag": 4.8,
   "place": "78 km SSW of Lumatil, Philippines",
   "time": 1782271926910,
   "lon": 124.6956,
   "lat": 5.194,
   "depth": 35,
   "url": "https://earthquake.usgs.gov/earthquakes/eventpage/us6000t7s8"
  },
  {
   "mag": 4.8,
   "place": "61 km WNW of Catuday, Philippines",
   "time": 1782265048257,
   "lon": 119.2597,
   "lat": 16.457,
   "depth": 10,
   "url": "https://earthquake.usgs.gov/earthquakes/eventpage/us6000t7ru"
  },
  {
   "mag": 4.8,
   "place": "52 km WNW of Catuday, Philippines",
   "time": 1782258917095,
   "lon": 119.3422,
   "lat": 16.461,
   "depth": 10,
   "url": "https://earthquake.usgs.gov/earthquakes/eventpage/us6000t7rf"
  },
  {
   "mag": 4.6,
   "place": "41 km NE of San Fernando, Peru",
   "time": 1782318359573,
   "lon": -74.2589,
   "lat": -8.1501,
   "depth": 167.918,
   "url": "https://earthquake.usgs.gov/earthquakes/eventpage/us6000t7wm"
  },
  {
   "mag": 4.6,
   "place": "287 km S of Ambon, Indonesia",
   "time": 1782271616139,
   "lon": 128.5566,
   "lat": -6.2707,
   "depth": 344.617,
   "url": "https://earthquake.usgs.gov/earthquakes/eventpage/us6000t7s7"
  },
  {
   "mag": 4.6,
   "place": "south of the Fiji Islands",
   "time": 1782261618966,
   "lon": -179.7705,
   "lat": -24.2534,
   "depth": 489.864,
   "url": "https://earthquake.usgs.gov/earthquakes/eventpage/us6000t7rn"
  },
  {
   "mag": 4.5,
   "place": "123 km NE of Tobelo, Indonesia",
   "time": 1782334975207,
   "lon": 128.7113,
   "lat": 2.5942,
   "depth": 258.866,
   "url": "https://earthquake.usgs.gov/earthquakes/eventpage/us6000t7yv"
  },
  {
   "mag": 4.5,
   "place": "south of the Fiji Islands",
   "time": 1782307174898,
   "lon": 179.8323,
   "lat": -25.1509,
   "depth": 512.681,
   "url": "https://earthquake.usgs.gov/earthquakes/eventpage/us6000t7un"
  },
  {
   "mag": 4.5,
   "place": "64 km WNW of Catuday, Philippines",
   "time": 1782298288685,
   "lon": 119.2775,
   "lat": 16.574,
   "depth": 10,
   "url": "https://earthquake.usgs.gov/earthquakes/eventpage/us6000t7u2"
  },
  {
   "mag": 4.5,
   "place": "8 km NNE of La Serena, Chile",
   "time": 1782297394167,
   "lon": -71.2145,
   "lat": -29.8291,
   "depth": 59.354,
   "url": "https://earthquake.usgs.gov/earthquakes/eventpage/us6000t7tx"
  },
  {
   "mag": 4.5,
   "place": "17 km SSE of El Hoyo, Argentina",
   "time": 1782291420388,
   "lon": -63.1861,
   "lat": -27.1825,
   "depth": 587.411,
   "url": "https://earthquake.usgs.gov/earthquakes/eventpage/us6000t7tg"
  },
  {
   "mag": 4.4,
   "place": "49 km WNW of Macabuboni, Philippines",
   "time": 1782265709098,
   "lon": 119.3341,
   "lat": 16.3256,
   "depth": 10,
   "url": "https://earthquake.usgs.gov/earthquakes/eventpage/us6000t7rv"
  },
  {
   "mag": 4.3,
   "place": "10 km W of Quvasoy, Uzbekistan",
   "time": 1782317222405,
   "lon": 71.8638,
   "lat": 40.3102,
   "depth": 18.98,
   "url": "https://earthquake.usgs.gov/earthquakes/eventpage/us6000t7wh"
  },
  {
   "mag": 4.2,
   "place": "152 km ENE of Petropavlovsk-Kamchatsky, Russia",
   "time": 1782278815458,
   "lon": 160.556,
   "lat": 53.7999,
   "depth": 52.473,
   "url": "https://earthquake.usgs.gov/earthquakes/eventpage/us6000t7sx"
  },
  {
   "mag": 4,
   "place": "124 km SW of Adak, Alaska",
   "time": 1782331399963,
   "lon": -178.038,
   "lat": 51.171,
   "depth": 19.9,
   "url": "https://earthquake.usgs.gov/earthquakes/eventpage/aka2026mkxyfx"
  },
  {
   "mag": 3.9,
   "place": "265 km SE of Attu Station, Alaska",
   "time": 1782299072795,
   "lon": 176.4151,
   "lat": 51.5198,
   "depth": 57.859,
   "url": "https://earthquake.usgs.gov/earthquakes/eventpage/us6000t7u5"
  },
  {
   "mag": 3.7,
   "place": "off the coast of Oregon",
   "time": 1782294568246,
   "lon": -129.0274,
   "lat": 44.4794,
   "depth": 10,
   "url": "https://earthquake.usgs.gov/earthquakes/eventpage/us6000t7tr"
  },
  {
   "mag": 3.6,
   "place": "14 km S of Volcano, Hawaii",
   "time": 1782325777230,
   "lon": -155.215666666667,
   "lat": 19.309,
   "depth": 7.37,
   "url": "https://earthquake.usgs.gov/earthquakes/eventpage/hv74990097"
  },
  {
   "mag": 3.2,
   "place": "34 km W of Kotzebue, Alaska",
   "time": 1782315144025,
   "lon": -163.388,
   "lat": 66.861,
   "depth": 5,
   "url": "https://earthquake.usgs.gov/earthquakes/eventpage/aka2026mkoycw"
  },
  {
   "mag": 3.2,
   "place": "199 km SSW of Akhiok, Alaska",
   "time": 1782267545406,
   "lon": -155.445,
   "lat": 55.302,
   "depth": 52,
   "url": "https://earthquake.usgs.gov/earthquakes/eventpage/aka2026mjolnr"
  },
  {
   "mag": 3,
   "place": "122 km SW of Pelican, Alaska",
   "time": 1782299600815,
   "lon": -137.578,
   "lat": 57.132,
   "depth": 5,
   "url": "https://earthquake.usgs.gov/earthquakes/eventpage/aka2026mkggvj"
  },
  {
   "mag": 3,
   "place": "5 km S of Meadow Lakes, Alaska",
   "time": 1782290774787,
   "lon": -149.62,
   "lat": 61.574,
   "depth": 14,
   "url": "https://earthquake.usgs.gov/earthquakes/eventpage/aka2026mkbjen"
  },
  {
   "mag": 2.9,
   "place": "31 km ESE of Pedro Bay, Alaska",
   "time": 1782333714446,
   "lon": -153.565,
   "lat": 59.709,
   "depth": 135.4,
   "url": "https://earthquake.usgs.gov/earthquakes/eventpage/aka2026mkzfre"
  },
  {
   "mag": 2.9,
   "place": "10 km SW of Manton, CA",
   "time": 1782298951680,
   "lon": -121.936332702637,
   "lat": 40.3506660461426,
   "depth": -0.560000002384186,
   "url": "https://earthquake.usgs.gov/earthquakes/eventpage/nc75382821"
  },
  {
   "mag": 2.8,
   "place": "10 km NNW of Redwood Valley, CA",
   "time": 1782342426360,
   "lon": -123.242668151855,
   "lat": 39.3536682128906,
   "depth": 5.26000022888184,
   "url": "https://earthquake.usgs.gov/earthquakes/eventpage/nc75383591"
  },
  {
   "mag": 2.8,
   "place": "9 km N of Redwood Valley, CA",
   "time": 1782323232710,
   "lon": -123.192169189453,
   "lat": 39.3431663513184,
   "depth": 7.92999982833862,
   "url": "https://earthquake.usgs.gov/earthquakes/eventpage/nc75383201"
  },
  {
   "mag": 2.8,
   "place": "28 km N of Isabela, Puerto Rico",
   "time": 1782301526310,
   "lon": -67.0471666666667,
   "lat": 18.7541666666667,
   "depth": 34.15,
   "url": "https://earthquake.usgs.gov/earthquakes/eventpage/pr71521043"
  },
  {
   "mag": 2.8,
   "place": "18 km WSW of Johannesburg, CA",
   "time": 1782279147750,
   "lon": -117.814,
   "lat": 35.2995,
   "depth": 8.55,
   "url": "https://earthquake.usgs.gov/earthquakes/eventpage/ci41494136"
  },
  {
   "mag": 2.8,
   "place": "33 km SSE of Nelchina, Alaska",
   "time": 1782261184176,
   "lon": -146.494,
   "lat": 61.717,
   "depth": 17.8,
   "url": "https://earthquake.usgs.gov/earthquakes/eventpage/aka2026mjkxoh"
  },
  {
   "mag": 2.7,
   "place": "12 km ESE of Willits, CA",
   "time": 1782323902840,
   "lon": -123.224166870117,
   "lat": 39.372501373291,
   "depth": 7.42999982833862,
   "url": "https://earthquake.usgs.gov/earthquakes/eventpage/nc75383221"
  },
  {
   "mag": 2.7,
   "place": "10 km ESE of Willits, CA",
   "time": 1782317202310,
   "lon": -123.259330749512,
   "lat": 39.3643341064453,
   "depth": 4.73999977111816,
   "url": "https://earthquake.usgs.gov/earthquakes/eventpage/nc75383061"
  },
  {
   "mag": 2.6,
   "place": "12 km N of Redwood Valley, CA",
   "time": 1782317206510,
   "lon": -123.222999572754,
   "lat": 39.3718338012695,
   "depth": 8.59000015258789,
   "url": "https://earthquake.usgs.gov/earthquakes/eventpage/nc75383066"
  },
  {
   "mag": 2.6,
   "place": "16 km NE of Perryville, Alaska",
   "time": 1782316383739,
   "lon": -158.978,
   "lat": 56.024,
   "depth": 101.4,
   "url": "https://earthquake.usgs.gov/earthquakes/eventpage/aka2026mkppgo"
  },
  {
   "mag": 2.6,
   "place": "9 km ENE of Kaltag, Alaska",
   "time": 1782308840900,
   "lon": -158.536,
   "lat": 64.36,
   "depth": 1.1,
   "url": "https://earthquake.usgs.gov/earthquakes/eventpage/aka2026mklkhs"
  },
  {
   "mag": 2.6,
   "place": "80 km W of Petrolia, CA",
   "time": 1782303412560,
   "lon": -125.221664428711,
   "lat": 40.390998840332,
   "depth": 0.649999976158142,
   "url": "https://earthquake.usgs.gov/earthquakes/eventpage/nc75382866"
  },
  {
   "mag": 2.6,
   "place": "18 km WSW of Johannesburg, CA",
   "time": 1782291977770,
   "lon": -117.809166666667,
   "lat": 35.2948333333333,
   "depth": 7.65,
   "url": "https://earthquake.usgs.gov/earthquakes/eventpage/ci41494240"
  },
  {
   "mag": 2.6,
   "place": "95 km S of False Pass, Alaska",
   "time": 1782259471302,
   "lon": -163.555,
   "lat": 53.996,
   "depth": 28.7,
   "url": "https://earthquake.usgs.gov/earthquakes/eventpage/aka2026mjjyuj"
  },
  {
   "mag": 2.5,
   "place": "11 km N of Redwood Valley, CA",
   "time": 1782314248900,
   "lon": -123.219497680664,
   "lat": 39.3623352050781,
   "depth": 1.77999997138977,
   "url": "https://earthquake.usgs.gov/earthquakes/eventpage/nc75382946"
  },
  {
   "mag": 2.5,
   "place": "8 km WNW of Excursion Inlet, Alaska",
   "time": 1782307000790,
   "lon": -135.576,
   "lat": 58.459,
   "depth": 5,
   "url": "https://earthquake.usgs.gov/earthquakes/eventpage/aka2026mkkjrj"
  },
  {
   "mag": 2.5,
   "place": "92 km SE of Akutan, Alaska",
   "time": 1782264259856,
   "lon": -164.755,
   "lat": 53.568,
   "depth": 14.7,
   "url": "https://earthquake.usgs.gov/earthquakes/eventpage/aka2026mjmqco"
  },
  {
   "mag": 2.4,
   "place": "46 km WNW of Toyah, Texas",
   "time": 1782340558919,
   "lon": -104.233,
   "lat": 31.492,
   "depth": 0,
   "url": "https://earthquake.usgs.gov/earthquakes/eventpage/tx2026mjdhqd"
  },
  {
   "mag": 2.4,
   "place": "11 km NNW of Redwood Valley, CA",
   "time": 1782320728010,
   "lon": -123.235832214355,
   "lat": 39.3624992370605,
   "depth": 5.65999984741211,
   "url": "https://earthquake.usgs.gov/earthquakes/eventpage/nc75383176"
  },
  {
   "mag": 2.4,
   "place": "52 km NW of Ninilchik, Alaska",
   "time": 1782300942158,
   "lon": -152.298,
   "lat": 60.401,
   "depth": 103.3,
   "url": "https://earthquake.usgs.gov/earthquakes/eventpage/aka2026mkgzvc"
  },
  {
   "mag": 2.4,
   "place": "11 km NNE of Gerber, CA",
   "time": 1782274733780,
   "lon": -122.106163024902,
   "lat": 40.1483345031738,
   "depth": 27.2900009155273,
   "url": "https://earthquake.usgs.gov/earthquakes/eventpage/nc75382626"
  },
  {
   "mag": 2.4,
   "place": "183 km SSE of Akutan, Alaska",
   "time": 1782262204087,
   "lon": -164.304,
   "lat": 52.738,
   "depth": 23.3,
   "url": "https://earthquake.usgs.gov/earthquakes/eventpage/aka2026mjlmji"
  },
  {
   "mag": 2.4,
   "place": "30 km E of Nelson Lagoon, Alaska",
   "time": 1782260343163,
   "lon": -160.712,
   "lat": 55.985,
   "depth": 150.3,
   "url": "https://earthquake.usgs.gov/earthquakes/eventpage/aka2026mjklcr"
  },
  {
   "mag": 2.3,
   "place": "40 km W of Nanwalek, Alaska",
   "time": 1782343645409,
   "lon": -152.626,
   "lat": 59.42,
   "depth": 75.4,
   "url": "https://earthquake.usgs.gov/earthquakes/eventpage/aka2026mleter"
  },
  {
   "mag": 2.3,
   "place": "20 km SE of Pāhala, Hawaii",
   "time": 1782274741600,
   "lon": -155.359664916992,
   "lat": 19.0590000152588,
   "depth": 30.9099998474121,
   "url": "https://earthquake.usgs.gov/earthquakes/eventpage/hv74989722"
  },
  {
   "mag": 2.3,
   "place": "16 km W of Healy, Alaska",
   "time": 1782268060312,
   "lon": -149.306,
   "lat": 63.845,
   "depth": 121.3,
   "url": "https://earthquake.usgs.gov/earthquakes/eventpage/aka2026mjosxi"
  },
  {
   "mag": 2.3,
   "place": "83 km SSE of Akutan, Alaska",
   "time": 1782263685370,
   "lon": -165.421,
   "lat": 53.417,
   "depth": 28.3,
   "url": "https://earthquake.usgs.gov/earthquakes/eventpage/aka2026mjmhmn"
  },
  {
   "mag": 2.2,
   "place": "42 km SSE of Evanston, Wyoming",
   "time": 1782328553420,
   "lon": -110.853166666667,
   "lat": 40.8966666666667,
   "depth": 13.54,
   "url": "https://earthquake.usgs.gov/earthquakes/eventpage/uu80143266"
  },
  {
   "mag": 2.2,
   "place": "8 km NNW of Redwood Valley, CA",
   "time": 1782315038520,
   "lon": -123.232002258301,
   "lat": 39.3373336791992,
   "depth": 4.94000005722046,
   "url": "https://earthquake.usgs.gov/earthquakes/eventpage/nc75382966"
  },
  {
   "mag": 2.2,
   "place": "3 km SSW of San Juan Bautista, CA",
   "time": 1782288198210,
   "lon": -121.555168151855,
   "lat": 36.8185005187988,
   "depth": 5.82000017166138,
   "url": "https://earthquake.usgs.gov/earthquakes/eventpage/nc75382746"
  },
  {
   "mag": 2.2,
   "place": "7 km ESE of Roseland, CA",
   "time": 1782277225930,
   "lon": -122.653335571289,
   "lat": 38.3959999084473,
   "depth": 9.11999988555908,
   "url": "https://earthquake.usgs.gov/earthquakes/eventpage/nc75382651"
  },
  {
   "mag": 2.2,
   "place": "55 km WNW of Nanwalek, Alaska",
   "time": 1782275759762,
   "lon": -152.767,
   "lat": 59.61,
   "depth": 90,
   "url": "https://earthquake.usgs.gov/earthquakes/eventpage/aka2026mjtaaj"
  },
  {
   "mag": 2.2,
   "place": "9 km SSW of Guánica, Puerto Rico",
   "time": 1782271082460,
   "lon": -66.9406666666667,
   "lat": 17.8891666666667,
   "depth": 11.52,
   "url": "https://earthquake.usgs.gov/earthquakes/eventpage/pr71521028"
  },
  {
   "mag": 2.1,
   "place": "10 km NNW of Redwood Valley, CA",
   "time": 1782338497730,
   "lon": -123.227333068848,
   "lat": 39.349666595459,
   "depth": 6.05000019073486,
   "url": "https://earthquake.usgs.gov/earthquakes/eventpage/nc75383556"
  },
  {
   "mag": 2.1,
   "place": "5 km SW of Anza, CA",
   "time": 1782338331680,
   "lon": -116.718333333333,
   "lat": 33.5293333333333,
   "depth": 5.07,
   "url": "https://earthquake.usgs.gov/earthquakes/eventpage/ci41494760"
  },
  {
   "mag": 2.1,
   "place": "26 km E of Pāhala, Hawaii",
   "time": 1782326945530,
   "lon": -155.230499267578,
   "lat": 19.1919994354248,
   "depth": 40.0099983215332,
   "url": "https://earthquake.usgs.gov/earthquakes/eventpage/hv74990112"
  },
  {
   "mag": 2.1,
   "place": "11 km ESE of Willits, CA",
   "time": 1782323667340,
   "lon": -123.231834411621,
   "lat": 39.3720016479492,
   "depth": 6.42999982833862,
   "url": "https://earthquake.usgs.gov/earthquakes/eventpage/nc75383216"
  },
  {
   "mag": 2.1,
   "place": "8 km NNW of Redwood Valley, CA",
   "time": 1782315098030,
   "lon": -123.227996826172,
   "lat": 39.337833404541,
   "depth": 4.82000017166138,
   "url": "https://earthquake.usgs.gov/earthquakes/eventpage/nc75382971"
  },
  {
   "mag": 2.1,
   "place": "17 km SW of Manton, CA",
   "time": 1782301786710,
   "lon": -122.005996704102,
   "lat": 40.3096656799316,
   "depth": 4.09000015258789,
   "url": "https://earthquake.usgs.gov/earthquakes/eventpage/nc75382846"
  },
  {
   "mag": 2.1,
   "place": "4 km NNE of Hilltop, Texas",
   "time": 1782298780871,
   "lon": -99.153,
   "lat": 28.733,
   "depth": 4.9447,
   "url": "https://earthquake.usgs.gov/earthquakes/eventpage/tx2026migfqj"
  },
  {
   "mag": 2.1,
   "place": "59 km WNW of Sitka, Alaska",
   "time": 1782294655322,
   "lon": -136.202,
   "lat": 57.292,
   "depth": 8.5,
   "url": "https://earthquake.usgs.gov/earthquakes/eventpage/aka2026mkdngr"
  },
  {
   "mag": 2.1,
   "place": "14 km ENE of Hebgen Lake Estates, Montana",
   "time": 1782289816560,
   "lon": -111.018666666667,
   "lat": 44.8208333333333,
   "depth": 8.02,
   "url": "https://earthquake.usgs.gov/earthquakes/eventpage/uu80143206"
  },
  {
   "mag": 2.1,
   "place": "18 km WSW of Johannesburg, CA",
   "time": 1782278729250,
   "lon": -117.817166666667,
   "lat": 35.3021666666667,
   "depth": 8.56,
   "url": "https://earthquake.usgs.gov/earthquakes/eventpage/ci41494128"
  },
  {
   "mag": 2.1,
   "place": "17 km NW of Ninilchik, Alaska",
   "time": 1782274576241,
   "lon": -151.918,
   "lat": 60.152,
   "depth": 71.2,
   "url": "https://earthquake.usgs.gov/earthquakes/eventpage/aka2026mjsjbm"
  },
  {
   "mag": 2.0,
   "place": "12 km N of Redwood Valley, CA",
   "time": 1782337975320,
   "lon": -123.227333068848,
   "lat": 39.3686676025391,
   "depth": 6.80000019073486,
   "url": "https://earthquake.usgs.gov/earthquakes/eventpage/nc75383536"
  },
  {
   "mag": 2.0,
   "place": "11 km ESE of Willits, CA",
   "time": 1782328774320,
   "lon": -123.231498718262,
   "lat": 39.3716659545898,
   "depth": 3.15000009536743,
   "url": "https://earthquake.usgs.gov/earthquakes/eventpage/nc75383341"
  },
  {
   "mag": 2,
   "place": "32 km SSW of Nanwalek, Alaska",
   "time": 1782324351620,
   "lon": -152.181,
   "lat": 59.101,
   "depth": 68.2,
   "url": "https://earthquake.usgs.gov/earthquakes/eventpage/aka2026mkuakc"
  },
  {
   "mag": 2.0,
   "place": "8 km NNW of Redwood Valley, CA",
   "time": 1782316198590,
   "lon": -123.244163513184,
   "lat": 39.3278350830078,
   "depth": 4.26999998092651,
   "url": "https://earthquake.usgs.gov/earthquakes/eventpage/nc75383021"
  },
  {
   "mag": 2,
   "place": "12 km ESE of Willits, CA",
   "time": 1782315230150,
   "lon": -123.22883605957,
   "lat": 39.3698348999023,
   "depth": 6.80999994277954,
   "url": "https://earthquake.usgs.gov/earthquakes/eventpage/nc75382976"
  },
  {
   "mag": 2,
   "place": "93 km SSE of Perryville, Alaska",
   "time": 1782277175966,
   "lon": -158.744,
   "lat": 55.1,
   "depth": 0.9,
   "url": "https://earthquake.usgs.gov/earthquakes/eventpage/aka2026mjtuqv"
  },
  {
   "mag": 1.9,
   "place": "41 km W of Jal, New Mexico",
   "time": 1782339413825,
   "lon": -103.628,
   "lat": 32.133,
   "depth": 0,
   "url": "https://earthquake.usgs.gov/earthquakes/eventpage/tx2026mjcrej"
  },
  {
   "mag": 1.9,
   "place": "12 km N of Redwood Valley, CA",
   "time": 1782338065720,
   "lon": -123.227836608887,
   "lat": 39.3689994812012,
   "depth": 6.53999996185303,
   "url": "https://earthquake.usgs.gov/earthquakes/eventpage/nc75383546"
  },
  {
   "mag": 1.9,
   "place": "12 km ESE of Willits, CA",
   "time": 1782326033410,
   "lon": -123.228668212891,
   "lat": 39.3699989318848,
   "depth": 6.6100001335144,
   "url": "https://earthquake.usgs.gov/earthquakes/eventpage/nc75383296"
  },
  {
   "mag": 1.9,
   "place": "9 km NNW of Redwood Valley, CA",
   "time": 1782319945970,
   "lon": -123.229331970215,
   "lat": 39.3481674194336,
   "depth": 5.57999992370605,
   "url": "https://earthquake.usgs.gov/earthquakes/eventpage/nc75383156"
  },
  {
   "mag": 1.9,
   "place": "9 km NNW of Redwood Valley, CA",
   "time": 1782319351220,
   "lon": -123.235168457031,
   "lat": 39.3411674499512,
   "depth": 4.75,
   "url": "https://earthquake.usgs.gov/earthquakes/eventpage/nc75383136"
  },
  {
   "mag": 1.9,
   "place": "52 km WNW of Toyah, Texas",
   "time": 1782318397747,
   "lon": -104.305,
   "lat": 31.491,
   "depth": 0,
   "url": "https://earthquake.usgs.gov/earthquakes/eventpage/tx2026mirbiu"
  },
  {
   "mag": 1.9,
   "place": "10 km ESE of Willits, CA",
   "time": 1782318229990,
   "lon": -123.260665893555,
   "lat": 39.3644981384277,
   "depth": 4.82999992370605,
   "url": "https://earthquake.usgs.gov/earthquakes/eventpage/nc75383101"
  },
  {
   "mag": 1.9,
   "place": "27 km SE of Mammoth, Wyoming",
   "time": 1782316231630,
   "lon": -110.437666666667,
   "lat": 44.821,
   "depth": 10.41,
   "url": "https://earthquake.usgs.gov/earthquakes/eventpage/uu80143241"
  },
  {
   "mag": 1.9,
   "place": "12 km ESE of Willits, CA",
   "time": 1782315969470,
   "lon": -123.232498168945,
   "lat": 39.3676681518555,
   "depth": -0.5,
   "url": "https://earthquake.usgs.gov/earthquakes/eventpage/nc75383016"
  },
  {
   "mag": 1.9,
   "place": "67 km WNW of Ninilchik, Alaska",
   "time": 1782307026263,
   "lon": -152.84,
   "lat": 60.215,
   "depth": 124.9,
   "url": "https://earthquake.usgs.gov/earthquakes/eventpage/aka2026mkkkco"
  },
  {
   "mag": 1.9,
   "place": "4 km E of Covelo, CA",
   "time": 1782306485080,
   "lon": -123.199501037598,
   "lat": 39.7998352050781,
   "depth": 10.2299995422363,
   "url": "https://earthquake.usgs.gov/earthquakes/eventpage/nc75382886"
  },
  {
   "mag": 1.9,
   "place": "18 km WSW of Johannesburg, CA",
   "time": 1782305951640,
   "lon": -117.808333333333,
   "lat": 35.2935,
   "depth": 7.62,
   "url": "https://earthquake.usgs.gov/earthquakes/eventpage/ci41494312"
  },
  {
   "mag": 1.9,
   "place": "64 km ESE of Denali National Park, Alaska",
   "time": 1782303014752,
   "lon": -150.608,
   "lat": 63.243,
   "depth": 134.5,
   "url": "https://earthquake.usgs.gov/earthquakes/eventpage/aka2026mkiebz"
  },
  {
   "mag": 1.9,
   "place": "19 km ENE of Red Bluff, CA",
   "time": 1782301478640,
   "lon": -122.023666381836,
   "lat": 40.2386665344238,
   "depth": 21.9599990844727,
   "url": "https://earthquake.usgs.gov/earthquakes/eventpage/nc75382836"
  },
  {
   "mag": 1.9,
   "place": "14 km SW of Manton, CA",
   "time": 1782280953840,
   "lon": -121.959831237793,
   "lat": 40.3166656494141,
   "depth": 3.17000007629395,
   "url": "https://earthquake.usgs.gov/earthquakes/eventpage/nc75382726"
  },
  {
   "mag": 1.9,
   "place": "9 km NNE of Pāhala, Hawaii",
   "time": 1782278293490,
   "lon": -155.439666748047,
   "lat": 19.2849998474121,
   "depth": 1.6599999666214,
   "url": "https://earthquake.usgs.gov/earthquakes/eventpage/hv74989757"
  },
  {
   "mag": 1.9,
   "place": "3 km SW of Pāhala, Hawaii",
   "time": 1782277090220,
   "lon": -155.504333496094,
   "lat": 19.1854991912842,
   "depth": 32.0200004577637,
   "url": "https://earthquake.usgs.gov/earthquakes/eventpage/hv74989742"
  },
  {
   "mag": 1.9,
   "place": "4 km SSW of Pāhala, Hawaii",
   "time": 1782269326760,
   "lon": -155.489837646484,
   "lat": 19.1674995422363,
   "depth": 27.8999996185303,
   "url": "https://earthquake.usgs.gov/earthquakes/eventpage/hv74989657"
  },
  {
   "mag": 1.9,
   "place": "4 km NW of The Geysers, CA",
   "time": 1782269156780,
   "lon": -122.780830383301,
   "lat": 38.8025016784668,
   "depth": 3.69000005722046,
   "url": "https://earthquake.usgs.gov/earthquakes/eventpage/nc75382581"
  },
  {
   "mag": 1.9,
   "place": "84 km W of Akhiok, Alaska",
   "time": 1782268416341,
   "lon": -155.532,
   "lat": 56.823,
   "depth": 6.2,
   "url": "https://earthquake.usgs.gov/earthquakes/eventpage/aka2026mjoybx"
  },
  {
   "mag": 1.8,
   "place": "17 km NNE of Shingletown, CA",
   "time": 1782344622920,
   "lon": -121.839332580566,
   "lat": 40.6408348083496,
   "depth": 1.64999997615814,
   "url": "https://earthquake.usgs.gov/earthquakes/eventpage/nc75383601"
  },
  {
   "mag": 1.8,
   "place": "14 km SSW of Skwentna, Alaska",
   "time": 1782330109728,
   "lon": -151.457,
   "lat": 61.86,
   "depth": 81.7,
   "url": "https://earthquake.usgs.gov/earthquakes/eventpage/aka2026mkxfqn"
  },
  {
   "mag": 1.8,
   "place": "7 km NNW of Honoka‘a, Hawaii",
   "time": 1782329357080,
   "lon": -155.481506347656,
   "lat": 20.1436672210693,
   "depth": -1.69000005722046,
   "url": "https://earthquake.usgs.gov/earthquakes/eventpage/hv74990137"
  },
  {
   "mag": 1.8,
   "place": "8 km NNW of Redwood Valley, CA",
   "time": 1782326987510,
   "lon": -123.228668212891,
   "lat": 39.3366661071777,
   "depth": 4.90999984741211,
   "url": "https://earthquake.usgs.gov/earthquakes/eventpage/nc75383321"
  },
  {
   "mag": 1.8,
   "place": "3 km E of Lexington, Oregon",
   "time": 1782326625420,
   "lon": -119.644,
   "lat": 45.4395,
   "depth": 8.91,
   "url": "https://earthquake.usgs.gov/earthquakes/eventpage/uw714031501"
  },
  {
   "mag": 1.8,
   "place": "5 km SSE of Monroe, Oregon",
   "time": 1782321734250,
   "lon": -123.272833333333,
   "lat": 44.2668333333333,
   "depth": -0.41,
   "url": "https://earthquake.usgs.gov/earthquakes/eventpage/uw714031471"
  },
  {
   "mag": 1.8,
   "place": "17 km SE of Lindsay, Texas",
   "time": 1782318186407,
   "lon": -103.404,
   "lat": 31.261,
   "depth": 3.4851,
   "url": "https://earthquake.usgs.gov/earthquakes/eventpage/tx2026miqyih"
  },
  {
   "mag": 1.8,
   "place": "27 km SE of Mammoth, Wyoming",
   "time": 1782313145470,
   "lon": -110.436666666667,
   "lat": 44.8178333333333,
   "depth": 10.43,
   "url": "https://earthquake.usgs.gov/earthquakes/eventpage/uu80143231"
  },
  {
   "mag": 1.8,
   "place": "57 km NW of McCarthy, Alaska",
   "time": 1782310208783,
   "lon": -143.535,
   "lat": 61.862,
   "depth": 5,
   "url": "https://earthquake.usgs.gov/earthquakes/eventpage/aka2026mkmeaf"
  },
  {
   "mag": 1.8,
   "place": "28 km NW of Susitna, Alaska",
   "time": 1782294391520,
   "lon": -150.94,
   "lat": 61.696,
   "depth": 59.8,
   "url": "https://earthquake.usgs.gov/earthquakes/eventpage/aka2026mkdjlo"
  },
  {
   "mag": 1.8,
   "place": "72 km WNW of Happy Valley, Alaska",
   "time": 1782285391163,
   "lon": -152.987,
   "lat": 60.123,
   "depth": 136.9,
   "url": "https://earthquake.usgs.gov/earthquakes/eventpage/aka2026mjyjjj"
  },
  {
   "mag": 1.8,
   "place": "18 km N of Pāhala, Hawaii",
   "time": 1782280637570,
   "lon": -155.500671386719,
   "lat": 19.3726673126221,
   "depth": 5.65000009536743,
   "url": "https://earthquake.usgs.gov/earthquakes/eventpage/hv74989777"
  },
  {
   "mag": 1.8,
   "place": "6 km ENE of Big Lake, Alaska",
   "time": 1782279532865,
   "lon": -149.836,
   "lat": 61.544,
   "depth": 37.4,
   "url": "https://earthquake.usgs.gov/earthquakes/eventpage/aka2026mjvcop"
  },
  {
   "mag": 1.8,
   "place": "2 km SW of Pāhala, Hawaii",
   "time": 1782274912800,
   "lon": -155.494995117188,
   "lat": 19.1884994506836,
   "depth": 31.0699996948242,
   "url": "https://earthquake.usgs.gov/earthquakes/eventpage/hv74989727"
  },
  {
   "mag": 1.8,
   "place": "21 km SE of Pāhala, Hawaii",
   "time": 1782273629580,
   "lon": -155.352172851562,
   "lat": 19.0556659698486,
   "depth": 29.3400001525879,
   "url": "https://earthquake.usgs.gov/earthquakes/eventpage/hv74989707"
  },
  {
   "mag": 1.8,
   "place": "28 km WSW of Olancha, CA",
   "time": 1782272987170,
   "lon": -118.2775,
   "lat": 36.1556666666667,
   "depth": 8.22,
   "url": "https://earthquake.usgs.gov/earthquakes/eventpage/ci41494072"
  },
  {
   "mag": 1.8,
   "place": "16 km SSW of Leilani Estates, Hawaii",
   "time": 1782270851740,
   "lon": -154.985336303711,
   "lat": 19.3316669464111,
   "depth": 5.42000007629395,
   "url": "https://earthquake.usgs.gov/earthquakes/eventpage/hv74989677"
  },
  {
   "mag": 1.8,
   "place": "15 km ENE of Hebgen Lake Estates, Montana",
   "time": 1782259725350,
   "lon": -111.020666666667,
   "lat": 44.8298333333333,
   "depth": 8.97,
   "url": "https://earthquake.usgs.gov/earthquakes/eventpage/uu80143161"
  },
  {
   "mag": 1.7,
   "place": "57 km NW of Toyah, Texas",
   "time": 1782341077572,
   "lon": -104.282,
   "lat": 31.618,
   "depth": 4.0268,
   "url": "https://earthquake.usgs.gov/earthquakes/eventpage/tx2026mjdpby"
  },
  {
   "mag": 1.7,
   "place": "7 km SSW of Boonville, CA",
   "time": 1782339516730,
   "lon": -123.402168273926,
   "lat": 38.949333190918,
   "depth": 2.54999995231628,
   "url": "https://earthquake.usgs.gov/earthquakes/eventpage/nc75383571"
  },
  {
   "mag": 1.7,
   "place": "32 km SE of Malaga, New Mexico",
   "time": 1782339281348,
   "lon": -103.791,
   "lat": 32.056,
   "depth": 0,
   "url": "https://earthquake.usgs.gov/earthquakes/eventpage/tx2026mjcpkh"
  },
  {
   "mag": 1.7,
   "place": "10 km ESE of Willits, CA",
   "time": 1782335018670,
   "lon": -123.248497009277,
   "lat": 39.3773345947266,
   "depth": 4.3899998664856,
   "url": "https://earthquake.usgs.gov/earthquakes/eventpage/nc75383506"
  },
  {
   "mag": 1.7,
   "place": "8 km NNW of Redwood Valley, CA",
   "time": 1782329446730,
   "lon": -123.224998474121,
   "lat": 39.3375015258789,
   "depth": 5,
   "url": "https://earthquake.usgs.gov/earthquakes/eventpage/nc75383356"
  },
  {
   "mag": 1.7,
   "place": "15 km NW of Pomeroy, Washington",
   "time": 1782323145730,
   "lon": -117.770333333333,
   "lat": 46.5533333333333,
   "depth": -0.39,
   "url": "https://earthquake.usgs.gov/earthquakes/eventpage/uw714031481"
  },
  {
   "mag": 1.7,
   "place": "10 km ESE of Willits, CA",
   "time": 1782318647450,
   "lon": -123.260833740234,
   "lat": 39.3626670837402,
   "depth": 3.57999992370605,
   "url": "https://earthquake.usgs.gov/earthquakes/eventpage/nc75383116"
  },
  {
   "mag": 1.7,
   "place": "17 km E of Pāhala, Hawaii",
   "time": 1782303938600,
   "lon": -155.309005737305,
   "lat": 19.1940002441406,
   "depth": 39.7299995422363,
   "url": "https://earthquake.usgs.gov/earthquakes/eventpage/hv74989947"
  },
  {
   "mag": 1.7,
   "place": "140 km ESE of Chignik, Alaska",
   "time": 1782301796253,
   "lon": -156.211,
   "lat": 56.005,
   "depth": 5,
   "url": "https://earthquake.usgs.gov/earthquakes/eventpage/aka2026mkhmli"
  },
  {
   "mag": 1.7,
   "place": "11 km WSW of Stanton, Texas",
   "time": 1782292657128,
   "lon": -101.912,
   "lat": 32.108,
   "depth": 8.9355,
   "url": "https://earthquake.usgs.gov/earthquakes/eventpage/tx2026micvfg"
  },
  {
   "mag": 1.7,
   "place": "8 km WNW of Happy Valley, Alaska",
   "time": 1782281253942,
   "lon": -151.886,
   "lat": 59.97,
   "depth": 13.9,
   "url": "https://earthquake.usgs.gov/earthquakes/eventpage/aka2026mjwbit"
  },
  {
   "mag": 1.7,
   "place": "22 km SE of Pāhala, Hawaii",
   "time": 1782277482690,
   "lon": -155.328994750977,
   "lat": 19.0543327331543,
   "depth": 35.9900016784668,
   "url": "https://earthquake.usgs.gov/earthquakes/eventpage/hv74989747"
  },
  {
   "mag": 1.7,
   "place": "88 km WSW of Akhiok, Alaska",
   "time": 1782272766659,
   "lon": -155.592,
   "lat": 56.772,
   "depth": 11.9,
   "url": "https://earthquake.usgs.gov/earthquakes/eventpage/aka2026mjriys"
  },
  {
   "mag": 1.7,
   "place": "14 km ENE of Hebgen Lake Estates, Montana",
   "time": 1782270245180,
   "lon": -111.020166666667,
   "lat": 44.8243333333333,
   "depth": 8.68,
   "url": "https://earthquake.usgs.gov/earthquakes/eventpage/uu80143186"
  },
  {
   "mag": 1.7,
   "place": "67 km W of Salamatof, Alaska",
   "time": 1782266355977,
   "lon": -152.542,
   "lat": 60.728,
   "depth": 116.9,
   "url": "https://earthquake.usgs.gov/earthquakes/eventpage/aka2026mjnuii"
  },
  {
   "mag": 1.7,
   "place": "3 km SE of Pinnacles, CA",
   "time": 1782259433710,
   "lon": -121.11833190918,
   "lat": 36.5154991149902,
   "depth": 0.0900000035762787,
   "url": "https://earthquake.usgs.gov/earthquakes/eventpage/nc75382526"
  },
  {
   "mag": 1.6,
   "place": "57 km NW of Toyah, Texas",
   "time": 1782341475660,
   "lon": -104.288,
   "lat": 31.614,
   "depth": 3.6546,
   "url": "https://earthquake.usgs.gov/earthquakes/eventpage/tx2026mjduuw"
  },
  {
   "mag": 1.6,
   "place": "16 km W of Searles Valley, CA",
   "time": 1782334973380,
   "lon": -117.577166666667,
   "lat": 35.7521666666667,
   "depth": 8.07,
   "url": "https://earthquake.usgs.gov/earthquakes/eventpage/ci41494720"
  },
  {
   "mag": 1.6,
   "place": "38 km NNW of Valdez, Alaska",
   "time": 1782331954076,
   "lon": -146.558,
   "lat": 61.462,
   "depth": 3.8,
   "url": "https://earthquake.usgs.gov/earthquakes/eventpage/aka2026mkyggs"
  },
  {
   "mag": 1.6,
   "place": "12 km ESE of Willits, CA",
   "time": 1782325500020,
   "lon": -123.223335266113,
   "lat": 39.3806648254395,
   "depth": 8.9399995803833,
   "url": "https://earthquake.usgs.gov/earthquakes/eventpage/nc75383276"
  },
  {
   "mag": 1.6,
   "place": "9 km NNW of Redwood Valley, CA",
   "time": 1782322937520,
   "lon": -123.238166809082,
   "lat": 39.3413314819336,
   "depth": 4.01000022888184,
   "url": "https://earthquake.usgs.gov/earthquakes/eventpage/nc75383196"
  },
  {
   "mag": 1.6,
   "place": "12 km ESE of Willits, CA",
   "time": 1782320150910,
   "lon": -123.229667663574,
   "lat": 39.3703346252441,
   "depth": 7.15999984741211,
   "url": "https://earthquake.usgs.gov/earthquakes/eventpage/nc75383161"
  },
  {
   "mag": 1.6,
   "place": "12 km ESE of Willits, CA",
   "time": 1782319520110,
   "lon": -123.228996276855,
   "lat": 39.3701667785645,
   "depth": 6.94000005722046,
   "url": "https://earthquake.usgs.gov/earthquakes/eventpage/nc75383141"
  },
  {
   "mag": 1.6,
   "place": "11 km N of Redwood Valley, CA",
   "time": 1782318964580,
   "lon": -123.222831726074,
   "lat": 39.3623352050781,
   "depth": 6.82000017166138,
   "url": "https://earthquake.usgs.gov/earthquakes/eventpage/nc75383121"
  },
  {
   "mag": 1.6,
   "place": "27 km N of Aleneva, Alaska",
   "time": 1782318396589,
   "lon": -152.969,
   "lat": 58.309,
   "depth": 26.4,
   "url": "https://earthquake.usgs.gov/earthquakes/eventpage/aka2026mkqsip"
  },
  {
   "mag": 1.6,
   "place": "8 km N of Redwood Valley, CA",
   "time": 1782317959210,
   "lon": -123.210334777832,
   "lat": 39.3351669311523,
   "depth": 7.76000022888184,
   "url": "https://earthquake.usgs.gov/earthquakes/eventpage/nc75383096"
  },
  {
   "mag": 1.6,
   "place": "9 km NNW of Redwood Valley, CA",
   "time": 1782317568960,
   "lon": -123.236831665039,
   "lat": 39.3388328552246,
   "depth": 4.15000009536743,
   "url": "https://earthquake.usgs.gov/earthquakes/eventpage/nc75383081"
  },
  {
   "mag": 1.6,
   "place": "11 km N of Redwood Valley, CA",
   "time": 1782316745790,
   "lon": -123.222831726074,
   "lat": 39.3663330078125,
   "depth": 7.19999980926514,
   "url": "https://earthquake.usgs.gov/earthquakes/eventpage/nc75383051"
  },
  {
   "mag": 1.6,
   "place": "8 km NNW of Redwood Valley, CA",
   "time": 1782316334370,
   "lon": -123.245002746582,
   "lat": 39.3278350830078,
   "depth": 2.75999999046326,
   "url": "https://earthquake.usgs.gov/earthquakes/eventpage/nc75383031"
  },
  {
   "mag": 1.6,
   "place": "10 km NNW of Redwood Valley, CA",
   "time": 1782316276290,
   "lon": -123.236167907715,
   "lat": 39.3501663208008,
   "depth": 6.07000017166138,
   "url": "https://earthquake.usgs.gov/earthquakes/eventpage/nc75383026"
  },
  {
   "mag": 1.6,
   "place": "10 km NNW of Redwood Valley, CA",
   "time": 1782315537220,
   "lon": -123.235000610352,
   "lat": 39.3491668701172,
   "depth": 5.32999992370605,
   "url": "https://earthquake.usgs.gov/earthquakes/eventpage/nc75382986"
  },
  {
   "mag": 1.6,
   "place": "81 km E of Chignik, Alaska",
   "time": 1782312647022,
   "lon": -157.089,
   "lat": 56.282,
   "depth": 18.9,
   "url": "https://earthquake.usgs.gov/earthquakes/eventpage/aka2026mknngi"
  },
  {
   "mag": 1.6,
   "place": "32 km SSW of Anaconda, Montana",
   "time": 1782297919940,
   "lon": -113.157666666667,
   "lat": 45.882,
   "depth": 5,
   "url": "https://earthquake.usgs.gov/earthquakes/eventpage/mb90146208"
  },
  {
   "mag": 1.6,
   "place": "24 km SW of Independence, CA",
   "time": 1782295872100,
   "lon": -118.387166666667,
   "lat": 36.6453333333333,
   "depth": 3.26,
   "url": "https://earthquake.usgs.gov/earthquakes/eventpage/ci41494272"
  },
  {
   "mag": 1.6,
   "place": "68 km W of Cantwell, Alaska",
   "time": 1782295703876,
   "lon": -150.319,
   "lat": 63.412,
   "depth": 0,
   "url": "https://earthquake.usgs.gov/earthquakes/eventpage/aka2026mkecnx"
  },
  {
   "mag": 1.6,
   "place": "55 km S of Whites City, New Mexico",
   "time": 1782295082298,
   "lon": -104.391,
   "lat": 31.678,
   "depth": 6.0999,
   "url": "https://earthquake.usgs.gov/earthquakes/eventpage/tx2026mieeob"
  },
  {
   "mag": 1.6,
   "place": "28 km WSW of Ivanof Bay, Alaska",
   "time": 1782294479457,
   "lon": -159.898,
   "lat": 55.801,
   "depth": 1.6,
   "url": "https://earthquake.usgs.gov/earthquakes/eventpage/aka2026mkdksk"
  },
  {
   "mag": 1.6,
   "place": "32 km NW of Chenega, Alaska",
   "time": 1782277009395,
   "lon": -148.461,
   "lat": 60.25,
   "depth": 9.2,
   "url": "https://earthquake.usgs.gov/earthquakes/eventpage/aka2026mjtsgp"
  },
  {
   "mag": 1.6,
   "place": "2 km E of Pecos, Texas",
   "time": 1782275762517,
   "lon": -103.464,
   "lat": 31.423,
   "depth": 0,
   "url": "https://earthquake.usgs.gov/earthquakes/eventpage/tx2026mhtmus"
  },
  {
   "mag": 1.6,
   "place": "12 km WNW of Whittier, Alaska",
   "time": 1782267361293,
   "lon": -148.903,
   "lat": 60.807,
   "depth": 5,
   "url": "https://earthquake.usgs.gov/earthquakes/eventpage/aka2026mjoivc"
  },
  {
   "mag": 1.5,
   "place": "10 km WSW of Stanton, Texas",
   "time": 1782339416682,
   "lon": -101.894,
   "lat": 32.094,
   "depth": 3.1151,
   "url": "https://earthquake.usgs.gov/earthquakes/eventpage/tx2026mjcrfo"
  },
  {
   "mag": 1.5,
   "place": "14 km NNW of Blackwell, Texas",
   "time": 1782338128231,
   "lon": -100.402,
   "lat": 32.201,
   "depth": 5.6937,
   "url": "https://earthquake.usgs.gov/earthquakes/eventpage/tx2026mjbysd"
  },
  {
   "mag": 1.5,
   "place": "54 km NW of Toyah, Texas",
   "time": 1782335243751,
   "lon": -104.255,
   "lat": 31.609,
   "depth": 4.9719,
   "url": "https://earthquake.usgs.gov/earthquakes/eventpage/tx2026mjajfa"
  },
  {
   "mag": 1.5,
   "place": "16 km ENE of Falls City, Texas",
   "time": 1782331670720,
   "lon": -97.864,
   "lat": 29.054,
   "depth": 7.3976,
   "url": "https://earthquake.usgs.gov/earthquakes/eventpage/tx2026miyjxw"
  },
  {
   "mag": 1.5,
   "place": "10 km S of Joshua Tree, CA",
   "time": 1782323439040,
   "lon": -116.319833333333,
   "lat": 34.0458333333333,
   "depth": 8.97,
   "url": "https://earthquake.usgs.gov/earthquakes/eventpage/ci41494496"
  },
  {
   "mag": 1.5,
   "place": "11 km ESE of Willits, CA",
   "time": 1782318583990,
   "lon": -123.233665466309,
   "lat": 39.3714981079102,
   "depth": 6.67999982833862,
   "url": "https://earthquake.usgs.gov/earthquakes/eventpage/nc75383106"
  },
  {
   "mag": 1.5,
   "place": "20 km SE of Fox River, Alaska",
   "time": 1782316188040,
   "lon": -150.74,
   "lat": 59.709,
   "depth": 37.7,
   "url": "https://earthquake.usgs.gov/earthquakes/eventpage/aka2026mkpmkl"
  },
  {
   "mag": 1.5,
   "place": "8 km NNW of Redwood Valley, CA",
   "time": 1782314767880,
   "lon": -123.227836608887,
   "lat": 39.3373336791992,
   "depth": 2.74000000953674,
   "url": "https://earthquake.usgs.gov/earthquakes/eventpage/nc75382951"
  },
  {
   "mag": 1.5,
   "place": "9 km NE of Hoodsport, Washington",
   "time": 1782308892500,
   "lon": -123.052833333333,
   "lat": 47.4698333333333,
   "depth": 8.2,
   "url": "https://earthquake.usgs.gov/earthquakes/eventpage/uw714031281"
  },
  {
   "mag": 1.5,
   "place": "9 km NE of Hoodsport, Washington",
   "time": 1782308505070,
   "lon": -123.046666666667,
   "lat": 47.4671666666667,
   "depth": 8.17,
   "url": "https://earthquake.usgs.gov/earthquakes/eventpage/uw714031271"
  },
  {
   "mag": 1.5,
   "place": "56 km S of Whites City, New Mexico",
   "time": 1782295025954,
   "lon": -104.387,
   "lat": 31.668,
   "depth": 4.9207,
   "url": "https://earthquake.usgs.gov/earthquakes/eventpage/tx2026mieaxm"
  },
  {
   "mag": 1.5,
   "place": "58 km SSW of Nanwalek, Alaska",
   "time": 1782288517853,
   "lon": -152.226,
   "lat": 58.855,
   "depth": 51.2,
   "url": "https://earthquake.usgs.gov/earthquakes/eventpage/aka2026mkacod"
  },
  {
   "mag": 1.5,
   "place": "7 km NW of The Geysers, CA",
   "time": 1782280519580,
   "lon": -122.817497253418,
   "lat": 38.8153343200684,
   "depth": 2.27999997138977,
   "url": "https://earthquake.usgs.gov/earthquakes/eventpage/nc75382716"
  },
  {
   "mag": 1.4,
   "place": "10 km ESE of Willits, CA",
   "time": 1782330828390,
   "lon": -123.237663269043,
   "lat": 39.3858337402344,
   "depth": 7.75,
   "url": "https://earthquake.usgs.gov/earthquakes/eventpage/nc75383396"
  },
  {
   "mag": 1.4,
   "place": "12 km S of Shelton, Washington",
   "time": 1782330309960,
   "lon": -123.094166666667,
   "lat": 47.104,
   "depth": -0.21,
   "url": "https://earthquake.usgs.gov/earthquakes/eventpage/uw714031581"
  },
  {
   "mag": 1.4,
   "place": "10 km ESE of Willits, CA",
   "time": 1782317552610,
   "lon": -123.249496459961,
   "lat": 39.3663330078125,
   "depth": 4.23999977111816,
   "url": "https://earthquake.usgs.gov/earthquakes/eventpage/nc75383076"
  },
  {
   "mag": 1.4,
   "place": "6 km NW of The Geysers, CA",
   "time": 1782313699880,
   "lon": -122.81266784668,
   "lat": 38.8153343200684,
   "depth": 2.71000003814697,
   "url": "https://earthquake.usgs.gov/earthquakes/eventpage/nc75382931"
  },
  {
   "mag": 1.4,
   "place": "63 km ENE of Ouzinkie, Alaska",
   "time": 1782295165142,
   "lon": -151.587,
   "lat": 58.224,
   "depth": 5.5,
   "url": "https://earthquake.usgs.gov/earthquakes/eventpage/aka2026mkduqr"
  },
  {
   "mag": 1.4,
   "place": "83 km W of Karluk, Alaska",
   "time": 1782284307886,
   "lon": -155.848,
   "lat": 57.55,
   "depth": 5,
   "url": "https://earthquake.usgs.gov/earthquakes/eventpage/aka2026mjxtsn"
  },
  {
   "mag": 1.4,
   "place": "2 km WNW of Wrightwood, CA",
   "time": 1782283076080,
   "lon": -117.658666666667,
   "lat": 34.3665,
   "depth": 5.52,
   "url": "https://earthquake.usgs.gov/earthquakes/eventpage/ci41494168"
  },
  {
   "mag": 1.4,
   "place": "7 km NW of The Geysers, CA",
   "time": 1782279123710,
   "lon": -122.81616973877,
   "lat": 38.8141670227051,
   "depth": 2.47000002861023,
   "url": "https://earthquake.usgs.gov/earthquakes/eventpage/nc75382671"
  },
  {
   "mag": 1.4,
   "place": "4 km SE of Quilcene, Washington",
   "time": 1782270947940,
   "lon": -122.831166666667,
   "lat": 47.7905,
   "depth": 20.03,
   "url": "https://earthquake.usgs.gov/earthquakes/eventpage/uw714031091"
  },
  {
   "mag": 1.4,
   "place": "56 km WSW of Adak, Alaska",
   "time": 1782270457120,
   "lon": -177.327,
   "lat": 51.6053333333333,
   "depth": 8.9,
   "url": "https://earthquake.usgs.gov/earthquakes/eventpage/av94265948"
  },
  {
   "mag": 1.4,
   "place": "4 km WNW of Redway, CA",
   "time": 1782263314590,
   "lon": -123.861831665039,
   "lat": 40.1363334655762,
   "depth": 22.5699996948242,
   "url": "https://earthquake.usgs.gov/earthquakes/eventpage/nc75382536"
  },
  {
   "mag": 1.3,
   "place": "25 km ENE of West Yellowstone, Montana",
   "time": 1782335442970,
   "lon": -110.819166666667,
   "lat": 44.764,
   "depth": 4.94,
   "url": "https://earthquake.usgs.gov/earthquakes/eventpage/uu80143276"
  },
  {
   "mag": 1.3,
   "place": "13 km SE of Tehachapi, CA",
   "time": 1782325528890,
   "lon": -118.335,
   "lat": 35.0618333333333,
   "depth": -0.55,
   "url": "https://earthquake.usgs.gov/earthquakes/eventpage/ci41494560"
  },
  {
   "mag": 1.3,
   "place": "10 km NW of Redwood Valley, CA",
   "time": 1782323508820,
   "lon": -123.279502868652,
   "lat": 39.3308334350586,
   "depth": 4.55000019073486,
   "url": "https://earthquake.usgs.gov/earthquakes/eventpage/nc75383206"
  },
  {
   "mag": 1.3,
   "place": "7 km NW of The Geysers, CA",
   "time": 1782311776730,
   "lon": -122.806167602539,
   "lat": 38.8219985961914,
   "depth": 2.26999998092651,
   "url": "https://earthquake.usgs.gov/earthquakes/eventpage/nc75382906"
  },
  {
   "mag": 1.3,
   "place": "21 km ESE of Forsan, Texas",
   "time": 1782295757964,
   "lon": -101.143,
   "lat": 32.069,
   "depth": 8.3008,
   "url": "https://earthquake.usgs.gov/earthquakes/eventpage/tx2026mieoey"
  },
  {
   "mag": 1.3,
   "place": "28 km WSW of Olancha, CA",
   "time": 1782291870980,
   "lon": -118.278666666667,
   "lat": 36.1575,
   "depth": 7.94,
   "url": "https://earthquake.usgs.gov/earthquakes/eventpage/ci41494232"
  },
  {
   "mag": 1.3,
   "place": "12 km NW of Progreso, B.C., MX",
   "time": 1782289087160,
   "lon": -115.659166666667,
   "lat": 32.6631666666667,
   "depth": 10.52,
   "url": "https://earthquake.usgs.gov/earthquakes/eventpage/ci41494216"
  },
  {
   "mag": 1.3,
   "place": "14 km ENE of Hebgen Lake Estates, Montana",
   "time": 1782284093080,
   "lon": -111.0255,
   "lat": 44.8266666666667,
   "depth": 8.04,
   "url": "https://earthquake.usgs.gov/earthquakes/eventpage/uu80007553"
  },
  {
   "mag": 1.3,
   "place": "13 km WSW of Stanton, Texas",
   "time": 1782283684976,
   "lon": -101.928,
   "lat": 32.105,
   "depth": 8.3252,
   "url": "https://earthquake.usgs.gov/earthquakes/eventpage/tx2026mhxwul"
  },
  {
   "mag": 1.3,
   "place": "3 km ESE of The Geysers, CA",
   "time": 1782281065960,
   "lon": -122.726997375488,
   "lat": 38.7628326416016,
   "depth": 2.72000002861023,
   "url": "https://earthquake.usgs.gov/earthquakes/eventpage/nc75382731"
  },
  {
   "mag": 1.3,
   "place": "4 km SSW of Brawley, CA",
   "time": 1782277685310,
   "lon": -115.549166666667,
   "lat": 32.9511666666667,
   "depth": 9.82,
   "url": "https://earthquake.usgs.gov/earthquakes/eventpage/ci41494120"
  },
  {
   "mag": 1.3,
   "place": "16 km ENE of Ocotillo, CA",
   "time": 1782271444310,
   "lon": -115.832833333333,
   "lat": 32.7788333333333,
   "depth": 4.82,
   "url": "https://earthquake.usgs.gov/earthquakes/eventpage/ci41494064"
  },
  {
   "mag": 1.3,
   "place": "13 km WSW of Stanton, Texas",
   "time": 1782268078511,
   "lon": -101.924,
   "lat": 32.103,
   "depth": 7.6904,
   "url": "https://earthquake.usgs.gov/earthquakes/eventpage/tx2026mhpghw"
  },
  {
   "mag": 1.3,
   "place": "11 km NNE of Ocotillo Wells, CA",
   "time": 1782263061460,
   "lon": -116.079666666667,
   "lat": 33.2295,
   "depth": 10.11,
   "url": "https://earthquake.usgs.gov/earthquakes/eventpage/ci41494000"
  },
  {
   "mag": 1.2,
   "place": "9 km NW of Redwood Valley, CA",
   "time": 1782343403030,
   "lon": -123.26000213623,
   "lat": 39.3288345336914,
   "depth": 2.8199999332428,
   "url": "https://earthquake.usgs.gov/earthquakes/eventpage/nc75383596"
  },
  {
   "mag": 1.2,
   "place": "5 km SE of Home Gardens, CA",
   "time": 1782328631400,
   "lon": -117.488,
   "lat": 33.8463333333333,
   "depth": -0.45,
   "url": "https://earthquake.usgs.gov/earthquakes/eventpage/ci41494616"
  },
  {
   "mag": 1.2,
   "place": "22 km NW of Parkfield, CA",
   "time": 1782325701450,
   "lon": -120.610000610352,
   "lat": 36.0363349914551,
   "depth": 1.51999998092651,
   "url": "https://earthquake.usgs.gov/earthquakes/eventpage/nc75383286"
  },
  {
   "mag": 1.2,
   "place": "1 km ENE of The Geysers, CA",
   "time": 1782316679700,
   "lon": -122.744499206543,
   "lat": 38.7815017700195,
   "depth": 0.759999990463257,
   "url": "https://earthquake.usgs.gov/earthquakes/eventpage/nc75383046"
  },
  {
   "mag": 1.2,
   "place": "7 km NNW of Redwood Valley, CA",
   "time": 1782316363520,
   "lon": -123.244003295898,
   "lat": 39.3245010375977,
   "depth": 4.30000019073486,
   "url": "https://earthquake.usgs.gov/earthquakes/eventpage/nc75383036"
  },
  {
   "mag": 1.2,
   "place": "16 km NNW of Midland, Texas",
   "time": 1782313078383,
   "lon": -102.153,
   "lat": 32.129,
   "depth": 0.7423,
   "url": "https://earthquake.usgs.gov/earthquakes/eventpage/tx2026miocym"
  },
  {
   "mag": 1.2,
   "place": "5 km SW of Ridgemark, CA",
   "time": 1782301308600,
   "lon": -121.400329589844,
   "lat": 36.780834197998,
   "depth": 5.48999977111816,
   "url": "https://earthquake.usgs.gov/earthquakes/eventpage/nc75382831"
  },
  {
   "mag": 1.2,
   "place": "16 km W of Simmler, CA",
   "time": 1782294311470,
   "lon": -120.177833333333,
   "lat": 35.3543333333333,
   "depth": 6.81,
   "url": "https://earthquake.usgs.gov/earthquakes/eventpage/ci41494256"
  },
  {
   "mag": 1.2,
   "place": "11 km NNE of Ocotillo Wells, CA",
   "time": 1782276257530,
   "lon": -116.081166666667,
   "lat": 33.231,
   "depth": 9.84,
   "url": "https://earthquake.usgs.gov/earthquakes/eventpage/ci41494104"
  },
  {
   "mag": 1.2,
   "place": "9 km NW of The Geysers, CA",
   "time": 1782264896840,
   "lon": -122.835998535156,
   "lat": 38.8356666564941,
   "depth": 1.87000000476837,
   "url": "https://earthquake.usgs.gov/earthquakes/eventpage/nc75382541"
  },
  {
   "mag": 1.2,
   "place": "11 km NNE of Ocotillo Wells, CA",
   "time": 1782263079340,
   "lon": -116.081666666667,
   "lat": 33.2321666666667,
   "depth": 7.33,
   "url": "https://earthquake.usgs.gov/earthquakes/eventpage/ci10245142"
  },
  {
   "mag": 1.1,
   "place": "9 km NNW of Redwood Valley, CA",
   "time": 1782338033850,
   "lon": -123.251335144043,
   "lat": 39.336498260498,
   "depth": 7.65000009536743,
   "url": "https://earthquake.usgs.gov/earthquakes/eventpage/nc75383541"
  },
  {
   "mag": 1.1,
   "place": "4 km E of Lewisville, Washington",
   "time": 1782337881940,
   "lon": -122.464833333333,
   "lat": 45.8068333333333,
   "depth": -0.58,
   "url": "https://earthquake.usgs.gov/earthquakes/eventpage/uw714031721"
  },
  {
   "mag": 1.1,
   "place": "7 km S of Mojave, CA",
   "time": 1782327646320,
   "lon": -118.186833333333,
   "lat": 34.9916666666667,
   "depth": -0.9,
   "url": "https://earthquake.usgs.gov/earthquakes/eventpage/ci41494608"
  },
  {
   "mag": 1.1,
   "place": "5 km SW of Salton City, CA",
   "time": 1782326700330,
   "lon": -115.999333333333,
   "lat": 33.2696666666667,
   "depth": 2.7,
   "url": "https://earthquake.usgs.gov/earthquakes/eventpage/ci41494600"
  },
  {
   "mag": 1.1,
   "place": "42 km NNE of Chenega, Alaska",
   "time": 1782324074634,
   "lon": -147.824,
   "lat": 60.44,
   "depth": 32.4,
   "url": "https://earthquake.usgs.gov/earthquakes/eventpage/aka2026mktwkd"
  },
  {
   "mag": 1.1,
   "place": "57 km WSW of Anchor Point, Alaska",
   "time": 1782318086933,
   "lon": -152.821,
   "lat": 59.632,
   "depth": 82.3,
   "url": "https://earthquake.usgs.gov/earthquakes/eventpage/aka2026mkqnri"
  },
  {
   "mag": 1.1,
   "place": "4 km W of Cobb, CA",
   "time": 1782314204880,
   "lon": -122.764663696289,
   "lat": 38.8248329162598,
   "depth": 1.92999994754791,
   "url": "https://earthquake.usgs.gov/earthquakes/eventpage/nc75382941"
  },
  {
   "mag": 1.1,
   "place": "45 km WSW of Tatitlek, Alaska",
   "time": 1782308022691,
   "lon": -147.449,
   "lat": 60.704,
   "depth": 12,
   "url": "https://earthquake.usgs.gov/earthquakes/eventpage/aka2026mkkykv"
  },
  {
   "mag": 1.1,
   "place": "7 km NNW of Julian, CA",
   "time": 1782302794270,
   "lon": -116.641833333333,
   "lat": 33.136,
   "depth": 3.83,
   "url": "https://earthquake.usgs.gov/earthquakes/eventpage/ci41494288"
  },
  {
   "mag": 1.1,
   "place": "3 km WSW of Cobb, CA",
   "time": 1782300268180,
   "lon": -122.761665344238,
   "lat": 38.8136672973633,
   "depth": 1.79999995231628,
   "url": "https://earthquake.usgs.gov/earthquakes/eventpage/nc75382826"
  },
  {
   "mag": 1.1,
   "place": "8 km NW of The Geysers, CA",
   "time": 1782298120190,
   "lon": -122.818336486816,
   "lat": 38.8301658630371,
   "depth": 1.42999994754791,
   "url": "https://earthquake.usgs.gov/earthquakes/eventpage/nc75382816"
  },
  {
   "mag": 1.1,
   "place": "83 km NNW of Karluk, Alaska",
   "time": 1782282502063,
   "lon": -154.877,
   "lat": 58.284,
   "depth": 12.5,
   "url": "https://earthquake.usgs.gov/earthquakes/eventpage/aka2026mjwtqk"
  },
  {
   "mag": 1.1,
   "place": "24 km NW of Toyah, Texas",
   "time": 1782279502587,
   "lon": -103.988,
   "lat": 31.461,
   "depth": 3.3826,
   "url": "https://earthquake.usgs.gov/earthquakes/eventpage/tx2026mhvota"
  },
  {
   "mag": 1.1,
   "place": "64 km W of Nikolski, Alaska",
   "time": 1782274454460,
   "lon": -169.814333333333,
   "lat": 52.8553333333333,
   "depth": -0.35,
   "url": "https://earthquake.usgs.gov/earthquakes/eventpage/av94266108"
  },
  {
   "mag": 1.1,
   "place": "3 km WSW of Cobb, CA",
   "time": 1782270551020,
   "lon": -122.762001037598,
   "lat": 38.8160018920898,
   "depth": 1.87999999523163,
   "url": "https://earthquake.usgs.gov/earthquakes/eventpage/nc75382601"
  },
  {
   "mag": 1.1,
   "place": "4 km NW of The Geysers, CA",
   "time": 1782269127170,
   "lon": -122.78150177002,
   "lat": 38.8058319091797,
   "depth": 3.22000002861023,
   "url": "https://earthquake.usgs.gov/earthquakes/eventpage/nc75382576"
  },
  {
   "mag": 1.0,
   "place": "6 km WNW of Cobb, CA",
   "time": 1782342180060,
   "lon": -122.791999816895,
   "lat": 38.8351669311523,
   "depth": 2.17000007629395,
   "url": "https://earthquake.usgs.gov/earthquakes/eventpage/nc75383586"
  },
  {
   "mag": 1.0,
   "place": "6 km WNW of The Geysers, CA",
   "time": 1782331915380,
   "lon": -122.812835693359,
   "lat": 38.8056678771973,
   "depth": 21.6800003051758,
   "url": "https://earthquake.usgs.gov/earthquakes/eventpage/nc75383431"
  },
  {
   "mag": 1.0,
   "place": "9 km NNW of Redwood Valley, CA",
   "time": 1782317528210,
   "lon": -123.23999786377,
   "lat": 39.3400001525879,
   "depth": 3.13000011444092,
   "url": "https://earthquake.usgs.gov/earthquakes/eventpage/nc75383071"
  },
  {
   "mag": 1.0,
   "place": "3 km NW of The Geysers, CA",
   "time": 1782315816790,
   "lon": -122.780166625977,
   "lat": 38.8013343811035,
   "depth": 3.22000002861023,
   "url": "https://earthquake.usgs.gov/earthquakes/eventpage/nc75383006"
  },
  {
   "mag": 1.0,
   "place": "7 km NW of The Geysers, CA",
   "time": 1782311938060,
   "lon": -122.804496765137,
   "lat": 38.8250007629395,
   "depth": 2.50999999046326,
   "url": "https://earthquake.usgs.gov/earthquakes/eventpage/nc75382911"
  },
  {
   "mag": 1,
   "place": "4 km SSW of The Geysers, CA",
   "time": 1782297171930,
   "lon": -122.776832580566,
   "lat": 38.7495002746582,
   "depth": 21.7900009155273,
   "url": "https://earthquake.usgs.gov/earthquakes/eventpage/nc75382806"
  },
  {
   "mag": 1.0,
   "place": "7 km NNW of Mira Loma, CA",
   "time": 1782293997370,
   "lon": -117.5525,
   "lat": 34.044,
   "depth": 10.89,
   "url": "https://earthquake.usgs.gov/earthquakes/eventpage/ci41494248"
  },
  {
   "mag": 1.0,
   "place": "3 km SSW of Fern Forest, Hawaii",
   "time": 1782276260330,
   "lon": -155.1415,
   "lat": 19.4386666666667,
   "depth": 0.01,
   "url": "https://earthquake.usgs.gov/earthquakes/eventpage/hv74989737"
  },
  {
   "mag": 1.0,
   "place": "14 km SSW of Olancha, CA",
   "time": 1782275471470,
   "lon": -118.069166666667,
   "lat": 36.1681666666667,
   "depth": 3.42,
   "url": "https://earthquake.usgs.gov/earthquakes/eventpage/ci41494096"
  },
  {
   "mag": 1.0,
   "place": "10 km NNE of Ocotillo Wells, CA",
   "time": 1782274070790,
   "lon": -116.084,
   "lat": 33.2286666666667,
   "depth": 8.87,
   "url": "https://earthquake.usgs.gov/earthquakes/eventpage/ci41494088"
  },
  {
   "mag": 1.0,
   "place": "1 km E of The Geysers, CA",
   "time": 1782272366950,
   "lon": -122.745162963867,
   "lat": 38.7771682739258,
   "depth": 1.77999997138977,
   "url": "https://earthquake.usgs.gov/earthquakes/eventpage/nc75382611"
  },
  {
   "mag": 1.0,
   "place": "61 km ESE of West Yellowstone, Montana",
   "time": 1782269276800,
   "lon": -110.455833333333,
   "lat": 44.362,
   "depth": 8.89,
   "url": "https://earthquake.usgs.gov/earthquakes/eventpage/uu80143181"
  },
  {
   "mag": 1.0,
   "place": "7 km NE of Westmorland, CA",
   "time": 1782269133820,
   "lon": -115.578166666667,
   "lat": 33.0853333333333,
   "depth": 11.1,
   "url": "https://earthquake.usgs.gov/earthquakes/eventpage/ci41494056"
  },
  {
   "mag": 0.9,
   "place": "84 km W of Karluk, Alaska",
   "time": 1782331686156,
   "lon": -155.852,
   "lat": 57.481,
   "depth": 82.7,
   "url": "https://earthquake.usgs.gov/earthquakes/eventpage/aka2026mkycjy"
  },
  {
   "mag": 0.9,
   "place": "8 km SSE of Redlands, CA",
   "time": 1782322794540,
   "lon": -117.153666666667,
   "lat": 33.9866666666667,
   "depth": 14.76,
   "url": "https://earthquake.usgs.gov/earthquakes/eventpage/ci41494472"
  },
  {
   "mag": 0.9,
   "place": "14 km ENE of Indio, CA",
   "time": 1782316057940,
   "lon": -116.0805,
   "lat": 33.786,
   "depth": 2.1,
   "url": "https://earthquake.usgs.gov/earthquakes/eventpage/ci41494408"
  },
  {
   "mag": 0.9,
   "place": "24 km SE of Mammoth, Wyoming",
   "time": 1782312024100,
   "lon": -110.487166666667,
   "lat": 44.8163333333333,
   "depth": 6.64,
   "url": "https://earthquake.usgs.gov/earthquakes/eventpage/uu80143226"
  },
  {
   "mag": 0.9,
   "place": "16 km NNE of Perryville, Alaska",
   "time": 1782302247665,
   "lon": -159.05,
   "lat": 56.053,
   "depth": 82.9,
   "url": "https://earthquake.usgs.gov/earthquakes/eventpage/aka2026mkhsze"
  },
  {
   "mag": 0.9,
   "place": "15 km ENE of Hebgen Lake Estates, Montana",
   "time": 1782296740560,
   "lon": -111.018,
   "lat": 44.8343333333333,
   "depth": 8.69,
   "url": "https://earthquake.usgs.gov/earthquakes/eventpage/uu80143221"
  },
  {
   "mag": 0.9,
   "place": "6 km W of Cobb, CA",
   "time": 1782288386090,
   "lon": -122.795166015625,
   "lat": 38.8248329162598,
   "depth": 2.61999988555908,
   "url": "https://earthquake.usgs.gov/earthquakes/eventpage/nc75382751"
  },
  {
   "mag": 0.9,
   "place": "13 km WSW of Lake Hughes, CA",
   "time": 1782286368450,
   "lon": -118.579666666667,
   "lat": 34.6368333333333,
   "depth": 9.89,
   "url": "https://earthquake.usgs.gov/earthquakes/eventpage/ci41494192"
  },
  {
   "mag": 0.9,
   "place": "14 km ENE of Hebgen Lake Estates, Montana",
   "time": 1782282931360,
   "lon": -111.018833333333,
   "lat": 44.8228333333333,
   "depth": 8.2,
   "url": "https://earthquake.usgs.gov/earthquakes/eventpage/uu80143196"
  },
  {
   "mag": 0.9,
   "place": "6 km WSW of The Geysers, CA",
   "time": 1782280743670,
   "lon": -122.826332092285,
   "lat": 38.7648315429688,
   "depth": 13.4099998474121,
   "url": "https://earthquake.usgs.gov/earthquakes/eventpage/nc75382721"
  },
  {
   "mag": 0.9,
   "place": "4 km W of Cobb, CA",
   "time": 1782280223040,
   "lon": -122.775001525879,
   "lat": 38.8224983215332,
   "depth": 5.15000009536743,
   "url": "https://earthquake.usgs.gov/earthquakes/eventpage/nc75382701"
  },
  {
   "mag": 0.9,
   "place": "60 km ESE of West Yellowstone, Montana",
   "time": 1782267577430,
   "lon": -110.4625,
   "lat": 44.3668333333333,
   "depth": 8.84,
   "url": "https://earthquake.usgs.gov/earthquakes/eventpage/uu80143176"
  },
  {
   "mag": 0.9,
   "place": "5 km WNW of The Geysers, CA",
   "time": 1782267521740,
   "lon": -122.807998657227,
   "lat": 38.7898330688477,
   "depth": 3.67000007629395,
   "url": "https://earthquake.usgs.gov/earthquakes/eventpage/nc75382556"
  },
  {
   "mag": 0.9,
   "place": "61 km ESE of West Yellowstone, Montana",
   "time": 1782266407950,
   "lon": -110.451,
   "lat": 44.366,
   "depth": 7.98,
   "url": "https://earthquake.usgs.gov/earthquakes/eventpage/uu80143166"
  },
  {
   "mag": 0.9,
   "place": "13 km WSW of Stanton, Texas",
   "time": 1782261891423,
   "lon": -101.926,
   "lat": 32.101,
   "depth": 8.8135,
   "url": "https://earthquake.usgs.gov/earthquakes/eventpage/tx2026mhlvpn"
  },
  {
   "mag": 0.8,
   "place": "16 km NE of Little Lake, CA",
   "time": 1782325733060,
   "lon": -117.772833333333,
   "lat": 36.0266666666667,
   "depth": 1.54,
   "url": "https://earthquake.usgs.gov/earthquakes/eventpage/ci41494592"
  },
  {
   "mag": 0.8,
   "place": "84 km NNW of Karluk, Alaska",
   "time": 1782322415206,
   "lon": -154.975,
   "lat": 58.274,
   "depth": 5,
   "url": "https://earthquake.usgs.gov/earthquakes/eventpage/aka2026mksykp"
  },
  {
   "mag": 0.8,
   "place": "10 km S of Idyllwild, CA",
   "time": 1782322019420,
   "lon": -116.707333333333,
   "lat": 33.647,
   "depth": 15.13,
   "url": "https://earthquake.usgs.gov/earthquakes/eventpage/ci41494456"
  },
  {
   "mag": 0.8,
   "place": "4 km NW of The Geysers, CA",
   "time": 1782317101260,
   "lon": -122.792831420898,
   "lat": 38.8040008544922,
   "depth": 3.64000010490417,
   "url": "https://earthquake.usgs.gov/earthquakes/eventpage/nc75383056"
  },
  {
   "mag": 0.8,
   "place": "15 km N of Warner Springs, CA",
   "time": 1782315901860,
   "lon": -116.622833333333,
   "lat": 33.421,
   "depth": 7.96,
   "url": "https://earthquake.usgs.gov/earthquakes/eventpage/ci41494400"
  },
  {
   "mag": 0.8,
   "place": "21 km E of Little Lake, CA",
   "time": 1782313306100,
   "lon": -117.678666666667,
   "lat": 35.95,
   "depth": 5.09,
   "url": "https://earthquake.usgs.gov/earthquakes/eventpage/ci41494368"
  },
  {
   "mag": 0.8,
   "place": "14 km WSW of Stanton, Texas",
   "time": 1782283737133,
   "lon": -101.934,
   "lat": 32.097,
   "depth": 7.2754,
   "url": "https://earthquake.usgs.gov/earthquakes/eventpage/tx2026mhxvfa"
  },
  {
   "mag": 0.8,
   "place": "2 km NNE of Colton, CA",
   "time": 1782259476470,
   "lon": -117.306333333333,
   "lat": 34.086,
   "depth": 13.85,
   "url": "https://earthquake.usgs.gov/earthquakes/eventpage/ci41493976"
  },
  {
   "mag": 0.8,
   "place": "13 km W of Stanton, Texas",
   "time": 1782258934324,
   "lon": -101.931,
   "lat": 32.11,
   "depth": 8.5693,
   "url": "https://earthquake.usgs.gov/earthquakes/eventpage/tx2026mhkfig"
  },
  {
   "mag": 0.7,
   "place": "11 km NE of Julian, CA",
   "time": 1782329619420,
   "lon": -116.526166666667,
   "lat": 33.1503333333333,
   "depth": 6.35,
   "url": "https://earthquake.usgs.gov/earthquakes/eventpage/ci41494656"
  },
  {
   "mag": 0.7,
   "place": "5 km S of Idyllwild, CA",
   "time": 1782328704240,
   "lon": -116.716166666667,
   "lat": 33.694,
   "depth": 16.9,
   "url": "https://earthquake.usgs.gov/earthquakes/eventpage/ci41494624"
  },
  {
   "mag": 0.7,
   "place": "6 km WNW of Cobb, CA",
   "time": 1782325643500,
   "lon": -122.794502258301,
   "lat": 38.8370018005371,
   "depth": 1.41999995708466,
   "url": "https://earthquake.usgs.gov/earthquakes/eventpage/nc75383281"
  },
  {
   "mag": 0.7,
   "place": "2 km WNW of Anderson Springs, CA",
   "time": 1782325215440,
   "lon": -122.71216583252,
   "lat": 38.7786674499512,
   "depth": 0.25,
   "url": "https://earthquake.usgs.gov/earthquakes/eventpage/nc75383261"
  },
  {
   "mag": 0.7,
   "place": "7 km WNW of Cobb, CA",
   "time": 1782319765260,
   "lon": -122.797668457031,
   "lat": 38.8373336791992,
   "depth": 2.1800000667572,
   "url": "https://earthquake.usgs.gov/earthquakes/eventpage/nc75383146"
  },
  {
   "mag": 0.7,
   "place": "6 km NW of The Geysers, CA",
   "time": 1782313267920,
   "lon": -122.807830810547,
   "lat": 38.8153343200684,
   "depth": -0.610000014305115,
   "url": "https://earthquake.usgs.gov/earthquakes/eventpage/nc75382916"
  },
  {
   "mag": 0.7,
   "place": "2 km N of The Geysers, CA",
   "time": 1782293367340,
   "lon": -122.753997802734,
   "lat": 38.7956657409668,
   "depth": 1.27999997138977,
   "url": "https://earthquake.usgs.gov/earthquakes/eventpage/nc75382781"
  },
  {
   "mag": 0.7,
   "place": "5 km NNW of Running Springs, CA",
   "time": 1782286990630,
   "lon": -117.128,
   "lat": 34.2473333333333,
   "depth": 2.24,
   "url": "https://earthquake.usgs.gov/earthquakes/eventpage/ci41494208"
  },
  {
   "mag": 0.7,
   "place": "3 km E of Moreno Valley, CA",
   "time": 1782286796300,
   "lon": -117.197,
   "lat": 33.9311666666667,
   "depth": 13.96,
   "url": "https://earthquake.usgs.gov/earthquakes/eventpage/ci41494200"
  },
  {
   "mag": 0.7,
   "place": "11 km WSW of Salton City, CA",
   "time": 1782281367970,
   "lon": -116.054833333333,
   "lat": 33.2508333333333,
   "depth": 3.38,
   "url": "https://earthquake.usgs.gov/earthquakes/eventpage/ci41494160"
  },
  {
   "mag": 0.7,
   "place": "162 km W of Adak, Alaska",
   "time": 1782280350680,
   "lon": -178.984166666667,
   "lat": 51.7686666666667,
   "depth": 14.83,
   "url": "https://earthquake.usgs.gov/earthquakes/eventpage/av94266293"
  },
  {
   "mag": 0.7,
   "place": "25 km SE of Malaga, New Mexico",
   "time": 1782278525253,
   "lon": -103.909,
   "lat": 32.046,
   "depth": 7.3303,
   "url": "https://earthquake.usgs.gov/earthquakes/eventpage/tx2026mhvari"
  },
  {
   "mag": 0.7,
   "place": "13 km ENE of Cloverdale, CA",
   "time": 1782278195540,
   "lon": -122.87816619873,
   "lat": 38.8411674499512,
   "depth": 2.3199999332428,
   "url": "https://earthquake.usgs.gov/earthquakes/eventpage/nc75382656"
  },
  {
   "mag": 0.7,
   "place": "11 km NNE of Ocotillo Wells, CA",
   "time": 1782273178280,
   "lon": -116.078166666667,
   "lat": 33.2318333333333,
   "depth": 9.75,
   "url": "https://earthquake.usgs.gov/earthquakes/eventpage/ci41494080"
  },
  {
   "mag": 0.7,
   "place": "10 km WNW of The Geysers, CA",
   "time": 1782270171390,
   "lon": -122.854667663574,
   "lat": 38.8216667175293,
   "depth": 2.42000007629395,
   "url": "https://earthquake.usgs.gov/earthquakes/eventpage/nc75382596"
  },
  {
   "mag": 0.7,
   "place": "8 km W of Cobb, CA",
   "time": 1782268562210,
   "lon": -122.809829711914,
   "lat": 38.832332611084,
   "depth": 1.91999995708466,
   "url": "https://earthquake.usgs.gov/earthquakes/eventpage/nc75382571"
  },
  {
   "mag": 0.7,
   "place": "61 km ESE of West Yellowstone, Montana",
   "time": 1782267183060,
   "lon": -110.457333333333,
   "lat": 44.3656666666667,
   "depth": 8.23,
   "url": "https://earthquake.usgs.gov/earthquakes/eventpage/uu80143171"
  },
  {
   "mag": 0.7,
   "place": "11 km NNE of Ocotillo Wells, CA",
   "time": 1782262652060,
   "lon": -116.081,
   "lat": 33.232,
   "depth": 9.18,
   "url": "https://earthquake.usgs.gov/earthquakes/eventpage/ci41493992"
  },
  {
   "mag": 0.7,
   "place": "26 km SE of Mammoth, Wyoming",
   "time": 1782259579740,
   "lon": -110.506,
   "lat": 44.7858333333333,
   "depth": 4.32,
   "url": "https://earthquake.usgs.gov/earthquakes/eventpage/uu80143156"
  },
  {
   "mag": 0.6,
   "place": "5 km WSW of Anza, CA",
   "time": 1782321086870,
   "lon": -116.724333333333,
   "lat": 33.534,
   "depth": 5.3,
   "url": "https://earthquake.usgs.gov/earthquakes/eventpage/ci41494432"
  },
  {
   "mag": 0.6,
   "place": "10 km NE of Hoodsport, Washington",
   "time": 1782320690350,
   "lon": -123.024166666667,
   "lat": 47.4586666666667,
   "depth": 14.43,
   "url": "https://earthquake.usgs.gov/earthquakes/eventpage/uw714031441"
  },
  {
   "mag": 0.6,
   "place": "11 km WNW of Cobb, CA",
   "time": 1782306137750,
   "lon": -122.845336914062,
   "lat": 38.8513336181641,
   "depth": 1.75,
   "url": "https://earthquake.usgs.gov/earthquakes/eventpage/nc75382876"
  },
  {
   "mag": 0.6,
   "place": "4 km W of Cobb, CA",
   "time": 1782302355590,
   "lon": -122.764167785645,
   "lat": 38.8231658935547,
   "depth": 2.19000005722046,
   "url": "https://earthquake.usgs.gov/earthquakes/eventpage/nc75382851"
  },
  {
   "mag": 0.6,
   "place": "4 km NW of Anza, CA",
   "time": 1782298162700,
   "lon": -116.700833333333,
   "lat": 33.5776666666667,
   "depth": 15.49,
   "url": "https://earthquake.usgs.gov/earthquakes/eventpage/ci41494280"
  },
  {
   "mag": 0.6,
   "place": "10 km ENE of Ocotillo Wells, CA",
   "time": 1782279356550,
   "lon": -116.030333333333,
   "lat": 33.18,
   "depth": 5.13,
   "url": "https://earthquake.usgs.gov/earthquakes/eventpage/ci41494144"
  },
  {
   "mag": 0.6,
   "place": "10 km W of Corona, CA",
   "time": 1782265509770,
   "lon": -117.677333333333,
   "lat": 33.8576666666667,
   "depth": 7.73,
   "url": "https://earthquake.usgs.gov/earthquakes/eventpage/ci41494032"
  },
  {
   "mag": 0.6,
   "place": "12 km WSW of Stanton, Texas",
   "time": 1782264209369,
   "lon": -101.916,
   "lat": 32.105,
   "depth": 8.8135,
   "url": "https://earthquake.usgs.gov/earthquakes/eventpage/tx2026mhndcb"
  },
  {
   "mag": 0.5,
   "place": "15 km ENE of Indio, CA",
   "time": 1782313928220,
   "lon": -116.0795,
   "lat": 33.7895,
   "depth": 2.59,
   "url": "https://earthquake.usgs.gov/earthquakes/eventpage/ci10245150"
  },
  {
   "mag": 0.5,
   "place": "7 km NNW of Julian, CA",
   "time": 1782303267350,
   "lon": -116.637833333333,
   "lat": 33.1361666666667,
   "depth": 4.43,
   "url": "https://earthquake.usgs.gov/earthquakes/eventpage/ci41494296"
  },
  {
   "mag": 0.5,
   "place": "15 km ENE of Hebgen Lake Estates, Montana",
   "time": 1782295106490,
   "lon": -111.017833333333,
   "lat": 44.8345,
   "depth": 8.41,
   "url": "https://earthquake.usgs.gov/earthquakes/eventpage/uu80143216"
  },
  {
   "mag": 0.5,
   "place": "19 km SW of Ocotillo Wells, CA",
   "time": 1782291386290,
   "lon": -116.292166666667,
   "lat": 33.0313333333333,
   "depth": 6.53,
   "url": "https://earthquake.usgs.gov/earthquakes/eventpage/ci41494224"
  },
  {
   "mag": 0.5,
   "place": "146 km W of Adak, Alaska",
   "time": 1782281939630,
   "lon": -178.753,
   "lat": 51.8246666666667,
   "depth": 15.13,
   "url": "https://earthquake.usgs.gov/earthquakes/eventpage/av94266343"
  },
  {
   "mag": 0.5,
   "place": "1 km ENE of Coso Junction, CA",
   "time": 1782279441300,
   "lon": -117.941833333333,
   "lat": 36.0473333333333,
   "depth": 2.72,
   "url": "https://earthquake.usgs.gov/earthquakes/eventpage/ci41494152"
  },
  {
   "mag": 0.5,
   "place": "Rat Islands, Aleutian Islands, Alaska",
   "time": 1782260130440,
   "lon": 178.439333333333,
   "lat": 51.9911666666667,
   "depth": 3.4,
   "url": "https://earthquake.usgs.gov/earthquakes/eventpage/av94265608"
  },
  {
   "mag": 0.4,
   "place": "86 km NNW of Karluk, Alaska",
   "time": 1782324905667,
   "lon": -154.967,
   "lat": 58.296,
   "depth": 5,
   "url": "https://earthquake.usgs.gov/earthquakes/eventpage/aka2026mkuikp"
  },
  {
   "mag": 0.4,
   "place": "23 km ENE of Ashford, Washington",
   "time": 1782305576940,
   "lon": -121.759166666667,
   "lat": 46.8533333333333,
   "depth": 1.14,
   "url": "https://earthquake.usgs.gov/earthquakes/eventpage/uw714031221"
  },
  {
   "mag": 0.4,
   "place": "10 km NNE of Snoqualmie, Washington",
   "time": 1782298273670,
   "lon": -121.7675,
   "lat": 47.615,
   "depth": 14.22,
   "url": "https://earthquake.usgs.gov/earthquakes/eventpage/uw714031201"
  },
  {
   "mag": 0.4,
   "place": "61 km WNW of Beluga, Alaska",
   "time": 1782270729930,
   "lon": -152.0795,
   "lat": 61.4223333333333,
   "depth": 9.39,
   "url": "https://earthquake.usgs.gov/earthquakes/eventpage/av94265963"
  }
 ]
}