{
 "updated": "2026-07-13T10:44:10.992248+00:00",
 "terms": [
  {
   "term": "iran",
   "count": 16
  },
  {
   "term": "strikes",
   "count": 11
  },
  {
   "term": "china",
   "count": 11
  },
  {
   "term": "attacks",
   "count": 7
  },
  {
   "term": "world",
   "count": 6
  },
  {
   "term": "sponsored",
   "count": 6
  },
  {
   "term": "content",
   "count": 6
  },
  {
   "term": "yankee",
   "count": 5
  },
  {
   "term": "stadium",
   "count": 5
  },
  {
   "term": "white",
   "count": 5
  },
  {
   "term": "years",
   "count": 5
  },
  {
   "term": "indonesia",
   "count": 5
  },
  {
   "term": "neill",
   "count": 5
  },
  {
   "term": "green",
   "count": 5
  },
  {
   "term": "band",
   "count": 4
  },
  {
   "term": "story",
   "count": 4
  },
  {
   "term": "concert",
   "count": 4
  },
  {
   "term": "record",
   "count": 4
  },
  {
   "term": "people",
   "count": 4
  },
  {
   "term": "tour",
   "count": 4
  },
  {
   "term": "2026",
   "count": 4
  },
  {
   "term": "anniversary",
   "count": 4
  },
  {
   "term": "industry",
   "count": 4
  },
  {
   "term": "year",
   "count": 4
  },
  {
   "term": "east",
   "count": 4
  },
  {
   "term": "south",
   "count": 4
  },
  {
   "term": "paris",
   "count": 4
  },
  {
   "term": "launches",
   "count": 4
  },
  {
   "term": "graham",
   "count": 4
  },
  {
   "term": "police",
   "count": 4
  }
 ],
 "entities": [
  {
   "name": "Iran",
   "count": 15
  },
  {
   "name": "China",
   "count": 10
  },
  {
   "name": "Sponsored Content",
   "count": 6
  },
  {
   "name": "Indonesia",
   "count": 5
  },
  {
   "name": "Sam Neill",
   "count": 5
  },
  {
   "name": "Green",
   "count": 5
  },
  {
   "name": "Paris",
   "count": 4
  },
  {
   "name": "Texas",
   "count": 4
  },
  {
   "name": "Setlist",
   "count": 3
  },
  {
   "name": "Europe",
   "count": 3
  },
  {
   "name": "Bahrain",
   "count": 3
  },
  {
   "name": "Kuwait",
   "count": 3
  },
  {
   "name": "Middle East",
   "count": 3
  },
  {
   "name": "Lindsey Graham",
   "count": 3
  },
  {
   "name": "France",
   "count": 3
  },
  {
   "name": "Panamá",
   "count": 3
  },
  {
   "name": "Hormuz",
   "count": 3
  },
  {
   "name": "Israel",
   "count": 3
  },
  {
   "name": "Hong Kong",
   "count": 3
  },
  {
   "name": "People",
   "count": 2
  },
  {
   "name": "Yankee Stadium",
   "count": 2
  },
  {
   "name": "Trump",
   "count": 2
  },
  {
   "name": "Ask HN",
   "count": 2
  },
  {
   "name": "Germany",
   "count": 2
  }
 ]
}