{
 "updated": "2026-07-03T10:12:52.881144+00:00",
 "place": "Ciudad de Panamá",
 "current": {
  "temp": 26,
  "feels": 31,
  "humidity": 97,
  "wind": 12,
  "code": 3,
  "is_day": 0
 },
 "daily": [
  {
   "date": "2026-07-03",
   "code": 95,
   "tmax": 29,
   "tmin": 25,
   "pop": 95
  },
  {
   "date": "2026-07-04",
   "code": 95,
   "tmax": 29,
   "tmin": 24,
   "pop": 90
  },
  {
   "date": "2026-07-05",
   "code": 95,
   "tmax": 31,
   "tmin": 25,
   "pop": 78
  },
  {
   "date": "2026-07-06",
   "code": 51,
   "tmax": 31,
   "tmin": 25,
   "pop": 96
  }
 ]
}